Workbook

Sheet FRONT
D6: IE Docket
B12: Style | E12: =+OB!C2 -> S2554MESS651WV
B13: Brand | E13: =+OB!E2 -> ADIDAS
B14: Target | E14: =+OB!K3 -> 850

Sheet COVER SHEET
B2: STARTUP PACKAGE
J3: M/P
C4: STYLE NO: | E4: =+OB!C2 -> S2554MESS651WV | G4: LINE : | J4: SEW | K4: =+OB!K76+OB!L74 -> 46.25
C5: TARGET: | E5: =+OB!K3 -> 850 | G5: UNIT: | J5: FIN | K5: =+OB!K84+OB!L84 -> 4
J6: OTH | K6: =+OB!C91+OB!C92+OB!C93 -> 4
J7: TOTAL | K7: =SUM(K4:K6) -> 54.25
C9: 1 | D9: OPERATION BREAK DOWN SEWING + FINISHING
C10: 2 | D10: BIHOURY REPORT
C11: 3 | D11: START UP DRIVE
C12: 4 | D12: TECHNICAL START UP
C13: 5 | D13: MACHINE LAYOUT
C14: 6 | D14: MACHINE REQUIREMENT PLAN
E15: PLAN INPUT : | H15: =OB!I90 -> 45955
E17: =OB!M3 -> NAZIR | J17: =OB!M4 -> SHANAKA
D18: P.M | E18: SUP | J18: IE

Sheet OB
B2: STYLE # | C2: S2554MESS651WV | E2: ADIDAS | H2: WORK MIN | I2: 600 | J2: WORK MIN | K2: 600 | L2: Date | M2: 45952
B3: TTL SMV | C3: =C85 -> 34.2 | D3: 100% Budget | E3: =+K3*C3/K2 -> 48.45 | F3: REVENUE | G3: =IF(E5="",(K3*C3*0.1),(K3*E5)) -> 2584 | H3: B/TARGET | I3: 850 | J3: L/TARGET | K3: =+I3*K4 -> 850 | L3: SUPERVISOR | M3: NAZIR
B4: OPERATOR | C4: =C89 -> 50.25 | D4: Variation | E4: =+C4-E3 -> 1.8 | F4: LINE COST | G4: =+C94*55 -> 2983.75 | H4: CATEGORY | I4: PANT | J4: EFFICIENCY | K4: 1 | L4: IE | M4: SHANAKA
B5: HELPER | C5: =C90 -> 0 | D5: CM | E5: 3.04 | F5: PROFIT/LOSS | G5: =+G3-G4 -> -399.75 | H5: B/ PCS/HEAD | I5: =+I3/(C4+C5) -> 16.915423 | J5: L/PCS/HEAD | K5: =+K3/(C4+C5) -> 16.915423
A7: SL | B7: OPERATION | C7: TIME IN | D7: TIME IN | E7: TGT/HR | F7: PLAN | G7: MACHINE | H7: WORK AIDS | I7: REQ MP | J7: ALLOTED | K7: ALLOTED | L7: ALLOTED | M7: REMARKS
C8: MIN | D8: SEC | F8: TGT/HR | H8: FOLDER/ ATTACHMENT | I8: (CAL) | J8: WP | K8: DIRECT | L8: INDIRECT
A9: BACK
A10: 1 | B10: ATTACH THREE STRIPE | C10: 0.9 | D10: =60*C10 -> 54 | E10: =IFERROR(60/C10,"") -> 66.666667 | F10: =+$K$3/($K$2/60) -> 85 | G10: KANSAI | I10: =IF(C10="","",($I$3/($I$2/60)*C10/60)) -> 1.275 | J10: =IFERROR(IF(I10<(MROUND(I10,1)+0.125),(MROUND(I10,1)),(CEILING(I10,1))),"") -> 2 | K10: =IFERROR(MROUND(I10,0.25),"") -> 1.25
A11: =+A10+1 -> 2 | B11: CHECK & TRIM THREE STRIPE | C11: 0.45 | D11: =60*C11 -> 27 | E11: =IFERROR(60/C11,"") -> 133.33333 | F11: =+$K$3/($K$2/60) -> 85 | G11: TABLE | I11: =IF(C11="","",($I$3/($I$2/60)*C11/60)) -> 0.6375 | J11: =IFERROR(IF(I11<(MROUND(I11,1)+0.125),(MROUND(I11,1)),(CEILING(I11,1))),"") -> 1 | K11: =IFERROR(MROUND(I11,0.25),"") -> 0.75
A12: =+A11+1 -> 3 | B12: JOIN BACK RISE | C12: 0.35 | D12: =60*C12 -> 21 | E12: =IFERROR(60/C12,"") -> 171.42857 | F12: =+$K$3/($K$2/60) -> 85 | G12: OL4T | I12: =IF(C12="","",($I$3/($I$2/60)*C12/60)) -> 0.49583333 | J12: =IFERROR(IF(I12<(MROUND(I12,1)+0.125),(MROUND(I12,1)),(CEILING(I12,1))),"") -> 1 | K12: =IFERROR(MROUND(I12,0.25),"") -> 0.5
A13: =+A12+1 -> 4 | B13: FUSE & CREASE BOTTOM FOR ZIPPER | C13: 0.85 | D13: =60*C13 -> 51 | E13: =IFERROR(60/C13,"") -> 70.588235 | F13: =+$K$3/($K$2/60) -> 85 | G13: IRON TABLE | I13: =IF(C13="","",($I$3/($I$2/60)*C13/60)) -> 1.2041667 | J13: =IFERROR(IF(I13<(MROUND(I13,1)+0.125),(MROUND(I13,1)),(CEILING(I13,1))),"") -> 2 | K13: =IFERROR(MROUND(I13,0.25),"") -> 1.25
A14: =+A13+1 -> 5 | B14: SERGE BOTTOM FOR LEG ZIPPER*2 | C14: 0.35 | D14: =60*C14 -> 21 | E14: =IFERROR(60/C14,"") -> 171.42857 | F14: =+$K$3/($K$2/60) -> 85 | G14: OL4T | I14: =IF(C14="","",($I$3/($I$2/60)*C14/60)) -> 0.49583333 | J14: =IFERROR(IF(I14<(MROUND(I14,1)+0.125),(MROUND(I14,1)),(CEILING(I14,1))),"") -> 1 | K14: =IFERROR(MROUND(I14,0.25),"") -> 0.5
A15: =+A14+1 -> 6 | D15: =60*C15 -> 0 | E15: =IFERROR(60/C15,"") | F15: =+$K$3/($K$2/60) -> 85 | I15: =IF(C15="","",($I$3/($I$2/60)*C15/60)) | J15: =IFERROR(IF(I15<(MROUND(I15,1)+0.125),(MROUND(I15,1)),(CEILING(I15,1))),"") | K15: =IFERROR(MROUND(I15,0.25),"")
A16: =+A15+1 -> 7 | D16: =60*C16 -> 0 | E16: =IFERROR(60/C16,"") | F16: =+$K$3/($K$2/60) -> 85 | I16: =IF(C16="","",($I$3/($I$2/60)*C16/60)) | J16: =IFERROR(IF(I16<(MROUND(I16,1)+0.125),(MROUND(I16,1)),(CEILING(I16,1))),"") | K16: =IFERROR(MROUND(I16,0.25),"")
A17: =+A16+1 -> 8 | D17: =60*C17 -> 0 | E17: =IFERROR(60/C17,"") | F17: =+$K$3/($K$2/60) -> 85 | I17: =IF(C17="","",($I$3/($I$2/60)*C17/60)) | J17: =IFERROR(IF(I17<(MROUND(I17,1)+0.125),(MROUND(I17,1)),(CEILING(I17,1))),"") | K17: =IFERROR(MROUND(I17,0.25),"")
A18: =+A22+1 -> 9 | D18: =60*C18 -> 0 | E18: =IFERROR(60/C18,"") | F18: =+$K$3/($K$2/60) -> 85 | I18: =IF(C18="","",($I$3/($I$2/60)*C18/60)) | J18: =IFERROR(IF(I18<(MROUND(I18,1)+0.125),(MROUND(I18,1)),(CEILING(I18,1))),"") | K18: =IFERROR(MROUND(I18,0.25),"")
A19: =+A14+1 -> 6 | D19: =60*C19 -> 0 | E19: =IFERROR(60/C19,"") | F19: =+$K$3/($K$2/60) -> 85 | I19: =IF(C19="","",($I$3/($I$2/60)*C19/60)) | J19: =IFERROR(IF(I19<(MROUND(I19,1)+0.125),(MROUND(I19,1)),(CEILING(I19,1))),"") | K19: =IFERROR(MROUND(I19,0.25),"")
A20: =+A19+1 -> 7 | D20: =60*C20 -> 0 | E20: =IFERROR(60/C20,"") | F20: =+$K$3/($K$2/60) -> 85 | I20: =IF(C20="","",($I$3/($I$2/60)*C20/60)) | J20: =IFERROR(IF(I20<(MROUND(I20,1)+0.125),(MROUND(I20,1)),(CEILING(I20,1))),"") | K20: =IFERROR(MROUND(I20,0.25),"")
A21: =+A17+1 -> 9 | D21: =60*C21 -> 0 | E21: =IFERROR(60/C21,"") | F21: =+$K$3/($K$2/60) -> 85 | I21: =IF(C21="","",($I$3/($I$2/60)*C21/60)) | J21: =IFERROR(IF(I21<(MROUND(I21,1)+0.125),(MROUND(I21,1)),(CEILING(I21,1))),"") | K21: =IFERROR(MROUND(I21,0.25),"")
A22: =+A16+1 -> 8 | D22: =60*C22 -> 0 | E22: =IFERROR(60/C22,"") | F22: =+$K$3/($K$2/60) -> 85 | I22: =IF(C22="","",($I$3/($I$2/60)*C22/60)) | J22: =IFERROR(IF(I22<(MROUND(I22,1)+0.125),(MROUND(I22,1)),(CEILING(I22,1))),"") | K22: =IFERROR(MROUND(I22,0.25),"")
A23: =+A21+1 -> 10 | D23: =60*C23 -> 0 | E23: =IFERROR(60/C23,"") | F23: =+$K$3/($K$2/60) -> 85 | I23: =IF(C23="","",($I$3/($I$2/60)*C23/60)) | J23: =IFERROR(IF(I23<(MROUND(I23,1)+0.125),(MROUND(I23,1)),(CEILING(I23,1))),"") | K23: =IFERROR(MROUND(I23,0.25),"")
A24: =+A23+1 -> 11 | D24: =60*C24 -> 0 | E24: =IFERROR(60/C24,"") | F24: =+$K$3/($K$2/60) -> 85 | I24: =IF(C24="","",($I$3/($I$2/60)*C24/60)) | J24: =IFERROR(IF(I24<(MROUND(I24,1)+0.125),(MROUND(I24,1)),(CEILING(I24,1))),"") | K24: =IFERROR(MROUND(I24,0.25),"")
A25: =+A24+1 -> 12 | D25: =60*C25 -> 0 | E25: =IFERROR(60/C25,"") | F25: =+$K$3/($K$2/60) -> 85 | I25: =IF(C25="","",($I$3/($I$2/60)*C25/60)) | J25: =IFERROR(IF(I25<(MROUND(I25,1)+0.125),(MROUND(I25,1)),(CEILING(I25,1))),"") | K25: =IFERROR(MROUND(I25,0.25),"")
A26: FRONT | C26: =SUM(C10:C25) -> 2.9 | I26: =SUM(I10:I25) -> 4.1083333 | J26: =SUM(J10:J25) -> 7 | K26: =SUM(K10:K25) -> 4.25 | L26: =SUM(L10:L25) -> 0
A27: =+A25+1 -> 13 | B27: FUSE & CREASE POCKET MOUTH | C27: 0.6 | D27: =60*C27 -> 36 | E27: =IFERROR(60/C27,"") -> 100 | F27: =+$K$3/($K$2/60) -> 85 | G27: IRON TABLE | I27: =IF(C27="","",($I$3/($I$2/60)*C27/60)) -> 0.85 | J27: =IFERROR(IF(I27<(MROUND(I27,1)+0.125),(MROUND(I27,1)),(CEILING(I27,1))),"") -> 1 | K27: =IFERROR(MROUND(I27,0.25),"") -> 0.75
A28: =+A27+1 -> 14 | B28: ATTACH FACING TO POCKET BAG*2 | C28: 0.35 | D28: =60*C28 -> 21 | E28: =IFERROR(60/C28,"") -> 171.42857 | F28: =+$K$3/($K$2/60) -> 85 | G28: SNLS | I28: =IF(C28="","",($I$3/($I$2/60)*C28/60)) -> 0.49583333 | J28: =IFERROR(IF(I28<(MROUND(I28,1)+0.125),(MROUND(I28,1)),(CEILING(I28,1))),"") -> 1 | K28: =IFERROR(MROUND(I28,0.25),"") -> 0.5
A29: =+A28+1 -> 15 | B29: ATTACH POCKET BAG TO FRONT | C29: 0.65 | D29: =60*C29 -> 39 | E29: =IFERROR(60/C29,"") -> 92.307692 | F29: =+$K$3/($K$2/60) -> 85 | G29: SNLS | I29: =IF(C29="","",($I$3/($I$2/60)*C29/60)) -> 0.92083333 | J29: =IFERROR(IF(I29<(MROUND(I29,1)+0.125),(MROUND(I29,1)),(CEILING(I29,1))),"") -> 1 | K29: =IFERROR(MROUND(I29,0.25),"") -> 1
A30: =+A29+1 -> 16 | B30: SHADOW STITCH POCKET MOUTH & CUT NOTCH | C30: 0.65 | D30: =60*C30 -> 39 | E30: =IFERROR(60/C30,"") -> 92.307692 | F30: =+$K$3/($K$2/60) -> 85 | G30: SNLS | I30: =IF(C30="","",($I$3/($I$2/60)*C30/60)) -> 0.92083333 | J30: =IFERROR(IF(I30<(MROUND(I30,1)+0.125),(MROUND(I30,1)),(CEILING(I30,1))),"") -> 1 | K30: =IFERROR(MROUND(I30,0.25),"") -> 1
A31: =+A30+1 -> 17 | B31: TACK INNER POCKET BAG | C31: 0.65 | D31: =60*C31 -> 39 | E31: =IFERROR(60/C31,"") -> 92.307692 | F31: =+$K$3/($K$2/60) -> 85 | G31: SNLS | I31: =IF(C31="","",($I$3/($I$2/60)*C31/60)) -> 0.92083333 | J31: =IFERROR(IF(I31<(MROUND(I31,1)+0.125),(MROUND(I31,1)),(CEILING(I31,1))),"") -> 1 | K31: =IFERROR(MROUND(I31,0.25),"") -> 1
A32: =+A31+1 -> 18 | B32: CLOSE POCKET BAG | C32: 0.65 | D32: =60*C32 -> 39 | E32: =IFERROR(60/C32,"") -> 92.307692 | F32: =+$K$3/($K$2/60) -> 85 | G32: OL4T | I32: =IF(C32="","",($I$3/($I$2/60)*C32/60)) -> 0.92083333 | J32: =IFERROR(IF(I32<(MROUND(I32,1)+0.125),(MROUND(I32,1)),(CEILING(I32,1))),"") -> 1 | K32: =IFERROR(MROUND(I32,0.25),"") -> 1
A33: =+A32+1 -> 19 | B33: POCKET BAG SIDE WAIST TACK | C33: 0.55 | D33: =60*C33 -> 33 | E33: =IFERROR(60/C33,"") -> 109.09091 | F33: =+$K$3/($K$2/60) -> 85 | G33: SNLS | I33: =IF(C33="","",($I$3/($I$2/60)*C33/60)) -> 0.77916667 | J33: =IFERROR(IF(I33<(MROUND(I33,1)+0.125),(MROUND(I33,1)),(CEILING(I33,1))),"") -> 1 | K33: =IFERROR(MROUND(I33,0.25),"") -> 0.75
A34: =+A33+1 -> 20 | B34: BARTACK POCKET*6 | C34: 0.45 | D34: =60*C34 -> 27 | E34: =IFERROR(60/C34,"") -> 133.33333 | F34: =+$K$3/($K$2/60) -> 85 | G34: BRTK | I34: =IF(C34="","",($I$3/($I$2/60)*C34/60)) -> 0.6375 | J34: =IFERROR(IF(I34<(MROUND(I34,1)+0.125),(MROUND(I34,1)),(CEILING(I34,1))),"") -> 1 | K34: =IFERROR(MROUND(I34,0.25),"") -> 0.75
A35: =+A34+1 -> 21 | B35: JOIN FRONT RISE | C35: 0.35 | D35: =60*C35 -> 21 | E35: =IFERROR(60/C35,"") -> 171.42857 | F35: =+$K$3/($K$2/60) -> 85 | G35: OL4T | I35: =IF(C35="","",($I$3/($I$2/60)*C35/60)) -> 0.49583333 | J35: =IFERROR(IF(I35<(MROUND(I35,1)+0.125),(MROUND(I35,1)),(CEILING(I35,1))),"") -> 1 | K35: =IFERROR(MROUND(I35,0.25),"") -> 0.5
A36: =+A35+1 -> 22 | D36: =60*C36 -> 0 | E36: =IFERROR(60/C36,"") | F36: =+$K$3/($K$2/60) -> 85 | I36: =IF(C36="","",($I$3/($I$2/60)*C36/60)) | J36: =IFERROR(IF(I36<(MROUND(I36,1)+0.125),(MROUND(I36,1)),(CEILING(I36,1))),"") | K36: =IFERROR(MROUND(I36,0.25),"")
A37: =+A36+1 -> 23 | D37: =60*C37 -> 0 | E37: =IFERROR(60/C37,"") | F37: =+$K$3/($K$2/60) -> 85 | I37: =IF(C37="","",($I$3/($I$2/60)*C37/60)) | J37: =IFERROR(IF(I37<(MROUND(I37,1)+0.125),(MROUND(I37,1)),(CEILING(I37,1))),"") | K37: =IFERROR(MROUND(I37,0.25),"")
A38: =+A37+1 -> 24 | D38: =60*C38 -> 0 | E38: =IFERROR(60/C38,"") | F38: =+$K$3/($K$2/60) -> 85 | I38: =IF(C38="","",($I$3/($I$2/60)*C38/60)) | J38: =IFERROR(IF(I38<(MROUND(I38,1)+0.125),(MROUND(I38,1)),(CEILING(I38,1))),"") | K38: =IFERROR(MROUND(I38,0.25),"")
A39: =+A38+1 -> 25 | D39: =60*C39 -> 0 | E39: =IFERROR(60/C39,"") | F39: =+$K$3/($K$2/60) -> 85 | I39: =IF(C39="","",($I$3/($I$2/60)*C39/60)) | J39: =IFERROR(IF(I39<(MROUND(I39,1)+0.125),(MROUND(I39,1)),(CEILING(I39,1))),"") | K39: =IFERROR(MROUND(I39,0.25),"")
A40: =+A39+1 -> 26 | D40: =60*C40 -> 0 | E40: =IFERROR(60/C40,"") | F40: =+$K$3/($K$2/60) -> 85 | I40: =IF(C40="","",($I$3/($I$2/60)*C40/60)) | J40: =IFERROR(IF(I40<(MROUND(I40,1)+0.125),(MROUND(I40,1)),(CEILING(I40,1))),"") | K40: =IFERROR(MROUND(I40,0.25),"")
A41: =+A40+1 -> 27 | D41: =60*C41 -> 0 | E41: =IFERROR(60/C41,"") | F41: =+$K$3/($K$2/60) -> 85 | I41: =IF(C41="","",($I$3/($I$2/60)*C41/60)) | J41: =IFERROR(IF(I41<(MROUND(I41,1)+0.125),(MROUND(I41,1)),(CEILING(I41,1))),"") | K41: =IFERROR(MROUND(I41,0.25),"")
A42: =+A41+1 -> 28 | D42: =60*C42 -> 0 | E42: =IFERROR(60/C42,"") | F42: =+$K$3/($K$2/60) -> 85 | I42: =IF(C42="","",($I$3/($I$2/60)*C42/60)) | J42: =IFERROR(IF(I42<(MROUND(I42,1)+0.125),(MROUND(I42,1)),(CEILING(I42,1))),"") | K42: =IFERROR(MROUND(I42,0.25),"")
A43: =+A42+1 -> 29 | D43: =60*C43 -> 0 | E43: =IFERROR(60/C43,"") | F43: =+$K$3/($K$2/60) -> 85 | I43: =IF(C43="","",($I$3/($I$2/60)*C43/60)) | J43: =IFERROR(IF(I43<(MROUND(I43,1)+0.125),(MROUND(I43,1)),(CEILING(I43,1))),"") | K43: =IFERROR(MROUND(I43,0.25),"")
A44: =+A43+1 -> 30 | D44: =60*C44 -> 0 | E44: =IFERROR(60/C44,"") | F44: =+$K$3/($K$2/60) -> 85 | I44: =IF(C44="","",($I$3/($I$2/60)*C44/60)) | J44: =IFERROR(IF(I44<(MROUND(I44,1)+0.125),(MROUND(I44,1)),(CEILING(I44,1))),"") | K44: =IFERROR(MROUND(I44,0.25),"")
A45: ASSEMBLY | C45: =SUM(C27:C44) -> 4.9 | I45: =SUM(I27:I44) -> 6.9416667 | J45: =SUM(J27:J44) -> 9 | K45: =SUM(K27:K44) -> 7.25 | L45: =SUM(L27:L44) -> 0
A46: =+A44+1 -> 31 | B46: TACK FRONT & BACK AT INSEAM FOR LEG ZIPPER | C46: 0.85 | D46: =60*C46 -> 51 | E46: =IFERROR(60/C46,"") -> 70.588235 | F46: =+$K$3/($K$2/60) -> 85 | G46: SNLS | I46: =IF(C46="","",($I$3/($I$2/60)*C46/60)) -> 1.2041667 | J46: =IFERROR(IF(I46<(MROUND(I46,1)+0.125),(MROUND(I46,1)),(CEILING(I46,1))),"") -> 2 | K46: =IFERROR(MROUND(I46,0.25),"") -> 1.25
A47: =+A46+1 -> 32 | B47: INSEAM | C47: 0.75 | D47: =60*C47 -> 45 | E47: =IFERROR(60/C47,"") -> 80 | F47: =+$K$3/($K$2/60) -> 85 | G47: OL4T | I47: =IF(C47="","",($I$3/($I$2/60)*C47/60)) -> 1.0625 | J47: =IFERROR(IF(I47<(MROUND(I47,1)+0.125),(MROUND(I47,1)),(CEILING(I47,1))),"") -> 1 | K47: =IFERROR(MROUND(I47,0.25),"") -> 1
A48: =+A47+1 -> 33 | B48: TACK LEG ZIPPER | C48: 0.35 | D48: =60*C48 -> 21 | E48: =IFERROR(60/C48,"") -> 171.42857 | F48: =+$K$3/($K$2/60) -> 85 | G48: SNLS | I48: =IF(C48="","",($I$3/($I$2/60)*C48/60)) -> 0.49583333 | J48: =IFERROR(IF(I48<(MROUND(I48,1)+0.125),(MROUND(I48,1)),(CEILING(I48,1))),"") -> 1 | K48: =IFERROR(MROUND(I48,0.25),"") -> 0.5
A49: =+A48+1 -> 34 | B49: ATTACH LEG ZIPPER | C49: 1.8 | D49: =60*C49 -> 108 | E49: =IFERROR(60/C49,"") -> 33.333333 | F49: =+$K$3/($K$2/60) -> 85 | G49: SNLS | I49: =IF(C49="","",($I$3/($I$2/60)*C49/60)) -> 2.55 | J49: =IFERROR(IF(I49<(MROUND(I49,1)+0.125),(MROUND(I49,1)),(CEILING(I49,1))),"") -> 3 | K49: =IFERROR(MROUND(I49,0.25),"") -> 2.5
A50: =+A49+1 -> 35 | B50: TACK FOR SIDE SEAM | C50: 0.9 | D50: =60*C50 -> 54 | E50: =IFERROR(60/C50,"") -> 66.666667 | F50: =+$K$3/($K$2/60) -> 85 | G50: SNLS | I50: =IF(C50="","",($I$3/($I$2/60)*C50/60)) -> 1.275 | J50: =IFERROR(IF(I50<(MROUND(I50,1)+0.125),(MROUND(I50,1)),(CEILING(I50,1))),"") -> 2 | K50: =IFERROR(MROUND(I50,0.25),"") -> 1.25
A51: =+A50+1 -> 36 | B51: SIDE SEAM | C51: 0.9 | D51: =60*C51 -> 54 | E51: =IFERROR(60/C51,"") -> 66.666667 | F51: =+$K$3/($K$2/60) -> 85 | G51: OL4T | I51: =IF(C51="","",($I$3/($I$2/60)*C51/60)) -> 1.275 | J51: =IFERROR(IF(I51<(MROUND(I51,1)+0.125),(MROUND(I51,1)),(CEILING(I51,1))),"") -> 2 | K51: =IFERROR(MROUND(I51,0.25),"") -> 1.25
A52: =+A51+1 -> 37 | B52: CREASE SIDE SEAM | C52: 0.65 | D52: =60*C52 -> 39 | E52: =IFERROR(60/C52,"") -> 92.307692 | F52: =+$K$3/($K$2/60) -> 85 | G52: IRON TABLE | I52: =IF(C52="","",($I$3/($I$2/60)*C52/60)) -> 0.92083333 | J52: =IFERROR(IF(I52<(MROUND(I52,1)+0.125),(MROUND(I52,1)),(CEILING(I52,1))),"") -> 1 | K52: =IFERROR(MROUND(I52,0.25),"") -> 1
A53: =+A52+1 -> 38 | B53: MARK FOR HIGH LOW | C53: 0.3 | D53: =60*C53 -> 18 | E53: =IFERROR(60/C53,"") -> 200 | F53: =+$K$3/($K$2/60) -> 85 | G53: TABLE | I53: =IF(C53="","",($I$3/($I$2/60)*C53/60)) -> 0.425 | J53: =IFERROR(IF(I53<(MROUND(I53,1)+0.125),(MROUND(I53,1)),(CEILING(I53,1))),"") -> 1 | K53: =IFERROR(MROUND(I53,0.25),"") -> 0.5
A54: =+A53+1 -> 39 | B54: MARK & TACK WB FOR BUTTON HOLE | C54: 0.9 | D54: =60*C54 -> 54 | E54: =IFERROR(60/C54,"") -> 66.666667 | F54: =+$K$3/($K$2/60) -> 85 | G54: SNLS | I54: =IF(C54="","",($I$3/($I$2/60)*C54/60)) -> 1.275 | J54: =IFERROR(IF(I54<(MROUND(I54,1)+0.125),(MROUND(I54,1)),(CEILING(I54,1))),"") -> 2 | K54: =IFERROR(MROUND(I54,0.25),"") -> 1.25
A55: =+A54+1 -> 40 | B55: CREASE WB JOININGS TO SPLIT | C55: 0.45 | D55: =60*C55 -> 27 | E55: =IFERROR(60/C55,"") -> 133.33333 | F55: =+$K$3/($K$2/60) -> 85 | G55: IRON TABLE | I55: =IF(C55="","",($I$3/($I$2/60)*C55/60)) -> 0.6375 | J55: =IFERROR(IF(I55<(MROUND(I55,1)+0.125),(MROUND(I55,1)),(CEILING(I55,1))),"") -> 1 | K55: =IFERROR(MROUND(I55,0.25),"") -> 0.75
A56: =+A55+1 -> 41 | B56: TOP STITCH BUTTON HOLE SIDE | C56: 0.9 | D56: =60*C56 -> 54 | E56: =IFERROR(60/C56,"") -> 66.666667 | F56: =+$K$3/($K$2/60) -> 85 | G56: SNLS | I56: =IF(C56="","",($I$3/($I$2/60)*C56/60)) -> 1.275 | J56: =IFERROR(IF(I56<(MROUND(I56,1)+0.125),(MROUND(I56,1)),(CEILING(I56,1))),"") -> 2 | K56: =IFERROR(MROUND(I56,0.25),"") -> 1.25
A57: =+A56+1 -> 42 | B57: ATTACH WB TO BODY | C57: 0.65 | D57: =60*C57 -> 39 | E57: =IFERROR(60/C57,"") -> 92.307692 | F57: =+$K$3/($K$2/60) -> 85 | G57: OL4T | I57: =IF(C57="","",($I$3/($I$2/60)*C57/60)) -> 0.92083333 | J57: =IFERROR(IF(I57<(MROUND(I57,1)+0.125),(MROUND(I57,1)),(CEILING(I57,1))),"") -> 1 | K57: =IFERROR(MROUND(I57,0.25),"") -> 1
A58: =+A57+1 -> 43 | B58: MAKE ELASTIC READY | C58: 0.35 | D58: =60*C58 -> 21 | E58: =IFERROR(60/C58,"") -> 171.42857 | F58: =+$K$3/($K$2/60) -> 85 | G58: PREP | I58: =IF(C58="","",($I$3/($I$2/60)*C58/60)) -> 0.49583333 | J58: =IFERROR(IF(I58<(MROUND(I58,1)+0.125),(MROUND(I58,1)),(CEILING(I58,1))),"") -> 1 | K58: =IFERROR(MROUND(I58,0.25),"") -> 0.5
... A70: =+A69+1 -> 55 | B70: TRIM AND INLINE CHECK | C70: 0.65 | D70: =60*C70 -> 39 | E70: =IFERROR(60/C70,"") -> 92.307692 | F70: =+$K$3/($K$2/60) -> 85 | G70: TABLE | I70: =IF(C70="","",($I$3/($I$2/60)*C70/60)) -> 0.92083333 | J70: =IFERROR(IF(I70<(MROUND(I70,1)+0.125),(MROUND(I70,1)),(CEILING(I70,1))),"") -> 1 | K70: =IFERROR(MROUND(I70,0.25),"") -> 1
A71: =+A70+1 -> 56 | B71: BUFFER | C71: 7.9 | D71: =60*C71 -> 474 | E71: =IFERROR(60/C71,"") -> 7.5949367 | F71: =+$K$3/($K$2/60) -> 85 | I71: =IF(C71="","",($I$3/($I$2/60)*C71/60)) -> 11.191667 | J71: =IFERROR(IF(I71<(MROUND(I71,1)+0.125),(MROUND(I71,1)),(CEILING(I71,1))),"") -> 12 | K71: =IFERROR(MROUND(I71,0.25),"") -> 11.25
A72: =+A71+1 -> 57 | D72: =60*C72 -> 0 | E72: =IFERROR(60/C72,"") | F72: =+$K$3/($K$2/60) -> 85 | I72: =IF(C72="","",($I$3/($I$2/60)*C72/60)) | J72: =IFERROR(IF(I72<(MROUND(I72,1)+0.125),(MROUND(I72,1)),(CEILING(I72,1))),"") | K72: =IFERROR(MROUND(I72,0.25),"")
A73: =+A72+1 -> 58 | D73: =+C73*60 -> 0 | E73: =IFERROR(60/C73,"") | F73: =+$K$3/($K$2/60) -> 85 | I73: =IF(C73="","",($I$3/($I$2/60)*C73/60)) | J73: =IFERROR(IF(I73<(MROUND(I73,1)+0.125),(MROUND(I73,1)),(CEILING(I73,1))),"") | K73: =IFERROR(MROUND(I73,0.25),"")
C74: =+SUM(C46:C73) -> 24.25 | I74: =+SUM(I46:I73) -> 34.354167 | J74: =+SUM(J46:J73) -> 44 | K74: =+SUM(K46:K73) -> 34.75 | L74: =+SUM(L46:L73) -> 0
A75: EOL-TB | B75: EOL-TB | C75: EOL-TB | G75: EOL-TB | J75: EOL-TB
B76: FINISHING | C76: =C26+C45+C74 -> 32.05 | I76: =I26+I45+I74 -> 45.404167 | J76: =J26+J45+J74 -> 60 | K76: =K26+K45+K74 -> 46.25 | L76: =L26+L45+L74 -> 0
A77: =+A73+1 -> 59 | B77: QUALITY CHECKER | D77: =C77*60 -> 0 | E77: =IFERROR(60/C77,"") | F77: =+$K$3/($K$2/60) -> 85 | G77: TABLE | I77: =IF(C77="","",($I$3/($I$2/60)*C77/60)) | J77: =IFERROR(IF(I77<(MROUND(I77,1)+0.125),(MROUND(I77,1)),(CEILING(I77,1))),"") | K77: =IFERROR(MROUND(I77,0.25),"")
A78: =+A77+1 -> 60 | B78: IRONING GARMENT + W/BAND | C78: 0.65 | D78: =+C78*60 -> 39 | E78: =IFERROR(60/C78,"") -> 92.307692 | F78: =+$K$3/($K$2/60) -> 85 | G78: IRON TABLE | I78: =IF(C78="","",($I$3/($I$2/60)*C78/60)) -> 0.92083333 | J78: =IFERROR(IF(I78<(MROUND(I78,1)+0.125),(MROUND(I78,1)),(CEILING(I78,1))),"") -> 1 | K78: 1
A79: =+A78+1 -> 61 | B79: SPEC & PRESENTATION QC | D79: =+C79*60 -> 0 | E79: =IFERROR(60/C79,"") | F79: =+$K$3/($K$2/60) -> 85 | G79: TABLE | I79: =IF(C79="","",($I$3/($I$2/60)*C79/60)) | J79: =IFERROR(IF(I79<(MROUND(I79,1)+0.125),(MROUND(I79,1)),(CEILING(I79,1))),"") | K79: =IFERROR(MROUND(I79,0.25),"")
A80: =+A79+1 -> 62 | B80: MATCHBOOK | C80: 0.25 | D80: =+C80*60 -> 15 | E80: =IFERROR(60/C80,"") -> 240 | F80: =+$K$3/($K$2/60) -> 85 | G80: BA | I80: =IF(C80="","",($I$3/($I$2/60)*C80/60)) -> 0.35416667 | J80: =IFERROR(IF(I80<(MROUND(I80,1)+0.125),(MROUND(I80,1)),(CEILING(I80,1))),"") -> 1 | K80: 1
A81: =+A80+1 -> 63 | B81: HANGTAG | C81: 0.25 | D81: =+C81*60 -> 15 | E81: =IFERROR(60/C81,"") -> 240 | F81: =+$K$3/($K$2/60) -> 85 | G81: TAG GUN | I81: =IF(C81="","",($I$3/($I$2/60)*C81/60)) -> 0.35416667 | J81: =IFERROR(IF(I81<(MROUND(I81,1)+0.125),(MROUND(I81,1)),(CEILING(I81,1))),"") -> 1
A82: =+A81+1 -> 64 | B82: FOLDING + POLYBAG | C82: 0.65 | D82: =+C82*60 -> 39 | E82: =IFERROR(60/C82,"") -> 92.307692 | F82: =+$K$3/($K$2/60) -> 85 | G82: TABLE | I82: =IF(C82="","",($I$3/($I$2/60)*C82/60)) -> 0.92083333 | J82: =IFERROR(IF(I82<(MROUND(I82,1)+0.125),(MROUND(I82,1)),(CEILING(I82,1))),"") -> 1 | K82: 1
A83: =+A82+1 -> 65 | B83: SKU + CTN | C83: 0.35 | D83: =C83*60 -> 21 | E83: =IFERROR(60/C83,"") -> 171.42857 | F83: =+$K$3/($K$2/60) -> 85 | G83: TABLE | I83: =IF(C83="","",($I$3/($I$2/60)*C83/60)) -> 0.49583333 | J83: =IFERROR(IF(I83<(MROUND(I83,1)+0.125),(MROUND(I83,1)),(CEILING(I83,1))),"") -> 1 | K83: 1
C84: =+SUM(C77:C83) -> 2.15 | I84: =+SUM(I77:I83) -> 3.0458333 | J84: =+SUM(J77:J83) -> 5 | K84: =+SUM(K77:K83) -> 4 | L84: =+SUM(L77:L83) -> 0
C85: =C84+C76 -> 34.2 | I85: =I84+I76 -> 48.45 | J85: =J84+J76 -> 65 | K85: =K84+K76 -> 50.25 | L85: =L84+L76 -> 0
G86: EOL-TB | J86: EOL-TB
J87: Date | K87: Build Up | L87: Balance | M87: Day Actual
B88: BULLETIN SUMMARY | D88: M/C TYPE | E88: REQ QTY | F88: M/C TYPE | G88: REQ QTY | H88: OQ | I88: 20000 | J88: =IF(TEXT(I90+I92,"dddd")="Friday",I90+I92+1,I90+I92) -> 45956.5 | K88: =+$I$3*N88 -> 255 | L88: =+$I$88-K88 -> 19745 | M88: =+J88-$I$90 -> 1.5 | N88: 0.3
B89: OPERATORS | C89: =K85 -> 50.25 | D89: SNLS | E89: =SUMIF($G$9:$G$83,D89,$J$9:$J$83) -> 21 | F89: FL2T-FB | G89: =SUMIF($G$9:$G$83,F89,$J$9:$J$83) -> 0 | H89: No of Line | I89: 1 | J89: =IF(TEXT(J88+1,"dddd")="Friday",J88+2,J88+1) -> 45957.5 | K89: =+$I$3*N89 -> 297.5 | L89: =+L88-K89 -> 19447.5 | M89: =+J89-$I$90 -> 2.5 | N89: 0.35
B90: HELPERS | C90: =L85 -> 0 | D90: SNEC | E90: =SUMIF($G$9:$G$83,D90,$J$9:$J$83) -> 0 | F90: FL3T-FB | G90: =SUMIF($G$9:$G$83,F90,$J$9:$J$83) -> 0 | H90: DATE OF START | I90: 45955 | J90: =IF(TEXT(J89+1,"dddd")="Friday",J89+2,J89+1) -> 45958.5 | K90: =+$I$3*N90 -> 340 | L90: =+L89-K90 -> 19107.5 | M90: =+J90-$I$90 -> 3.5 | N90: 0.4
B91: SUPERVISOR | C91: 1 | D91: APW | E91: =SUMIF($G$9:$G$83,D91,$J$9:$J$83) -> 0 | F91: FL4T-FB | G91: =SUMIF($G$9:$G$83,F91,$J$9:$J$83) -> 0 | J91: =IF(TEXT(J90+1,"dddd")="Friday",J90+2,J90+1) -> 45959.5 | K91: =+$I$3*N91 -> 382.5 | L91: =+L90-K91 -> 18725 | M91: =+J91-$I$90 -> 4.5 | N91: 0.45
B92: ROVING QC | C92: 1 | D92: OL3T | E92: =SUMIF($G$9:$G$83,D92,$J$9:$J$83) -> 0 | F92: FL5T-FB | G92: =SUMIF($G$9:$G$83,F92,$J$9:$J$83) -> 0 | H92: PICK UP DAY | I92: =+IF((C3<9.99),0.5,IF(AND(C3>9.999,C3<19.99),1,IF(AND(C3>19.999,C3<35),1.5,2)))*I89 -> 1.5 | J92: =IF(TEXT(J91+1,"dddd")="Friday",J91+2,J91+1) -> 45960.5 | K92: =+$I$3*N92 -> 425 | L92: =+L91-K92 -> 18300 | M92: =+J92-$I$90 -> 5.5 | N92: 0.5
B93: REPACK+AUDITOR | C93: 2 | D93: OL4T | E93: =SUMIF($G$9:$G$83,D93,$J$9:$J$83) -> 8 | F93: FL6T-FB | G93: =SUMIF($G$9:$G$83,F93,$J$9:$J$83) -> 0 | H93: Days in 100% | I93: =+I88/I3/I89 -> 23.529412 | J93: =IF(TEXT(J92+1,"dddd")="Friday",J92+2,J92+1) -> 45962.5 | K93: =+$I$3*N93 -> 467.5 | L93: =+L92-K93 -> 17832.5 | M93: =+J93-$I$90 -> 7.5 | N93: 0.55
B94: TOTAL | C94: =SUM(C89:C93) -> 54.25 | D94: OL5T | E94: =SUMIF($G$9:$G$83,D94,$J$9:$J$83) -> 0 | F94: FL2T-CB | G94: =SUMIF($G$9:$G$83,F94,$J$9:$J$83) -> 0 | H94: Eff %/OQ | I94: =+IF((I88<2499.9),30%,IF(AND(I88>2499.99,I88<4999.9),50%,IF(AND(I88>4999.99,I88<9999.9),65%,IF(AND(I88>9999.99,I88<19999.9),80%,IF(AND(I88>19999.99,I88<49999.9),85%,IF(AND(I88>49999.99,I88<74999.9),90%,IF(AND(I88>74999.99,I88<99999.9),95%,100%))))))) -> 0.85 | J94: =IF(TEXT(J93+1,"dddd")="Friday",J93+2,J93+1) -> 45963.5 | K94: =+$I$3*N94 -> 510 | L94: =+L93-K94 -> 17322.5 | M94: =+J94-$I$90 -> 8.5 | N94: 0.6
D95: DNLS | E95: =SUMIF($G$9:$G$83,D95,$J$9:$J$83) -> 0 | F95: FL3T-CB | G95: =SUMIF($G$9:$G$83,F95,$J$9:$J$83) -> 1 | H95: Days Req/OQ | I95: =(I93+I93*(1-K4/1)+I92)+(I93+I93*(1-K4/1)+I92)/7 -> 28.605042 | J95: =IF(TEXT(J94+1,"dddd")="Friday",J94+2,J94+1) -> 45964.5 | K95: =+$I$3*N95 -> 552.5 | L95: =+L94-K95 -> 16770 | M95: =+J95-$I$90 -> 9.5 | N95: 0.65
D96: SNCS | E96: =SUMIF($G$9:$G$83,D96,$J$9:$J$83) -> 0 | F96: FL4T-CB | G96: =SUMIF($G$9:$G$83,F96,$J$9:$J$83) -> 0 | H96: Line Cost | I96: =+I95*C94*55*I89 -> 85350.294 | J96: =IF(TEXT(J95+1,"dddd")="Friday",J95+2,J95+1) -> 45965.5 | K96: =+$I$3*N96 -> 595 | L96: =+L95-K96 -> 16175 | M96: =+J96-$I$90 -> 10.5 | N96: 0.7
D97: DNCS | E97: =SUMIF($G$9:$G$83,D97,$J$9:$J$83) -> 0 | F97: FL5T-CB | G97: =SUMIF($G$9:$G$83,F97,$J$9:$J$83) -> 0 | H97: Revenue | I97: =+I88*E5 -> 60800 | J97: =IF(TEXT(J96+1,"dddd")="Friday",J96+2,J96+1) -> 45966.5 | K97: =+$I$3*N97 -> 637.5 | L97: =+L96-K97 -> 15537.5 | M97: =+J97-$I$90 -> 11.5 | N97: 0.75
D98: KANSAI | E98: =SUMIF($G$9:$G$83,D98,$J$9:$J$83) -> 3 | F98: FL6T-CB | G98: =SUMIF($G$9:$G$83,F98,$J$9:$J$83) -> 0 | H98: Profit/Loss | I98: =+I97-I96 -> -24550.294 | J98: =IF(TEXT(J97+1,"dddd")="Friday",J97+2,J97+1) -> 45967.5 | K98: =+$I$3*N98 -> 680 | L98: =+L97-K98 -> 14857.5 | M98: =+J98-$I$90 -> 12.5 | N98: 0.8
D99: BRTK | E99: =SUMIF($G$9:$G$83,D99,$J$9:$J$83) -> 3 | F99: BLIND LOOP | G99: =SUMIF($G$9:$G$83,F99,$J$9:$J$83) -> 0 | H99: DATE OF END | I99: =+I90+I95 -> 45983.605 | J99: =IF(TEXT(J98+1,"dddd")="Friday",J98+2,J98+1) -> 45969.5 | K99: =+$I$3*N99 -> 722.5 | L99: =+L98-K99 -> 14135 | M99: =+J99-$I$90 -> 14.5 | N99: 0.85
D100: KEYHOLE | E100: =SUMIF($G$9:$G$83,D100,$J$9:$J$83) -> 0 | F100: FLAT LOOP | G100: =SUMIF($G$9:$G$83,F100,$J$9:$J$83) -> 0 | J100: =IF(TEXT(J99+1,"dddd")="Friday",J99+2,J99+1) -> 45970.5 | K100: =+$I$3*N100 -> 765 | L100: =+L99-K100 -> 13370 | M100: =+J100-$I$90 -> 15.5 | N100: 0.9
D101: SNAP | E101: =SUMIF($G$9:$G$83,D101,$J$9:$J$83) -> 0 | F101: KANSAI LOOP | G101: =SUMIF($G$9:$G$83,F101,$J$9:$J$83) -> 0 | J101: =IF(TEXT(J100+1,"dddd")="Friday",J100+2,J100+1) -> 45971.5 | K101: =+$I$3*N101 -> 807.5 | L101: =+L100-K101 -> 12562.5 | M101: =+J101-$I$90 -> 16.5 | N101: 0.95
D102: BH | E102: =SUMIF($G$9:$G$83,D102,$J$9:$J$83) -> 0 | F102: HEAT SEAL | G102: =SUMIF($G$9:$G$83,F102,$J$9:$J$83) -> 0 | J102: =IF(TEXT(J101+1,"dddd")="Friday",J101+2,J101+1) -> 45972.5 | K102: =+$I$3*N102 -> 850 | L102: =+L101-K102 -> 11712.5 | M102: =+J102-$I$90 -> 17.5 | N102: 1
D103: BA | E103: =SUMIF($G$9:$G$83,D103,$J$9:$J$83) -> 1 | F103: AUTO LOOP | G103: =SUMIF($G$9:$G$83,F103,$J$9:$J$83) -> 0 | J103: =IF(TEXT(J102+1,"dddd")="Friday",J102+2,J102+1) -> 45973.5 | K103: =+$I$3*N103 -> 892.5 | L103: =+L102-K103 -> 10820 | M103: =+J103-$I$90 -> 18.5 | N103: 1.05
D104: FOA | E104: =SUMIF($G$9:$G$83,D104,$J$9:$J$83) -> 0 | F104: TABLE | G104: =SUMIF($G$9:$G$83,F104,$J$9:$J$83) -> 7 | J104: =IF(TEXT(J103+1,"dddd")="Friday",J103+2,J103+1) -> 45974.5 | K104: =+$I$3*N104 -> 935 | L104: =+L103-K104 -> 9885 | M104: =+J104-$I$90 -> 19.5 | N104: 1.1
D105: FS | E105: =SUMIF($G$9:$G$83,D105,$J$9:$J$83) -> 0 | F105: TAG GUN | G105: =SUMIF($G$9:$G$83,F105,$J$9:$J$83) -> 1 | J105: =IF(TEXT(J104+1,"dddd")="Friday",J104+2,J104+1) -> 45976.5 | K105: =+$I$3*N105 -> 977.5 | L105: =+L104-K105 -> 8907.5 | M105: =+J105-$I$90 -> 21.5 | N105: 1.15
D106: BLIND HEM | E106: =SUMIF($G$9:$G$83,D106,$J$9:$J$83) -> 0 | F106: IRON TABLE | G106: =SUMIF($G$9:$G$83,F106,$J$9:$J$83) -> 7 | J106: =IF(TEXT(J105+1,"dddd")="Friday",J105+2,J105+1) -> 45977.5 | K106: =+$I$3*N106 -> 1020 | L106: =+L105-K106 -> 7887.5 | M106: =+J106-$I$90 -> 22.5 | N106: 1.2
J107: =(J108-J106)-(J108-J106)/7 -> 5.2328932 | K107: =+J107*K108 -> 5337.551 | L107: =+L106-K107 -> 2549.949
D108: TOTAL REQUIRED MACHINE | G108: =+SUM(E89:E106,G89:G106) -> 52 | J108: =+I99 -> 45983.605 | K108: =+K106 -> 1020 | L108: =+L107-K108 -> 1529.949 | M108: =+J108-$I$90 -> 28.605042
K109: =SUM(K88:K108) -> 18470.051

Sheet aSC LAYOUT
A2: MACHINE LAYOUT - NEEDLE TO NEEDLE MODULE
C5: BUYER | E5: =OB!E2 -> ADIDAS | R5: INPUT DATE | V5: =OB!I90 -> 45955
C6: STYLE | E6: =OB!C2 -> S2554MESS651WV | R6: IE | V6: =OB!M4 -> SHANAKA
C7: ITEM | E7: =OB!I4 -> PANT | R7: SUPERVISOR | V7: =OB!M3 -> NAZIR
A9: OUTPUT
A14: =IFERROR(INDEX(OB!$G:$G,MATCH('aSC LAYOUT'!$B:$B,OB!$A:$A,0)),"") | B14: =+W14+1 -> 112 | C14: =IFERROR(INDEX(OB!$B:$B,MATCH('aSC LAYOUT'!$B:$B,OB!$A:$A,0)),"") | E14: =IFERROR(INDEX(OB!$C:$C,MATCH('aSC LAYOUT'!$B:$B,OB!$A:$A,0)),"") | F14: =IFERROR(INDEX(OB!$K:$K,MATCH('aSC LAYOUT'!$B:$B,OB!$A:$A,0)),"") | G14: =IF(C14="","",(MROUND(IF(E14<=0,0,60/E14),5))) | H14: =E17 -> 0 | Q14: =T17 -> 0 | R14: =IF(V14="","",(MROUND(IF(T14<=0,0,60/T14),5))) | S14: =IFERROR(INDEX(OB!$K:$K,MATCH('aSC LAYOUT'!$W:$W,OB!$A:$A,0)),"") | T14: =IFERROR(INDEX(OB!$C:$C,MATCH('aSC LAYOUT'!$W:$W,OB!$A:$A,0)),"") | V14: =IFERROR(INDEX(OB!$B:$B,MATCH('aSC LAYOUT'!$W:$W,OB!$A:$A,0)),"") | W14: =+W19+1 -> 111 | X14: =IFERROR(INDEX(OB!$G:$G,MATCH('aSC LAYOUT'!$W:$W,OB!$A:$A,0)),"")
A15: =IFERROR(INDEX(OB!$G:$G,MATCH('aSC LAYOUT'!$B:$B,OB!$A:$A,0)),"") | C15: =IFERROR(INDEX(OB!$B:$B,MATCH('aSC LAYOUT'!$B:$B,OB!$A:$A,0)),"") | E15: =IFERROR(INDEX(OB!$C:$C,MATCH('aSC LAYOUT'!$B:$B,OB!$A:$A,0)),"") | F15: =IFERROR(INDEX(OB!$K:$K,MATCH('aSC LAYOUT'!$B:$B,OB!$A:$A,0)),"") | G15: =IF(C15="","",(MROUND(IF(E15<=0,0,60/E15),5))) | I15: WS | P15: WS | R15: =IF(V15="","",(MROUND(IF(T15<=0,0,60/T15),5))) | S15: =IFERROR(INDEX(OB!$K:$K,MATCH('aSC LAYOUT'!$W:$W,OB!$A:$A,0)),"") | T15: =IFERROR(INDEX(OB!$C:$C,MATCH('aSC LAYOUT'!$W:$W,OB!$A:$A,0)),"") | V15: =IFERROR(INDEX(OB!$B:$B,MATCH('aSC LAYOUT'!$W:$W,OB!$A:$A,0)),"") | X15: =IFERROR(INDEX(OB!$G:$G,MATCH('aSC LAYOUT'!$W:$W,OB!$A:$A,0)),"")
A16: =IFERROR(INDEX(OB!$G:$G,MATCH('aSC LAYOUT'!$B:$B,OB!$A:$A,0)),"") | C16: =IFERROR(INDEX(OB!$B:$B,MATCH('aSC LAYOUT'!$B:$B,OB!$A:$A,0)),"") | E16: =IFERROR(INDEX(OB!$C:$C,MATCH('aSC LAYOUT'!$B:$B,OB!$A:$A,0)),"") | F16: =IFERROR(INDEX(OB!$K:$K,MATCH('aSC LAYOUT'!$B:$B,OB!$A:$A,0)),"") | G16: =IF(C16="","",(MROUND(IF(E16<=0,0,60/E16),5))) | H16: =F17 -> 0 | I16: =+P16+1 -> 88 | P16: =+P21+1 -> 87 | Q16: =S17 -> 0 | R16: =IF(V16="","",(MROUND(IF(T16<=0,0,60/T16),5))) | S16: =IFERROR(INDEX(OB!$K:$K,MATCH('aSC LAYOUT'!$W:$W,OB!$A:$A,0)),"") | T16: =IFERROR(INDEX(OB!$C:$C,MATCH('aSC LAYOUT'!$W:$W,OB!$A:$A,0)),"") | V16: =IFERROR(INDEX(OB!$B:$B,MATCH('aSC LAYOUT'!$W:$W,OB!$A:$A,0)),"") | X16: =IFERROR(INDEX(OB!$G:$G,MATCH('aSC LAYOUT'!$W:$W,OB!$A:$A,0)),"")
E17: =SUM(E14:E16) -> 0 | F17: =SUM(F14:F16) -> 0 | S17: =SUM(S14:S16) -> 0 | T17: =SUM(T14:T16) -> 0
A19: =IFERROR(INDEX(OB!$G:$G,MATCH('aSC LAYOUT'!$B:$B,OB!$A:$A,0)),"") | B19: =+B24+1 -> 109 | C19: =IFERROR(INDEX(OB!$B:$B,MATCH('aSC LAYOUT'!$B:$B,OB!$A:$A,0)),"") | E19: =IFERROR(INDEX(OB!$C:$C,MATCH('aSC LAYOUT'!$B:$B,OB!$A:$A,0)),"") | F19: =IFERROR(INDEX(OB!$K:$K,MATCH('aSC LAYOUT'!$B:$B,OB!$A:$A,0)),"") | G19: =IF(C19="","",(MROUND(IF(E19<=0,0,60/E19),5))) | H19: =E22 -> 0 | Q19: =T22 -> 0 | R19: =IF(V19="","",(MROUND(IF(T19<=0,0,60/T19),5))) | S19: =IFERROR(INDEX(OB!$K:$K,MATCH('aSC LAYOUT'!$W:$W,OB!$A:$A,0)),"") | T19: =IFERROR(INDEX(OB!$C:$C,MATCH('aSC LAYOUT'!$W:$W,OB!$A:$A,0)),"") | V19: =IFERROR(INDEX(OB!$B:$B,MATCH('aSC LAYOUT'!$W:$W,OB!$A:$A,0)),"") | W19: =+B19+1 -> 110 | X19: =IFERROR(INDEX(OB!$G:$G,MATCH('aSC LAYOUT'!$W:$W,OB!$A:$A,0)),"")
A20: =IFERROR(INDEX(OB!$G:$G,MATCH('aSC LAYOUT'!$B:$B,OB!$A:$A,0)),"") | C20: =IFERROR(INDEX(OB!$B:$B,MATCH('aSC LAYOUT'!$B:$B,OB!$A:$A,0)),"") | E20: =IFERROR(INDEX(OB!$C:$C,MATCH('aSC LAYOUT'!$B:$B,OB!$A:$A,0)),"") | F20: =IFERROR(INDEX(OB!$K:$K,MATCH('aSC LAYOUT'!$B:$B,OB!$A:$A,0)),"") | G20: =IF(C20="","",(MROUND(IF(E20<=0,0,60/E20),5))) | I20: WS | P20: WS | R20: =IF(V20="","",(MROUND(IF(T20<=0,0,60/T20),5))) | S20: =IFERROR(INDEX(OB!$K:$K,MATCH('aSC LAYOUT'!$W:$W,OB!$A:$A,0)),"") | T20: =IFERROR(INDEX(OB!$C:$C,MATCH('aSC LAYOUT'!$W:$W,OB!$A:$A,0)),"") | V20: =IFERROR(INDEX(OB!$B:$B,MATCH('aSC LAYOUT'!$W:$W,OB!$A:$A,0)),"") | X20: =IFERROR(INDEX(OB!$G:$G,MATCH('aSC LAYOUT'!$W:$W,OB!$A:$A,0)),"")
A21: =IFERROR(INDEX(OB!$G:$G,MATCH('aSC LAYOUT'!$B:$B,OB!$A:$A,0)),"") | C21: =IFERROR(INDEX(OB!$B:$B,MATCH('aSC LAYOUT'!$B:$B,OB!$A:$A,0)),"") | E21: =IFERROR(INDEX(OB!$C:$C,MATCH('aSC LAYOUT'!$B:$B,OB!$A:$A,0)),"") | F21: =IFERROR(INDEX(OB!$K:$K,MATCH('aSC LAYOUT'!$B:$B,OB!$A:$A,0)),"") | G21: =IF(C21="","",(MROUND(IF(E21<=0,0,60/E21),5))) | H21: =F22 -> 0 | I21: =+I26+1 -> 85 | P21: =+I21+1 -> 86 | Q21: =S22 -> 0 | R21: =IF(V21="","",(MROUND(IF(T21<=0,0,60/T21),5))) | S21: =IFERROR(INDEX(OB!$K:$K,MATCH('aSC LAYOUT'!$W:$W,OB!$A:$A,0)),"") | T21: =IFERROR(INDEX(OB!$C:$C,MATCH('aSC LAYOUT'!$W:$W,OB!$A:$A,0)),"") | V21: =IFERROR(INDEX(OB!$B:$B,MATCH('aSC LAYOUT'!$W:$W,OB!$A:$A,0)),"") | X21: =IFERROR(INDEX(OB!$G:$G,MATCH('aSC LAYOUT'!$W:$W,OB!$A:$A,0)),"")
E22: =SUM(E19:E21) -> 0 | F22: =SUM(F19:F21) -> 0 | S22: =SUM(S19:S21) -> 0 | T22: =SUM(T19:T21) -> 0
A24: =IFERROR(INDEX(OB!$G:$G,MATCH('aSC LAYOUT'!$B:$B,OB!$A:$A,0)),"") | B24: =+W24+1 -> 108 | C24: =IFERROR(INDEX(OB!$B:$B,MATCH('aSC LAYOUT'!$B:$B,OB!$A:$A,0)),"") | E24: =IFERROR(INDEX(OB!$C:$C,MATCH('aSC LAYOUT'!$B:$B,OB!$A:$A,0)),"") | F24: =IFERROR(INDEX(OB!$K:$K,MATCH('aSC LAYOUT'!$B:$B,OB!$A:$A,0)),"") | G24: =IF(C24="","",(MROUND(IF(E24<=0,0,60/E24),5))) | H24: =E27 -> 0 | Q24: =T27 -> 0 | R24: =IF(V24="","",(MROUND(IF(T24<=0,0,60/T24),5))) | S24: =IFERROR(INDEX(OB!$K:$K,MATCH('aSC LAYOUT'!$W:$W,OB!$A:$A,0)),"") | T24: =IFERROR(INDEX(OB!$C:$C,MATCH('aSC LAYOUT'!$W:$W,OB!$A:$A,0)),"") | V24: =IFERROR(INDEX(OB!$B:$B,MATCH('aSC LAYOUT'!$W:$W,OB!$A:$A,0)),"") | W24: =+W29+1 -> 107 | X24: =IFERROR(INDEX(OB!$G:$G,MATCH('aSC LAYOUT'!$W:$W,OB!$A:$A,0)),"")
A25: =IFERROR(INDEX(OB!$G:$G,MATCH('aSC LAYOUT'!$B:$B,OB!$A:$A,0)),"") | C25: =IFERROR(INDEX(OB!$B:$B,MATCH('aSC LAYOUT'!$B:$B,OB!$A:$A,0)),"") | E25: =IFERROR(INDEX(OB!$C:$C,MATCH('aSC LAYOUT'!$B:$B,OB!$A:$A,0)),"") | F25: =IFERROR(INDEX(OB!$K:$K,MATCH('aSC LAYOUT'!$B:$B,OB!$A:$A,0)),"") | G25: =IF(C25="","",(MROUND(IF(E25<=0,0,60/E25),5))) | I25: WS | P25: WS | R25: =IF(V25="","",(MROUND(IF(T25<=0,0,60/T25),5))) | S25: =IFERROR(INDEX(OB!$K:$K,MATCH('aSC LAYOUT'!$W:$W,OB!$A:$A,0)),"") | T25: =IFERROR(INDEX(OB!$C:$C,MATCH('aSC LAYOUT'!$W:$W,OB!$A:$A,0)),"") | V25: =IFERROR(INDEX(OB!$B:$B,MATCH('aSC LAYOUT'!$W:$W,OB!$A:$A,0)),"") | X25: =IFERROR(INDEX(OB!$G:$G,MATCH('aSC LAYOUT'!$W:$W,OB!$A:$A,0)),"")
A26: =IFERROR(INDEX(OB!$G:$G,MATCH('aSC LAYOUT'!$B:$B,OB!$A:$A,0)),"") | C26: =IFERROR(INDEX(OB!$B:$B,MATCH('aSC LAYOUT'!$B:$B,OB!$A:$A,0)),"") | E26: =IFERROR(INDEX(OB!$C:$C,MATCH('aSC LAYOUT'!$B:$B,OB!$A:$A,0)),"") | F26: =IFERROR(INDEX(OB!$K:$K,MATCH('aSC LAYOUT'!$B:$B,OB!$A:$A,0)),"") | G26: =IF(C26="","",(MROUND(IF(E26<=0,0,60/E26),5))) | H26: =F27 -> 0 | I26: =+P26+1 -> 84 | P26: =+P31+1 -> 83 | Q26: =S27 -> 0 | R26: =IF(V26="","",(MROUND(IF(T26<=0,0,60/T26),5))) | S26: =IFERROR(INDEX(OB!$K:$K,MATCH('aSC LAYOUT'!$W:$W,OB!$A:$A,0)),"") | T26: =IFERROR(INDEX(OB!$C:$C,MATCH('aSC LAYOUT'!$W:$W,OB!$A:$A,0)),"") | V26: =IFERROR(INDEX(OB!$B:$B,MATCH('aSC LAYOUT'!$W:$W,OB!$A:$A,0)),"") | X26: =IFERROR(INDEX(OB!$G:$G,MATCH('aSC LAYOUT'!$W:$W,OB!$A:$A,0)),"")
E27: =SUM(E24:E26) -> 0 | F27: =SUM(F24:F26) -> 0 | S27: =SUM(S24:S26) -> 0 | T27: =SUM(T24:T26) -> 0
A29: =IFERROR(INDEX(OB!$G:$G,MATCH('aSC LAYOUT'!$B:$B,OB!$A:$A,0)),"") | B29: =+B34+1 -> 105 | C29: =IFERROR(INDEX(OB!$B:$B,MATCH('aSC LAYOUT'!$B:$B,OB!$A:$A,0)),"") | E29: =IFERROR(INDEX(OB!$C:$C,MATCH('aSC LAYOUT'!$B:$B,OB!$A:$A,0)),"") | F29: =IFERROR(INDEX(OB!$K:$K,MATCH('aSC LAYOUT'!$B:$B,OB!$A:$A,0)),"") | G29: =IF(C29="","",(MROUND(IF(E29<=0,0,60/E29),5))) | H29: =E32 -> 0 | Q29: =T32 -> 0 | R29: =IF(V29="","",(MROUND(IF(T29<=0,0,60/T29),5))) | S29: =IFERROR(INDEX(OB!$K:$K,MATCH('aSC LAYOUT'!$W:$W,OB!$A:$A,0)),"") | T29: =IFERROR(INDEX(OB!$C:$C,MATCH('aSC LAYOUT'!$W:$W,OB!$A:$A,0)),"") | V29: =IFERROR(INDEX(OB!$B:$B,MATCH('aSC LAYOUT'!$W:$W,OB!$A:$A,0)),"") | W29: =+B29+1 -> 106 | X29: =IFERROR(INDEX(OB!$G:$G,MATCH('aSC LAYOUT'!$W:$W,OB!$A:$A,0)),"")
A30: =IFERROR(INDEX(OB!$G:$G,MATCH('aSC LAYOUT'!$B:$B,OB!$A:$A,0)),"") | C30: =IFERROR(INDEX(OB!$B:$B,MATCH('aSC LAYOUT'!$B:$B,OB!$A:$A,0)),"") | E30: =IFERROR(INDEX(OB!$C:$C,MATCH('aSC LAYOUT'!$B:$B,OB!$A:$A,0)),"") | F30: =IFERROR(INDEX(OB!$K:$K,MATCH('aSC LAYOUT'!$B:$B,OB!$A:$A,0)),"") | G30: =IF(C30="","",(MROUND(IF(E30<=0,0,60/E30),5))) | I30: WS | P30: WS | R30: =IF(V30="","",(MROUND(IF(T30<=0,0,60/T30),5))) | S30: =IFERROR(INDEX(OB!$K:$K,MATCH('aSC LAYOUT'!$W:$W,OB!$A:$A,0)),"") | T30: =IFERROR(INDEX(OB!$C:$C,MATCH('aSC LAYOUT'!$W:$W,OB!$A:$A,0)),"") | V30: =IFERROR(INDEX(OB!$B:$B,MATCH('aSC LAYOUT'!$W:$W,OB!$A:$A,0)),"") | X30: =IFERROR(INDEX(OB!$G:$G,MATCH('aSC LAYOUT'!$W:$W,OB!$A:$A,0)),"")
A31: =IFERROR(INDEX(OB!$G:$G,MATCH('aSC LAYOUT'!$B:$B,OB!$A:$A,0)),"") | C31: =IFERROR(INDEX(OB!$B:$B,MATCH('aSC LAYOUT'!$B:$B,OB!$A:$A,0)),"") | E31: =IFERROR(INDEX(OB!$C:$C,MATCH('aSC LAYOUT'!$B:$B,OB!$A:$A,0)),"") | F31: =IFERROR(INDEX(OB!$K:$K,MATCH('aSC LAYOUT'!$B:$B,OB!$A:$A,0)),"") | G31: =IF(C31="","",(MROUND(IF(E31<=0,0,60/E31),5))) | H31: =F32 -> 0 | I31: =+I36+1 -> 81 | P31: =+I31+1 -> 82 | Q31: =S32 -> 0 | R31: =IF(V31="","",(MROUND(IF(T31<=0,0,60/T31),5))) | S31: =IFERROR(INDEX(OB!$K:$K,MATCH('aSC LAYOUT'!$W:$W,OB!$A:$A,0)),"") | T31: =IFERROR(INDEX(OB!$C:$C,MATCH('aSC LAYOUT'!$W:$W,OB!$A:$A,0)),"") | V31: =IFERROR(INDEX(OB!$B:$B,MATCH('aSC LAYOUT'!$W:$W,OB!$A:$A,0)),"") | X31: =IFERROR(INDEX(OB!$G:$G,MATCH('aSC LAYOUT'!$W:$W,OB!$A:$A,0)),"")
E32: =SUM(E29:E31) -> 0 | F32: =SUM(F29:F31) -> 0 | S32: =SUM(S29:S31) -> 0 | T32: =SUM(T29:T31) -> 0
A34: =IFERROR(INDEX(OB!$G:$G,MATCH('aSC LAYOUT'!$B:$B,OB!$A:$A,0)),"") | B34: =+W34+1 -> 104 | C34: =IFERROR(INDEX(OB!$B:$B,MATCH('aSC LAYOUT'!$B:$B,OB!$A:$A,0)),"") | E34: =IFERROR(INDEX(OB!$C:$C,MATCH('aSC LAYOUT'!$B:$B,OB!$A:$A,0)),"") | F34: =IFERROR(INDEX(OB!$K:$K,MATCH('aSC LAYOUT'!$B:$B,OB!$A:$A,0)),"") | G34: =IF(C34="","",(MROUND(IF(E34<=0,0,60/E34),5))) | H34: =E37 -> 0 | Q34: =T37 -> 0 | R34: =IF(V34="","",(MROUND(IF(T34<=0,0,60/T34),5))) | S34: =IFERROR(INDEX(OB!$K:$K,MATCH('aSC LAYOUT'!$W:$W,OB!$A:$A,0)),"") | T34: =IFERROR(INDEX(OB!$C:$C,MATCH('aSC LAYOUT'!$W:$W,OB!$A:$A,0)),"") | V34: =IFERROR(INDEX(OB!$B:$B,MATCH('aSC LAYOUT'!$W:$W,OB!$A:$A,0)),"") | W34: =+W39+1 -> 103 | X34: =IFERROR(INDEX(OB!$G:$G,MATCH('aSC LAYOUT'!$W:$W,OB!$A:$A,0)),"")
A35: =IFERROR(INDEX(OB!$G:$G,MATCH('aSC LAYOUT'!$B:$B,OB!$A:$A,0)),"") | C35: =IFERROR(INDEX(OB!$B:$B,MATCH('aSC LAYOUT'!$B:$B,OB!$A:$A,0)),"") | E35: =IFERROR(INDEX(OB!$C:$C,MATCH('aSC LAYOUT'!$B:$B,OB!$A:$A,0)),"") | F35: =IFERROR(INDEX(OB!$K:$K,MATCH('aSC LAYOUT'!$B:$B,OB!$A:$A,0)),"") | G35: =IF(C35="","",(MROUND(IF(E35<=0,0,60/E35),5))) | I35: WS | P35: WS | R35: =IF(V35="","",(MROUND(IF(T35<=0,0,60/T35),5))) | S35: =IFERROR(INDEX(OB!$K:$K,MATCH('aSC LAYOUT'!$W:$W,OB!$A:$A,0)),"") | T35: =IFERROR(INDEX(OB!$C:$C,MATCH('aSC LAYOUT'!$W:$W,OB!$A:$A,0)),"") | V35: =IFERROR(INDEX(OB!$B:$B,MATCH('aSC LAYOUT'!$W:$W,OB!$A:$A,0)),"") | X35: =IFERROR(INDEX(OB!$G:$G,MATCH('aSC LAYOUT'!$W:$W,OB!$A:$A,0)),"")
A36: =IFERROR(INDEX(OB!$G:$G,MATCH('aSC LAYOUT'!$B:$B,OB!$A:$A,0)),"") | C36: =IFERROR(INDEX(OB!$B:$B,MATCH('aSC LAYOUT'!$B:$B,OB!$A:$A,0)),"") | E36: =IFERROR(INDEX(OB!$C:$C,MATCH('aSC LAYOUT'!$B:$B,OB!$A:$A,0)),"") | F36: =IFERROR(INDEX(OB!$K:$K,MATCH('aSC LAYOUT'!$B:$B,OB!$A:$A,0)),"") | G36: =IF(C36="","",(MROUND(IF(E36<=0,0,60/E36),5))) | H36: =F37 -> 0 | I36: =+P36+1 -> 80 | P36: =+P41+1 -> 79 | Q36: =S37 -> 0 | R36: =IF(V36="","",(MROUND(IF(T36<=0,0,60/T36),5))) | S36: =IFERROR(INDEX(OB!$K:$K,MATCH('aSC LAYOUT'!$W:$W,OB!$A:$A,0)),"") | T36: =IFERROR(INDEX(OB!$C:$C,MATCH('aSC LAYOUT'!$W:$W,OB!$A:$A,0)),"") | V36: =IFERROR(INDEX(OB!$B:$B,MATCH('aSC LAYOUT'!$W:$W,OB!$A:$A,0)),"") | X36: =IFERROR(INDEX(OB!$G:$G,MATCH('aSC LAYOUT'!$W:$W,OB!$A:$A,0)),"")
E37: =SUM(E34:E36) -> 0 | F37: =SUM(F34:F36) -> 0 | S37: =SUM(S34:S36) -> 0 | T37: =SUM(T34:T36) -> 0
A39: =IFERROR(INDEX(OB!$G:$G,MATCH('aSC LAYOUT'!$B:$B,OB!$A:$A,0)),"") | B39: =+B44+1 -> 101 | C39: =IFERROR(INDEX(OB!$B:$B,MATCH('aSC LAYOUT'!$B:$B,OB!$A:$A,0)),"") | E39: =IFERROR(INDEX(OB!$C:$C,MATCH('aSC LAYOUT'!$B:$B,OB!$A:$A,0)),"") | F39: =IFERROR(INDEX(OB!$K:$K,MATCH('aSC LAYOUT'!$B:$B,OB!$A:$A,0)),"") | G39: =IF(C39="","",(MROUND(IF(E39<=0,0,60/E39),5))) | H39: =E42 -> 0 | Q39: =T42 -> 0 | R39: =IF(V39="","",(MROUND(IF(T39<=0,0,60/T39),5))) | S39: =IFERROR(INDEX(OB!$K:$K,MATCH('aSC LAYOUT'!$W:$W,OB!$A:$A,0)),"") | T39: =IFERROR(INDEX(OB!$C:$C,MATCH('aSC LAYOUT'!$W:$W,OB!$A:$A,0)),"") | V39: =IFERROR(INDEX(OB!$B:$B,MATCH('aSC LAYOUT'!$W:$W,OB!$A:$A,0)),"") | W39: =+B39+1 -> 102 | X39: =IFERROR(INDEX(OB!$G:$G,MATCH('aSC LAYOUT'!$W:$W,OB!$A:$A,0)),"")
A40: =IFERROR(INDEX(OB!$G:$G,MATCH('aSC LAYOUT'!$B:$B,OB!$A:$A,0)),"") | C40: =IFERROR(INDEX(OB!$B:$B,MATCH('aSC LAYOUT'!$B:$B,OB!$A:$A,0)),"") | E40: =IFERROR(INDEX(OB!$C:$C,MATCH('aSC LAYOUT'!$B:$B,OB!$A:$A,0)),"") | F40: =IFERROR(INDEX(OB!$K:$K,MATCH('aSC LAYOUT'!$B:$B,OB!$A:$A,0)),"") | G40: =IF(C40="","",(MROUND(IF(E40<=0,0,60/E40),5))) | I40: WS | P40: WS | R40: =IF(V40="","",(MROUND(IF(T40<=0,0,60/T40),5))) | S40: =IFERROR(INDEX(OB!$K:$K,MATCH('aSC LAYOUT'!$W:$W,OB!$A:$A,0)),"") | T40: =IFERROR(INDEX(OB!$C:$C,MATCH('aSC LAYOUT'!$W:$W,OB!$A:$A,0)),"") | V40: =IFERROR(INDEX(OB!$B:$B,MATCH('aSC LAYOUT'!$W:$W,OB!$A:$A,0)),"") | X40: =IFERROR(INDEX(OB!$G:$G,MATCH('aSC LAYOUT'!$W:$W,OB!$A:$A,0)),"")
A41: =IFERROR(INDEX(OB!$G:$G,MATCH('aSC LAYOUT'!$B:$B,OB!$A:$A,0)),"") | C41: =IFERROR(INDEX(OB!$B:$B,MATCH('aSC LAYOUT'!$B:$B,OB!$A:$A,0)),"") | E41: =IFERROR(INDEX(OB!$C:$C,MATCH('aSC LAYOUT'!$B:$B,OB!$A:$A,0)),"") | F41: =IFERROR(INDEX(OB!$K:$K,MATCH('aSC LAYOUT'!$B:$B,OB!$A:$A,0)),"") | G41: =IF(C41="","",(MROUND(IF(E41<=0,0,60/E41),5))) | H41: =F42 -> 0 | I41: =+I46+1 -> 77 | P41: =+I41+1 -> 78 | Q41: =S42 -> 0 | R41: =IF(V41="","",(MROUND(IF(T41<=0,0,60/T41),5))) | S41: =IFERROR(INDEX(OB!$K:$K,MATCH('aSC LAYOUT'!$W:$W,OB!$A:$A,0)),"") | T41: =IFERROR(INDEX(OB!$C:$C,MATCH('aSC LAYOUT'!$W:$W,OB!$A:$A,0)),"") | V41: =IFERROR(INDEX(OB!$B:$B,MATCH('aSC LAYOUT'!$W:$W,OB!$A:$A,0)),"") | X41: =IFERROR(INDEX(OB!$G:$G,MATCH('aSC LAYOUT'!$W:$W,OB!$A:$A,0)),"")
E42: =SUM(E39:E41) -> 0 | F42: =SUM(F39:F41) -> 0 | S42: =SUM(S39:S41) -> 0 | T42: =SUM(T39:T41) -> 0
A44: =IFERROR(INDEX(OB!$G:$G,MATCH('aSC LAYOUT'!$B:$B,OB!$A:$A,0)),"") | B44: =+W44+1 -> 100 | C44: =IFERROR(INDEX(OB!$B:$B,MATCH('aSC LAYOUT'!$B:$B,OB!$A:$A,0)),"") | E44: =IFERROR(INDEX(OB!$C:$C,MATCH('aSC LAYOUT'!$B:$B,OB!$A:$A,0)),"") | F44: =IFERROR(INDEX(OB!$K:$K,MATCH('aSC LAYOUT'!$B:$B,OB!$A:$A,0)),"") | G44: =IF(C44="","",(MROUND(IF(E44<=0,0,60/E44),5))) | H44: =E47 -> 0 | Q44: =T47 -> 0 | R44: =IF(V44="","",(MROUND(IF(T44<=0,0,60/T44),5))) | S44: =IFERROR(INDEX(OB!$K:$K,MATCH('aSC LAYOUT'!$W:$W,OB!$A:$A,0)),"") | T44: =IFERROR(INDEX(OB!$C:$C,MATCH('aSC LAYOUT'!$W:$W,OB!$A:$A,0)),"") | V44: =IFERROR(INDEX(OB!$B:$B,MATCH('aSC LAYOUT'!$W:$W,OB!$A:$A,0)),"") | W44: =+W49+1 -> 99 | X44: =IFERROR(INDEX(OB!$G:$G,MATCH('aSC LAYOUT'!$W:$W,OB!$A:$A,0)),"")
A45: =IFERROR(INDEX(OB!$G:$G,MATCH('aSC LAYOUT'!$B:$B,OB!$A:$A,0)),"") | C45: =IFERROR(INDEX(OB!$B:$B,MATCH('aSC LAYOUT'!$B:$B,OB!$A:$A,0)),"") | E45: =IFERROR(INDEX(OB!$C:$C,MATCH('aSC LAYOUT'!$B:$B,OB!$A:$A,0)),"") | F45: =IFERROR(INDEX(OB!$K:$K,MATCH('aSC LAYOUT'!$B:$B,OB!$A:$A,0)),"") | G45: =IF(C45="","",(MROUND(IF(E45<=0,0,60/E45),5))) | I45: WS | P45: WS | R45: =IF(V45="","",(MROUND(IF(T45<=0,0,60/T45),5))) | S45: =IFERROR(INDEX(OB!$K:$K,MATCH('aSC LAYOUT'!$W:$W,OB!$A:$A,0)),"") | T45: =IFERROR(INDEX(OB!$C:$C,MATCH('aSC LAYOUT'!$W:$W,OB!$A:$A,0)),"") | V45: =IFERROR(INDEX(OB!$B:$B,MATCH('aSC LAYOUT'!$W:$W,OB!$A:$A,0)),"") | X45: =IFERROR(INDEX(OB!$G:$G,MATCH('aSC LAYOUT'!$W:$W,OB!$A:$A,0)),"")
A46: =IFERROR(INDEX(OB!$G:$G,MATCH('aSC LAYOUT'!$B:$B,OB!$A:$A,0)),"") | C46: =IFERROR(INDEX(OB!$B:$B,MATCH('aSC LAYOUT'!$B:$B,OB!$A:$A,0)),"") | E46: =IFERROR(INDEX(OB!$C:$C,MATCH('aSC LAYOUT'!$B:$B,OB!$A:$A,0)),"") | F46: =IFERROR(INDEX(OB!$K:$K,MATCH('aSC LAYOUT'!$B:$B,OB!$A:$A,0)),"") | G46: =IF(C46="","",(MROUND(IF(E46<=0,0,60/E46),5))) | H46: =F47 -> 0 | I46: =+P46+1 -> 76 | P46: =+P51+1 -> 75 | Q46: =S47 -> 0 | R46: =IF(V46="","",(MROUND(IF(T46<=0,0,60/T46),5))) | S46: =IFERROR(INDEX(OB!$K:$K,MATCH('aSC LAYOUT'!$W:$W,OB!$A:$A,0)),"") | T46: =IFERROR(INDEX(OB!$C:$C,MATCH('aSC LAYOUT'!$W:$W,OB!$A:$A,0)),"") | V46: =IFERROR(INDEX(OB!$B:$B,MATCH('aSC LAYOUT'!$W:$W,OB!$A:$A,0)),"") | X46: =IFERROR(INDEX(OB!$G:$G,MATCH('aSC LAYOUT'!$W:$W,OB!$A:$A,0)),"")
E47: =SUM(E44:E46) -> 0 | F47: =SUM(F44:F46) -> 0 | S47: =SUM(S44:S46) -> 0 | T47: =SUM(T44:T46) -> 0
A49: =IFERROR(INDEX(OB!$G:$G,MATCH('aSC LAYOUT'!$B:$B,OB!$A:$A,0)),"") | B49: =+B54+1 -> 97 | C49: =IFERROR(INDEX(OB!$B:$B,MATCH('aSC LAYOUT'!$B:$B,OB!$A:$A,0)),"") | E49: =IFERROR(INDEX(OB!$C:$C,MATCH('aSC LAYOUT'!$B:$B,OB!$A:$A,0)),"") | F49: =IFERROR(INDEX(OB!$K:$K,MATCH('aSC LAYOUT'!$B:$B,OB!$A:$A,0)),"") | G49: =IF(C49="","",(MROUND(IF(E49<=0,0,60/E49),5))) | H49: =E52 -> 0 | Q49: =T52 -> 0 | R49: =IF(V49="","",(MROUND(IF(T49<=0,0,60/T49),5))) | S49: =IFERROR(INDEX(OB!$K:$K,MATCH('aSC LAYOUT'!$W:$W,OB!$A:$A,0)),"") | T49: =IFERROR(INDEX(OB!$C:$C,MATCH('aSC LAYOUT'!$W:$W,OB!$A:$A,0)),"") | V49: =IFERROR(INDEX(OB!$B:$B,MATCH('aSC LAYOUT'!$W:$W,OB!$A:$A,0)),"") | W49: =+B49+1 -> 98 | X49: =IFERROR(INDEX(OB!$G:$G,MATCH('aSC LAYOUT'!$W:$W,OB!$A:$A,0)),"")
A50: =IFERROR(INDEX(OB!$G:$G,MATCH('aSC LAYOUT'!$B:$B,OB!$A:$A,0)),"") | C50: =IFERROR(INDEX(OB!$B:$B,MATCH('aSC LAYOUT'!$B:$B,OB!$A:$A,0)),"") | E50: =IFERROR(INDEX(OB!$C:$C,MATCH('aSC LAYOUT'!$B:$B,OB!$A:$A,0)),"") | F50: =IFERROR(INDEX(OB!$K:$K,MATCH('aSC LAYOUT'!$B:$B,OB!$A:$A,0)),"") | G50: =IF(C50="","",(MROUND(IF(E50<=0,0,60/E50),5))) | I50: WS | P50: WS | R50: =IF(V50="","",(MROUND(IF(T50<=0,0,60/T50),5))) | S50: =IFERROR(INDEX(OB!$K:$K,MATCH('aSC LAYOUT'!$W:$W,OB!$A:$A,0)),"") | T50: =IFERROR(INDEX(OB!$C:$C,MATCH('aSC LAYOUT'!$W:$W,OB!$A:$A,0)),"") | V50: =IFERROR(INDEX(OB!$B:$B,MATCH('aSC LAYOUT'!$W:$W,OB!$A:$A,0)),"") | X50: =IFERROR(INDEX(OB!$G:$G,MATCH('aSC LAYOUT'!$W:$W,OB!$A:$A,0)),"")
A51: =IFERROR(INDEX(OB!$G:$G,MATCH('aSC LAYOUT'!$B:$B,OB!$A:$A,0)),"") | C51: =IFERROR(INDEX(OB!$B:$B,MATCH('aSC LAYOUT'!$B:$B,OB!$A:$A,0)),"") | E51: =IFERROR(INDEX(OB!$C:$C,MATCH('aSC LAYOUT'!$B:$B,OB!$A:$A,0)),"") | F51: =IFERROR(INDEX(OB!$K:$K,MATCH('aSC LAYOUT'!$B:$B,OB!$A:$A,0)),"") | G51: =IF(C51="","",(MROUND(IF(E51<=0,0,60/E51),5))) | H51: =F52 -> 0 | I51: =+I56+1 -> 73 | P51: =+I51+1 -> 74 | Q51: =S52 -> 0 | R51: =IF(V51="","",(MROUND(IF(T51<=0,0,60/T51),5))) | S51: =IFERROR(INDEX(OB!$K:$K,MATCH('aSC LAYOUT'!$W:$W,OB!$A:$A,0)),"") | T51: =IFERROR(INDEX(OB!$C:$C,MATCH('aSC LAYOUT'!$W:$W,OB!$A:$A,0)),"") | V51: =IFERROR(INDEX(OB!$B:$B,MATCH('aSC LAYOUT'!$W:$W,OB!$A:$A,0)),"") | X51: =IFERROR(INDEX(OB!$G:$G,MATCH('aSC LAYOUT'!$W:$W,OB!$A:$A,0)),"")
E52: =SUM(E49:E51) -> 0 | F52: =SUM(F49:F51) -> 0 | S52: =SUM(S49:S51) -> 0 | T52: =SUM(T49:T51) -> 0
A54: =IFERROR(INDEX(OB!$G:$G,MATCH('aSC LAYOUT'!$B:$B,OB!$A:$A,0)),"") | B54: =+W54+1 -> 96 | C54: =IFERROR(INDEX(OB!$B:$B,MATCH('aSC LAYOUT'!$B:$B,OB!$A:$A,0)),"") | E54: =IFERROR(INDEX(OB!$C:$C,MATCH('aSC LAYOUT'!$B:$B,OB!$A:$A,0)),"") | F54: =IFERROR(INDEX(OB!$K:$K,MATCH('aSC LAYOUT'!$B:$B,OB!$A:$A,0)),"") | G54: =IF(C54="","",(MROUND(IF(E54<=0,0,60/E54),5))) | H54: =E57 -> 0 | Q54: =T57 -> 0 | R54: =IF(V54="","",(MROUND(IF(T54<=0,0,60/T54),5))) | S54: =IFERROR(INDEX(OB!$K:$K,MATCH('aSC LAYOUT'!$W:$W,OB!$A:$A,0)),"") | T54: =IFERROR(INDEX(OB!$C:$C,MATCH('aSC LAYOUT'!$W:$W,OB!$A:$A,0)),"") | V54: =IFERROR(INDEX(OB!$B:$B,MATCH('aSC LAYOUT'!$W:$W,OB!$A:$A,0)),"") | W54: =+W59+1 -> 95 | X54: =IFERROR(INDEX(OB!$G:$G,MATCH('aSC LAYOUT'!$W:$W,OB!$A:$A,0)),"")
A55: =IFERROR(INDEX(OB!$G:$G,MATCH('aSC LAYOUT'!$B:$B,OB!$A:$A,0)),"") | C55: =IFERROR(INDEX(OB!$B:$B,MATCH('aSC LAYOUT'!$B:$B,OB!$A:$A,0)),"") | E55: =IFERROR(INDEX(OB!$C:$C,MATCH('aSC LAYOUT'!$B:$B,OB!$A:$A,0)),"") | F55: =IFERROR(INDEX(OB!$K:$K,MATCH('aSC LAYOUT'!$B:$B,OB!$A:$A,0)),"") | G55: =IF(C55="","",(MROUND(IF(E55<=0,0,60/E55),5))) | I55: WS | P55: WS | R55: =IF(V55="","",(MROUND(IF(T55<=0,0,60/T55),5))) | S55: =IFERROR(INDEX(OB!$K:$K,MATCH('aSC LAYOUT'!$W:$W,OB!$A:$A,0)),"") | T55: =IFERROR(INDEX(OB!$C:$C,MATCH('aSC LAYOUT'!$W:$W,OB!$A:$A,0)),"") | V55: =IFERROR(INDEX(OB!$B:$B,MATCH('aSC LAYOUT'!$W:$W,OB!$A:$A,0)),"") | X55: =IFERROR(INDEX(OB!$G:$G,MATCH('aSC LAYOUT'!$W:$W,OB!$A:$A,0)),"")
A56: =IFERROR(INDEX(OB!$G:$G,MATCH('aSC LAYOUT'!$B:$B,OB!$A:$A,0)),"") | C56: =IFERROR(INDEX(OB!$B:$B,MATCH('aSC LAYOUT'!$B:$B,OB!$A:$A,0)),"") | E56: =IFERROR(INDEX(OB!$C:$C,MATCH('aSC LAYOUT'!$B:$B,OB!$A:$A,0)),"") | F56: =IFERROR(INDEX(OB!$K:$K,MATCH('aSC LAYOUT'!$B:$B,OB!$A:$A,0)),"") | G56: =IF(C56="","",(MROUND(IF(E56<=0,0,60/E56),5))) | H56: =F57 -> 0 | I56: =+P56+1 -> 72 | P56: =+P61+1 -> 71 | Q56: =S57 -> 0 | R56: =IF(V56="","",(MROUND(IF(T56<=0,0,60/T56),5))) | S56: =IFERROR(INDEX(OB!$K:$K,MATCH('aSC LAYOUT'!$W:$W,OB!$A:$A,0)),"") | T56: =IFERROR(INDEX(OB!$C:$C,MATCH('aSC LAYOUT'!$W:$W,OB!$A:$A,0)),"") | V56: =IFERROR(INDEX(OB!$B:$B,MATCH('aSC LAYOUT'!$W:$W,OB!$A:$A,0)),"") | X56: =IFERROR(INDEX(OB!$G:$G,MATCH('aSC LAYOUT'!$W:$W,OB!$A:$A,0)),"")
E57: =SUM(E54:E56) -> 0 | F57: =SUM(F54:F56) -> 0 | S57: =SUM(S54:S56) -> 0 | T57: =SUM(T54:T56) -> 0
A59: =IFERROR(INDEX(OB!$G:$G,MATCH('aSC LAYOUT'!$B:$B,OB!$A:$A,0)),"") | B59: =+B64+1 -> 93 | C59: =IFERROR(INDEX(OB!$B:$B,MATCH('aSC LAYOUT'!$B:$B,OB!$A:$A,0)),"") | E59: =IFERROR(INDEX(OB!$C:$C,MATCH('aSC LAYOUT'!$B:$B,OB!$A:$A,0)),"") | F59: =IFERROR(INDEX(OB!$K:$K,MATCH('aSC LAYOUT'!$B:$B,OB!$A:$A,0)),"") | G59: =IF(C59="","",(MROUND(IF(E59<=0,0,60/E59),5))) | H59: =E62 -> 0 | Q59: =T62 -> 0 | R59: =IF(V59="","",(MROUND(IF(T59<=0,0,60/T59),5))) | S59: =IFERROR(INDEX(OB!$K:$K,MATCH('aSC LAYOUT'!$W:$W,OB!$A:$A,0)),"") | T59: =IFERROR(INDEX(OB!$C:$C,MATCH('aSC LAYOUT'!$W:$W,OB!$A:$A,0)),"") | V59: =IFERROR(INDEX(OB!$B:$B,MATCH('aSC LAYOUT'!$W:$W,OB!$A:$A,0)),"") | W59: =+B59+1 -> 94 | X59: =IFERROR(INDEX(OB!$G:$G,MATCH('aSC LAYOUT'!$W:$W,OB!$A:$A,0)),"")
A60: =IFERROR(INDEX(OB!$G:$G,MATCH('aSC LAYOUT'!$B:$B,OB!$A:$A,0)),"") | C60: =IFERROR(INDEX(OB!$B:$B,MATCH('aSC LAYOUT'!$B:$B,OB!$A:$A,0)),"") | E60: =IFERROR(INDEX(OB!$C:$C,MATCH('aSC LAYOUT'!$B:$B,OB!$A:$A,0)),"") | F60: =IFERROR(INDEX(OB!$K:$K,MATCH('aSC LAYOUT'!$B:$B,OB!$A:$A,0)),"") | G60: =IF(C60="","",(MROUND(IF(E60<=0,0,60/E60),5))) | I60: WS | P60: WS | R60: =IF(V60="","",(MROUND(IF(T60<=0,0,60/T60),5))) | S60: =IFERROR(INDEX(OB!$K:$K,MATCH('aSC LAYOUT'!$W:$W,OB!$A:$A,0)),"") | T60: =IFERROR(INDEX(OB!$C:$C,MATCH('aSC LAYOUT'!$W:$W,OB!$A:$A,0)),"") | V60: =IFERROR(INDEX(OB!$B:$B,MATCH('aSC LAYOUT'!$W:$W,OB!$A:$A,0)),"") | X60: =IFERROR(INDEX(OB!$G:$G,MATCH('aSC LAYOUT'!$W:$W,OB!$A:$A,0)),"")
A61: =IFERROR(INDEX(OB!$G:$G,MATCH('aSC LAYOUT'!$B:$B,OB!$A:$A,0)),"") | C61: =IFERROR(INDEX(OB!$B:$B,MATCH('aSC LAYOUT'!$B:$B,OB!$A:$A,0)),"") | E61: =IFERROR(INDEX(OB!$C:$C,MATCH('aSC LAYOUT'!$B:$B,OB!$A:$A,0)),"") | F61: =IFERROR(INDEX(OB!$K:$K,MATCH('aSC LAYOUT'!$B:$B,OB!$A:$A,0)),"") | G61: =IF(C61="","",(MROUND(IF(E61<=0,0,60/E61),5))) | H61: =F62 -> 0 | I61: =+I66+1 -> 69 | P61: =+I61+1 -> 70 | Q61: =S62 -> 0 | R61: =IF(V61="","",(MROUND(IF(T61<=0,0,60/T61),5))) | S61: =IFERROR(INDEX(OB!$K:$K,MATCH('aSC LAYOUT'!$W:$W,OB!$A:$A,0)),"") | T61: =IFERROR(INDEX(OB!$C:$C,MATCH('aSC LAYOUT'!$W:$W,OB!$A:$A,0)),"") | V61: =IFERROR(INDEX(OB!$B:$B,MATCH('aSC LAYOUT'!$W:$W,OB!$A:$A,0)),"") | X61: =IFERROR(INDEX(OB!$G:$G,MATCH('aSC LAYOUT'!$W:$W,OB!$A:$A,0)),"")
E62: =SUM(E59:E61) -> 0 | F62: =SUM(F59:F61) -> 0 | S62: =SUM(S59:S61) -> 0 | T62: =SUM(T59:T61) -> 0
A64: =IFERROR(INDEX(OB!$G:$G,MATCH('aSC LAYOUT'!$B:$B,OB!$A:$A,0)),"") | B64: =+W64+1 -> 92 | C64: =IFERROR(INDEX(OB!$B:$B,MATCH('aSC LAYOUT'!$B:$B,OB!$A:$A,0)),"") | E64: =IFERROR(INDEX(OB!$C:$C,MATCH('aSC LAYOUT'!$B:$B,OB!$A:$A,0)),"") | F64: =IFERROR(INDEX(OB!$K:$K,MATCH('aSC LAYOUT'!$B:$B,OB!$A:$A,0)),"") | G64: =IF(C64="","",(MROUND(IF(E64<=0,0,60/E64),5))) | H64: =E67 -> 0 | Q64: =T67 -> 0 | R64: =IF(V64="","",(MROUND(IF(T64<=0,0,60/T64),5))) | S64: =IFERROR(INDEX(OB!$K:$K,MATCH('aSC LAYOUT'!$W:$W,OB!$A:$A,0)),"") | T64: =IFERROR(INDEX(OB!$C:$C,MATCH('aSC LAYOUT'!$W:$W,OB!$A:$A,0)),"") | V64: =IFERROR(INDEX(OB!$B:$B,MATCH('aSC LAYOUT'!$W:$W,OB!$A:$A,0)),"") | W64: =+W69+1 -> 91 | X64: =IFERROR(INDEX(OB!$G:$G,MATCH('aSC LAYOUT'!$W:$W,OB!$A:$A,0)),"")
A65: =IFERROR(INDEX(OB!$G:$G,MATCH('aSC LAYOUT'!$B:$B,OB!$A:$A,0)),"") | C65: =IFERROR(INDEX(OB!$B:$B,MATCH('aSC LAYOUT'!$B:$B,OB!$A:$A,0)),"") | E65: =IFERROR(INDEX(OB!$C:$C,MATCH('aSC LAYOUT'!$B:$B,OB!$A:$A,0)),"") | F65: =IFERROR(INDEX(OB!$K:$K,MATCH('aSC LAYOUT'!$B:$B,OB!$A:$A,0)),"") | G65: =IF(C65="","",(MROUND(IF(E65<=0,0,60/E65),5))) | I65: WS | P65: WS | R65: =IF(V65="","",(MROUND(IF(T65<=0,0,60/T65),5))) | S65: =IFERROR(INDEX(OB!$K:$K,MATCH('aSC LAYOUT'!$W:$W,OB!$A:$A,0)),"") | T65: =IFERROR(INDEX(OB!$C:$C,MATCH('aSC LAYOUT'!$W:$W,OB!$A:$A,0)),"") | V65: =IFERROR(INDEX(OB!$B:$B,MATCH('aSC LAYOUT'!$W:$W,OB!$A:$A,0)),"") | X65: =IFERROR(INDEX(OB!$G:$G,MATCH('aSC LAYOUT'!$W:$W,OB!$A:$A,0)),"")
A66: =IFERROR(INDEX(OB!$G:$G,MATCH('aSC LAYOUT'!$B:$B,OB!$A:$A,0)),"") | C66: =IFERROR(INDEX(OB!$B:$B,MATCH('aSC LAYOUT'!$B:$B,OB!$A:$A,0)),"") | E66: =IFERROR(INDEX(OB!$C:$C,MATCH('aSC LAYOUT'!$B:$B,OB!$A:$A,0)),"") | F66: =IFERROR(INDEX(OB!$K:$K,MATCH('aSC LAYOUT'!$B:$B,OB!$A:$A,0)),"") | G66: =IF(C66="","",(MROUND(IF(E66<=0,0,60/E66),5))) | H66: =F67 -> 0 | I66: =+P66+1 -> 68 | P66: =+P71+1 -> 67 | Q66: =S67 -> 0 | R66: =IF(V66="","",(MROUND(IF(T66<=0,0,60/T66),5))) | S66: =IFERROR(INDEX(OB!$K:$K,MATCH('aSC LAYOUT'!$W:$W,OB!$A:$A,0)),"") | T66: =IFERROR(INDEX(OB!$C:$C,MATCH('aSC LAYOUT'!$W:$W,OB!$A:$A,0)),"") | V66: =IFERROR(INDEX(OB!$B:$B,MATCH('aSC LAYOUT'!$W:$W,OB!$A:$A,0)),"") | X66: =IFERROR(INDEX(OB!$G:$G,MATCH('aSC LAYOUT'!$W:$W,OB!$A:$A,0)),"")
E67: =SUM(E64:E66) -> 0 | F67: =SUM(F64:F66) -> 0 | S67: =SUM(S64:S66) -> 0 | T67: =SUM(T64:T66) -> 0
A69: =IFERROR(INDEX(OB!$G:$G,MATCH('aSC LAYOUT'!$B:$B,OB!$A:$A,0)),"") | B69: =+B74+1 -> 89 | C69: =IFERROR(INDEX(OB!$B:$B,MATCH('aSC LAYOUT'!$B:$B,OB!$A:$A,0)),"") | E69: =IFERROR(INDEX(OB!$C:$C,MATCH('aSC LAYOUT'!$B:$B,OB!$A:$A,0)),"") | F69: =IFERROR(INDEX(OB!$K:$K,MATCH('aSC LAYOUT'!$B:$B,OB!$A:$A,0)),"") | G69: =IF(C69="","",(MROUND(IF(E69<=0,0,60/E69),5))) | H69: =E72 -> 0 | Q69: =T72 -> 0 | R69: =IF(V69="","",(MROUND(IF(T69<=0,0,60/T69),5))) | S69: =IFERROR(INDEX(OB!$K:$K,MATCH('aSC LAYOUT'!$W:$W,OB!$A:$A,0)),"") | T69: =IFERROR(INDEX(OB!$C:$C,MATCH('aSC LAYOUT'!$W:$W,OB!$A:$A,0)),"") | V69: =IFERROR(INDEX(OB!$B:$B,MATCH('aSC LAYOUT'!$W:$W,OB!$A:$A,0)),"") | W69: =+B69+1 -> 90 | X69: =IFERROR(INDEX(OB!$G:$G,MATCH('aSC LAYOUT'!$W:$W,OB!$A:$A,0)),"")
A70: =IFERROR(INDEX(OB!$G:$G,MATCH('aSC LAYOUT'!$B:$B,OB!$A:$A,0)),"") | C70: =IFERROR(INDEX(OB!$B:$B,MATCH('aSC LAYOUT'!$B:$B,OB!$A:$A,0)),"") | E70: =IFERROR(INDEX(OB!$C:$C,MATCH('aSC LAYOUT'!$B:$B,OB!$A:$A,0)),"") | F70: =IFERROR(INDEX(OB!$K:$K,MATCH('aSC LAYOUT'!$B:$B,OB!$A:$A,0)),"") | G70: =IF(C70="","",(MROUND(IF(E70<=0,0,60/E70),5))) | I70: WS | P70: WS | R70: =IF(V70="","",(MROUND(IF(T70<=0,0,60/T70),5))) | S70: =IFERROR(INDEX(OB!$K:$K,MATCH('aSC LAYOUT'!$W:$W,OB!$A:$A,0)),"") | T70: =IFERROR(INDEX(OB!$C:$C,MATCH('aSC LAYOUT'!$W:$W,OB!$A:$A,0)),"") | V70: =IFERROR(INDEX(OB!$B:$B,MATCH('aSC LAYOUT'!$W:$W,OB!$A:$A,0)),"") | X70: =IFERROR(INDEX(OB!$G:$G,MATCH('aSC LAYOUT'!$W:$W,OB!$A:$A,0)),"")
A71: =IFERROR(INDEX(OB!$G:$G,MATCH('aSC LAYOUT'!$B:$B,OB!$A:$A,0)),"") | C71: =IFERROR(INDEX(OB!$B:$B,MATCH('aSC LAYOUT'!$B:$B,OB!$A:$A,0)),"") | E71: =IFERROR(INDEX(OB!$C:$C,MATCH('aSC LAYOUT'!$B:$B,OB!$A:$A,0)),"") | F71: =IFERROR(INDEX(OB!$K:$K,MATCH('aSC LAYOUT'!$B:$B,OB!$A:$A,0)),"") | G71: =IF(C71="","",(MROUND(IF(E71<=0,0,60/E71),5))) | H71: =F72 -> 0 | I71: =+I76+1 -> 65 | P71: =+I71+1 -> 66 | Q71: =S72 -> 0 | R71: =IF(V71="","",(MROUND(IF(T71<=0,0,60/T71),5))) | S71: =IFERROR(INDEX(OB!$K:$K,MATCH('aSC LAYOUT'!$W:$W,OB!$A:$A,0)),"") | T71: =IFERROR(INDEX(OB!$C:$C,MATCH('aSC LAYOUT'!$W:$W,OB!$A:$A,0)),"") | V71: =IFERROR(INDEX(OB!$B:$B,MATCH('aSC LAYOUT'!$W:$W,OB!$A:$A,0)),"") | X71: =IFERROR(INDEX(OB!$G:$G,MATCH('aSC LAYOUT'!$W:$W,OB!$A:$A,0)),"")
E72: =SUM(E69:E71) -> 0 | F72: =SUM(F69:F71) -> 0 | S72: =SUM(S69:S71) -> 0 | T72: =SUM(T69:T71) -> 0
A74: =IFERROR(INDEX(OB!$G:$G,MATCH('aSC LAYOUT'!$B:$B,OB!$A:$A,0)),"") | B74: =+W74+1 -> 88 | C74: =IFERROR(INDEX(OB!$B:$B,MATCH('aSC LAYOUT'!$B:$B,OB!$A:$A,0)),"") | E74: =IFERROR(INDEX(OB!$C:$C,MATCH('aSC LAYOUT'!$B:$B,OB!$A:$A,0)),"") | F74: =IFERROR(INDEX(OB!$K:$K,MATCH('aSC LAYOUT'!$B:$B,OB!$A:$A,0)),"") | G74: =IF(C74="","",(MROUND(IF(E74<=0,0,60/E74),5))) | H74: =E77 -> 0 | Q74: =T77 -> 0 | R74: =IF(V74="","",(MROUND(IF(T74<=0,0,60/T74),5))) | S74: =IFERROR(INDEX(OB!$K:$K,MATCH('aSC LAYOUT'!$W:$W,OB!$A:$A,0)),"") | T74: =IFERROR(INDEX(OB!$C:$C,MATCH('aSC LAYOUT'!$W:$W,OB!$A:$A,0)),"") | V74: =IFERROR(INDEX(OB!$B:$B,MATCH('aSC LAYOUT'!$W:$W,OB!$A:$A,0)),"") | W74: =+W79+1 -> 87 | X74: =IFERROR(INDEX(OB!$G:$G,MATCH('aSC LAYOUT'!$W:$W,OB!$A:$A,0)),"")
A75: =IFERROR(INDEX(OB!$G:$G,MATCH('aSC LAYOUT'!$B:$B,OB!$A:$A,0)),"") | C75: =IFERROR(INDEX(OB!$B:$B,MATCH('aSC LAYOUT'!$B:$B,OB!$A:$A,0)),"") | E75: =IFERROR(INDEX(OB!$C:$C,MATCH('aSC LAYOUT'!$B:$B,OB!$A:$A,0)),"") | F75: =IFERROR(INDEX(OB!$K:$K,MATCH('aSC LAYOUT'!$B:$B,OB!$A:$A,0)),"") | G75: =IF(C75="","",(MROUND(IF(E75<=0,0,60/E75),5))) | I75: WS | P75: WS | R75: =IF(V75="","",(MROUND(IF(T75<=0,0,60/T75),5))) | S75: =IFERROR(INDEX(OB!$K:$K,MATCH('aSC LAYOUT'!$W:$W,OB!$A:$A,0)),"") | T75: =IFERROR(INDEX(OB!$C:$C,MATCH('aSC LAYOUT'!$W:$W,OB!$A:$A,0)),"") | V75: =IFERROR(INDEX(OB!$B:$B,MATCH('aSC LAYOUT'!$W:$W,OB!$A:$A,0)),"") | X75: =IFERROR(INDEX(OB!$G:$G,MATCH('aSC LAYOUT'!$W:$W,OB!$A:$A,0)),"")
A76: =IFERROR(INDEX(OB!$G:$G,MATCH('aSC LAYOUT'!$B:$B,OB!$A:$A,0)),"") | C76: =IFERROR(INDEX(OB!$B:$B,MATCH('aSC LAYOUT'!$B:$B,OB!$A:$A,0)),"") | E76: =IFERROR(INDEX(OB!$C:$C,MATCH('aSC LAYOUT'!$B:$B,OB!$A:$A,0)),"") | F76: =IFERROR(INDEX(OB!$K:$K,MATCH('aSC LAYOUT'!$B:$B,OB!$A:$A,0)),"") | G76: =IF(C76="","",(MROUND(IF(E76<=0,0,60/E76),5))) | H76: =F77 -> 0 | I76: =+P76+1 -> 64 | P76: =+P81+1 -> 63 | Q76: =S77 -> 0 | R76: =IF(V76="","",(MROUND(IF(T76<=0,0,60/T76),5))) | S76: =IFERROR(INDEX(OB!$K:$K,MATCH('aSC LAYOUT'!$W:$W,OB!$A:$A,0)),"") | T76: =IFERROR(INDEX(OB!$C:$C,MATCH('aSC LAYOUT'!$W:$W,OB!$A:$A,0)),"") | V76: =IFERROR(INDEX(OB!$B:$B,MATCH('aSC LAYOUT'!$W:$W,OB!$A:$A,0)),"") | X76: =IFERROR(INDEX(OB!$G:$G,MATCH('aSC LAYOUT'!$W:$W,OB!$A:$A,0)),"")
E77: =SUM(E74:E76) -> 0 | F77: =SUM(F74:F76) -> 0 | S77: =SUM(S74:S76) -> 0 | T77: =SUM(T74:T76) -> 0
A79: =IFERROR(INDEX(OB!$G:$G,MATCH('aSC LAYOUT'!$B:$B,OB!$A:$A,0)),"") | B79: =+B84+1 -> 85 | C79: =IFERROR(INDEX(OB!$B:$B,MATCH('aSC LAYOUT'!$B:$B,OB!$A:$A,0)),"") | E79: =IFERROR(INDEX(OB!$C:$C,MATCH('aSC LAYOUT'!$B:$B,OB!$A:$A,0)),"") | F79: =IFERROR(INDEX(OB!$K:$K,MATCH('aSC LAYOUT'!$B:$B,OB!$A:$A,0)),"") | G79: =IF(C79="","",(MROUND(IF(E79<=0,0,60/E79),5))) | H79: =E82 -> 0 | Q79: =T82 -> 0 | R79: =IF(V79="","",(MROUND(IF(T79<=0,0,60/T79),5))) | S79: =IFERROR(INDEX(OB!$K:$K,MATCH('aSC LAYOUT'!$W:$W,OB!$A:$A,0)),"") | T79: =IFERROR(INDEX(OB!$C:$C,MATCH('aSC LAYOUT'!$W:$W,OB!$A:$A,0)),"") | V79: =IFERROR(INDEX(OB!$B:$B,MATCH('aSC LAYOUT'!$W:$W,OB!$A:$A,0)),"") | W79: =+B79+1 -> 86 | X79: =IFERROR(INDEX(OB!$G:$G,MATCH('aSC LAYOUT'!$W:$W,OB!$A:$A,0)),"")
A80: =IFERROR(INDEX(OB!$G:$G,MATCH('aSC LAYOUT'!$B:$B,OB!$A:$A,0)),"") | C80: =IFERROR(INDEX(OB!$B:$B,MATCH('aSC LAYOUT'!$B:$B,OB!$A:$A,0)),"") | E80: =IFERROR(INDEX(OB!$C:$C,MATCH('aSC LAYOUT'!$B:$B,OB!$A:$A,0)),"") | F80: =IFERROR(INDEX(OB!$K:$K,MATCH('aSC LAYOUT'!$B:$B,OB!$A:$A,0)),"") | G80: =IF(C80="","",(MROUND(IF(E80<=0,0,60/E80),5))) | I80: WS | P80: WS | R80: =IF(V80="","",(MROUND(IF(T80<=0,0,60/T80),5))) | S80: =IFERROR(INDEX(OB!$K:$K,MATCH('aSC LAYOUT'!$W:$W,OB!$A:$A,0)),"") | T80: =IFERROR(INDEX(OB!$C:$C,MATCH('aSC LAYOUT'!$W:$W,OB!$A:$A,0)),"") | V80: =IFERROR(INDEX(OB!$B:$B,MATCH('aSC LAYOUT'!$W:$W,OB!$A:$A,0)),"") | X80: =IFERROR(INDEX(OB!$G:$G,MATCH('aSC LAYOUT'!$W:$W,OB!$A:$A,0)),"")
A81: =IFERROR(INDEX(OB!$G:$G,MATCH('aSC LAYOUT'!$B:$B,OB!$A:$A,0)),"") | C81: =IFERROR(INDEX(OB!$B:$B,MATCH('aSC LAYOUT'!$B:$B,OB!$A:$A,0)),"") | E81: =IFERROR(INDEX(OB!$C:$C,MATCH('aSC LAYOUT'!$B:$B,OB!$A:$A,0)),"") | F81: =IFERROR(INDEX(OB!$K:$K,MATCH('aSC LAYOUT'!$B:$B,OB!$A:$A,0)),"") | G81: =IF(C81="","",(MROUND(IF(E81<=0,0,60/E81),5))) | H81: =F82 -> 0 | I81: =+I86+1 -> 61 | P81: =+I81+1 -> 62 | Q81: =S82 -> 0 | R81: =IF(V81="","",(MROUND(IF(T81<=0,0,60/T81),5))) | S81: =IFERROR(INDEX(OB!$K:$K,MATCH('aSC LAYOUT'!$W:$W,OB!$A:$A,0)),"") | T81: =IFERROR(INDEX(OB!$C:$C,MATCH('aSC LAYOUT'!$W:$W,OB!$A:$A,0)),"") | V81: =IFERROR(INDEX(OB!$B:$B,MATCH('aSC LAYOUT'!$W:$W,OB!$A:$A,0)),"") | X81: =IFERROR(INDEX(OB!$G:$G,MATCH('aSC LAYOUT'!$W:$W,OB!$A:$A,0)),"")
E82: =SUM(E79:E81) -> 0 | F82: =SUM(F79:F81) -> 0 | S82: =SUM(S79:S81) -> 0 | T82: =SUM(T79:T81) -> 0
A84: =IFERROR(INDEX(OB!$G:$G,MATCH('aSC LAYOUT'!$B:$B,OB!$A:$A,0)),"") | B84: =+W84+1 -> 84 | C84: =IFERROR(INDEX(OB!$B:$B,MATCH('aSC LAYOUT'!$B:$B,OB!$A:$A,0)),"") | E84: =IFERROR(INDEX(OB!$C:$C,MATCH('aSC LAYOUT'!$B:$B,OB!$A:$A,0)),"") | F84: =IFERROR(INDEX(OB!$K:$K,MATCH('aSC LAYOUT'!$B:$B,OB!$A:$A,0)),"") | G84: =IF(C84="","",(MROUND(IF(E84<=0,0,60/E84),5))) | H84: =E87 -> 0 | Q84: =T87 -> 0 | R84: =IF(V84="","",(MROUND(IF(T84<=0,0,60/T84),5))) | S84: =IFERROR(INDEX(OB!$K:$K,MATCH('aSC LAYOUT'!$W:$W,OB!$A:$A,0)),"") | T84: =IFERROR(INDEX(OB!$C:$C,MATCH('aSC LAYOUT'!$W:$W,OB!$A:$A,0)),"") | V84: =IFERROR(INDEX(OB!$B:$B,MATCH('aSC LAYOUT'!$W:$W,OB!$A:$A,0)),"") | W84: =+W89+1 -> 83 | X84: =IFERROR(INDEX(OB!$G:$G,MATCH('aSC LAYOUT'!$W:$W,OB!$A:$A,0)),"")
A85: =IFERROR(INDEX(OB!$G:$G,MATCH('aSC LAYOUT'!$B:$B,OB!$A:$A,0)),"") | C85: =IFERROR(INDEX(OB!$B:$B,MATCH('aSC LAYOUT'!$B:$B,OB!$A:$A,0)),"") | E85: =IFERROR(INDEX(OB!$C:$C,MATCH('aSC LAYOUT'!$B:$B,OB!$A:$A,0)),"") | F85: =IFERROR(INDEX(OB!$K:$K,MATCH('aSC LAYOUT'!$B:$B,OB!$A:$A,0)),"") | G85: =IF(C85="","",(MROUND(IF(E85<=0,0,60/E85),5))) | I85: WS | P85: WS | R85: =IF(V85="","",(MROUND(IF(T85<=0,0,60/T85),5))) | S85: =IFERROR(INDEX(OB!$K:$K,MATCH('aSC LAYOUT'!$W:$W,OB!$A:$A,0)),"") | T85: =IFERROR(INDEX(OB!$C:$C,MATCH('aSC LAYOUT'!$W:$W,OB!$A:$A,0)),"") | V85: =IFERROR(INDEX(OB!$B:$B,MATCH('aSC LAYOUT'!$W:$W,OB!$A:$A,0)),"") | X85: =IFERROR(INDEX(OB!$G:$G,MATCH('aSC LAYOUT'!$W:$W,OB!$A:$A,0)),"")
A86: =IFERROR(INDEX(OB!$G:$G,MATCH('aSC LAYOUT'!$B:$B,OB!$A:$A,0)),"") | C86: =IFERROR(INDEX(OB!$B:$B,MATCH('aSC LAYOUT'!$B:$B,OB!$A:$A,0)),"") | E86: =IFERROR(INDEX(OB!$C:$C,MATCH('aSC LAYOUT'!$B:$B,OB!$A:$A,0)),"") | F86: =IFERROR(INDEX(OB!$K:$K,MATCH('aSC LAYOUT'!$B:$B,OB!$A:$A,0)),"") | G86: =IF(C86="","",(MROUND(IF(E86<=0,0,60/E86),5))) | H86: =F87 -> 0 | I86: =+P86+1 -> 60 | P86: =+P91+1 -> 59 | Q86: =S87 -> 0 | R86: =IF(V86="","",(MROUND(IF(T86<=0,0,60/T86),5))) | S86: =IFERROR(INDEX(OB!$K:$K,MATCH('aSC LAYOUT'!$W:$W,OB!$A:$A,0)),"") | T86: =IFERROR(INDEX(OB!$C:$C,MATCH('aSC LAYOUT'!$W:$W,OB!$A:$A,0)),"") | V86: =IFERROR(INDEX(OB!$B:$B,MATCH('aSC LAYOUT'!$W:$W,OB!$A:$A,0)),"") | X86: =IFERROR(INDEX(OB!$G:$G,MATCH('aSC LAYOUT'!$W:$W,OB!$A:$A,0)),"")
E87: =SUM(E84:E86) -> 0 | F87: =SUM(F84:F86) -> 0 | S87: =SUM(S84:S86) -> 0 | T87: =SUM(T84:T86) -> 0
A89: =IFERROR(INDEX(OB!$G:$G,MATCH('aSC LAYOUT'!$B:$B,OB!$A:$A,0)),"") | B89: =+B94+1 -> 81 | C89: =IFERROR(INDEX(OB!$B:$B,MATCH('aSC LAYOUT'!$B:$B,OB!$A:$A,0)),"") | E89: =IFERROR(INDEX(OB!$C:$C,MATCH('aSC LAYOUT'!$B:$B,OB!$A:$A,0)),"") | F89: =IFERROR(INDEX(OB!$K:$K,MATCH('aSC LAYOUT'!$B:$B,OB!$A:$A,0)),"") | G89: =IF(C89="","",(MROUND(IF(E89<=0,0,60/E89),5))) | H89: =E92 -> 0 | Q89: =T92 -> 0 | R89: =IF(V89="","",(MROUND(IF(T89<=0,0,60/T89),5))) | S89: =IFERROR(INDEX(OB!$K:$K,MATCH('aSC LAYOUT'!$W:$W,OB!$A:$A,0)),"") | T89: =IFERROR(INDEX(OB!$C:$C,MATCH('aSC LAYOUT'!$W:$W,OB!$A:$A,0)),"") | V89: =IFERROR(INDEX(OB!$B:$B,MATCH('aSC LAYOUT'!$W:$W,OB!$A:$A,0)),"") | W89: =+B89+1 -> 82 | X89: =IFERROR(INDEX(OB!$G:$G,MATCH('aSC LAYOUT'!$W:$W,OB!$A:$A,0)),"")
A90: =IFERROR(INDEX(OB!$G:$G,MATCH('aSC LAYOUT'!$B:$B,OB!$A:$A,0)),"") | C90: =IFERROR(INDEX(OB!$B:$B,MATCH('aSC LAYOUT'!$B:$B,OB!$A:$A,0)),"") | E90: =IFERROR(INDEX(OB!$C:$C,MATCH('aSC LAYOUT'!$B:$B,OB!$A:$A,0)),"") | F90: =IFERROR(INDEX(OB!$K:$K,MATCH('aSC LAYOUT'!$B:$B,OB!$A:$A,0)),"") | G90: =IF(C90="","",(MROUND(IF(E90<=0,0,60/E90),5))) | I90: WS | P90: WS | R90: =IF(V90="","",(MROUND(IF(T90<=0,0,60/T90),5))) | S90: =IFERROR(INDEX(OB!$K:$K,MATCH('aSC LAYOUT'!$W:$W,OB!$A:$A,0)),"") | T90: =IFERROR(INDEX(OB!$C:$C,MATCH('aSC LAYOUT'!$W:$W,OB!$A:$A,0)),"") | V90: =IFERROR(INDEX(OB!$B:$B,MATCH('aSC LAYOUT'!$W:$W,OB!$A:$A,0)),"") | X90: =IFERROR(INDEX(OB!$G:$G,MATCH('aSC LAYOUT'!$W:$W,OB!$A:$A,0)),"")
A91: =IFERROR(INDEX(OB!$G:$G,MATCH('aSC LAYOUT'!$B:$B,OB!$A:$A,0)),"") | C91: =IFERROR(INDEX(OB!$B:$B,MATCH('aSC LAYOUT'!$B:$B,OB!$A:$A,0)),"") | E91: =IFERROR(INDEX(OB!$C:$C,MATCH('aSC LAYOUT'!$B:$B,OB!$A:$A,0)),"") | F91: =IFERROR(INDEX(OB!$K:$K,MATCH('aSC LAYOUT'!$B:$B,OB!$A:$A,0)),"") | G91: =IF(C91="","",(MROUND(IF(E91<=0,0,60/E91),5))) | H91: =F92 -> 0 | I91: =+I96+1 -> 57 | P91: =+I91+1 -> 58 | Q91: =S92 -> 0 | R91: =IF(V91="","",(MROUND(IF(T91<=0,0,60/T91),5))) | S91: =IFERROR(INDEX(OB!$K:$K,MATCH('aSC LAYOUT'!$W:$W,OB!$A:$A,0)),"") | T91: =IFERROR(INDEX(OB!$C:$C,MATCH('aSC LAYOUT'!$W:$W,OB!$A:$A,0)),"") | V91: =IFERROR(INDEX(OB!$B:$B,MATCH('aSC LAYOUT'!$W:$W,OB!$A:$A,0)),"") | X91: =IFERROR(INDEX(OB!$G:$G,MATCH('aSC LAYOUT'!$W:$W,OB!$A:$A,0)),"")
E92: =SUM(E89:E91) -> 0 | F92: =SUM(F89:F91) -> 0 | S92: =SUM(S89:S91) -> 0 | T92: =SUM(T89:T91) -> 0
A94: =IFERROR(INDEX(OB!$G:$G,MATCH('aSC LAYOUT'!$B:$B,OB!$A:$A,0)),"") | B94: =+W94+1 -> 80 | C94: =IFERROR(INDEX(OB!$B:$B,MATCH('aSC LAYOUT'!$B:$B,OB!$A:$A,0)),"") | E94: =IFERROR(INDEX(OB!$C:$C,MATCH('aSC LAYOUT'!$B:$B,OB!$A:$A,0)),"") | F94: =IFERROR(INDEX(OB!$K:$K,MATCH('aSC LAYOUT'!$B:$B,OB!$A:$A,0)),"") | G94: =IF(C94="","",(MROUND(IF(E94<=0,0,60/E94),5))) | H94: =E97 -> 0 | Q94: =T97 -> 0 | R94: =IF(V94="","",(MROUND(IF(T94<=0,0,60/T94),5))) | S94: =IFERROR(INDEX(OB!$K:$K,MATCH('aSC LAYOUT'!$W:$W,OB!$A:$A,0)),"") | T94: =IFERROR(INDEX(OB!$C:$C,MATCH('aSC LAYOUT'!$W:$W,OB!$A:$A,0)),"") | V94: =IFERROR(INDEX(OB!$B:$B,MATCH('aSC LAYOUT'!$W:$W,OB!$A:$A,0)),"") | W94: =+W99+1 -> 79 | X94: =IFERROR(INDEX(OB!$G:$G,MATCH('aSC LAYOUT'!$W:$W,OB!$A:$A,0)),"")
A95: =IFERROR(INDEX(OB!$G:$G,MATCH('aSC LAYOUT'!$B:$B,OB!$A:$A,0)),"") | C95: =IFERROR(INDEX(OB!$B:$B,MATCH('aSC LAYOUT'!$B:$B,OB!$A:$A,0)),"") | E95: =IFERROR(INDEX(OB!$C:$C,MATCH('aSC LAYOUT'!$B:$B,OB!$A:$A,0)),"") | F95: =IFERROR(INDEX(OB!$K:$K,MATCH('aSC LAYOUT'!$B:$B,OB!$A:$A,0)),"") | G95: =IF(C95="","",(MROUND(IF(E95<=0,0,60/E95),5))) | I95: WS | P95: WS | R95: =IF(V95="","",(MROUND(IF(T95<=0,0,60/T95),5))) | S95: =IFERROR(INDEX(OB!$K:$K,MATCH('aSC LAYOUT'!$W:$W,OB!$A:$A,0)),"") | T95: =IFERROR(INDEX(OB!$C:$C,MATCH('aSC LAYOUT'!$W:$W,OB!$A:$A,0)),"") | V95: =IFERROR(INDEX(OB!$B:$B,MATCH('aSC LAYOUT'!$W:$W,OB!$A:$A,0)),"") | X95: =IFERROR(INDEX(OB!$G:$G,MATCH('aSC LAYOUT'!$W:$W,OB!$A:$A,0)),"")
A96: =IFERROR(INDEX(OB!$G:$G,MATCH('aSC LAYOUT'!$B:$B,OB!$A:$A,0)),"") | C96: =IFERROR(INDEX(OB!$B:$B,MATCH('aSC LAYOUT'!$B:$B,OB!$A:$A,0)),"") | E96: =IFERROR(INDEX(OB!$C:$C,MATCH('aSC LAYOUT'!$B:$B,OB!$A:$A,0)),"") | F96: =IFERROR(INDEX(OB!$K:$K,MATCH('aSC LAYOUT'!$B:$B,OB!$A:$A,0)),"") | G96: =IF(C96="","",(MROUND(IF(E96<=0,0,60/E96),5))) | H96: =F97 -> 0 | I96: =+P96+1 -> 56 | P96: =+P101+1 -> 55 | Q96: =S97 -> 0 | R96: =IF(V96="","",(MROUND(IF(T96<=0,0,60/T96),5))) | S96: =IFERROR(INDEX(OB!$K:$K,MATCH('aSC LAYOUT'!$W:$W,OB!$A:$A,0)),"") | T96: =IFERROR(INDEX(OB!$C:$C,MATCH('aSC LAYOUT'!$W:$W,OB!$A:$A,0)),"") | V96: =IFERROR(INDEX(OB!$B:$B,MATCH('aSC LAYOUT'!$W:$W,OB!$A:$A,0)),"") | X96: =IFERROR(INDEX(OB!$G:$G,MATCH('aSC LAYOUT'!$W:$W,OB!$A:$A,0)),"")
E97: =SUM(E94:E96) -> 0 | F97: =SUM(F94:F96) -> 0 | S97: =SUM(S94:S96) -> 0 | T97: =SUM(T94:T96) -> 0
A99: =IFERROR(INDEX(OB!$G:$G,MATCH('aSC LAYOUT'!$B:$B,OB!$A:$A,0)),"") | B99: =+B104+1 -> 77 | C99: =IFERROR(INDEX(OB!$B:$B,MATCH('aSC LAYOUT'!$B:$B,OB!$A:$A,0)),"") | E99: =IFERROR(INDEX(OB!$C:$C,MATCH('aSC LAYOUT'!$B:$B,OB!$A:$A,0)),"") | F99: =IFERROR(INDEX(OB!$K:$K,MATCH('aSC LAYOUT'!$B:$B,OB!$A:$A,0)),"") | G99: =IF(C99="","",(MROUND(IF(E99<=0,0,60/E99),5))) | H99: =E102 -> 0 | Q99: =T102 -> 0 | R99: =IF(V99="","",(MROUND(IF(T99<=0,0,60/T99),5))) | S99: =IFERROR(INDEX(OB!$K:$K,MATCH('aSC LAYOUT'!$W:$W,OB!$A:$A,0)),"") | T99: =IFERROR(INDEX(OB!$C:$C,MATCH('aSC LAYOUT'!$W:$W,OB!$A:$A,0)),"") | V99: =IFERROR(INDEX(OB!$B:$B,MATCH('aSC LAYOUT'!$W:$W,OB!$A:$A,0)),"") | W99: =+B99+1 -> 78 | X99: =IFERROR(INDEX(OB!$G:$G,MATCH('aSC LAYOUT'!$W:$W,OB!$A:$A,0)),"")
A100: =IFERROR(INDEX(OB!$G:$G,MATCH('aSC LAYOUT'!$B:$B,OB!$A:$A,0)),"") | C100: =IFERROR(INDEX(OB!$B:$B,MATCH('aSC LAYOUT'!$B:$B,OB!$A:$A,0)),"") | E100: =IFERROR(INDEX(OB!$C:$C,MATCH('aSC LAYOUT'!$B:$B,OB!$A:$A,0)),"") | F100: =IFERROR(INDEX(OB!$K:$K,MATCH('aSC LAYOUT'!$B:$B,OB!$A:$A,0)),"") | G100: =IF(C100="","",(MROUND(IF(E100<=0,0,60/E100),5))) | I100: WS | P100: WS | R100: =IF(V100="","",(MROUND(IF(T100<=0,0,60/T100),5))) | S100: =IFERROR(INDEX(OB!$K:$K,MATCH('aSC LAYOUT'!$W:$W,OB!$A:$A,0)),"") | T100: =IFERROR(INDEX(OB!$C:$C,MATCH('aSC LAYOUT'!$W:$W,OB!$A:$A,0)),"") | V100: =IFERROR(INDEX(OB!$B:$B,MATCH('aSC LAYOUT'!$W:$W,OB!$A:$A,0)),"") | X100: =IFERROR(INDEX(OB!$G:$G,MATCH('aSC LAYOUT'!$W:$W,OB!$A:$A,0)),"")
A101: =IFERROR(INDEX(OB!$G:$G,MATCH('aSC LAYOUT'!$B:$B,OB!$A:$A,0)),"") | C101: =IFERROR(INDEX(OB!$B:$B,MATCH('aSC LAYOUT'!$B:$B,OB!$A:$A,0)),"") | E101: =IFERROR(INDEX(OB!$C:$C,MATCH('aSC LAYOUT'!$B:$B,OB!$A:$A,0)),"") | F101: =IFERROR(INDEX(OB!$K:$K,MATCH('aSC LAYOUT'!$B:$B,OB!$A:$A,0)),"") | G101: =IF(C101="","",(MROUND(IF(E101<=0,0,60/E101),5))) | H101: =F102 -> 0 | I101: =+I106+1 -> 53 | P101: =+I101+1 -> 54 | Q101: =S102 -> 0 | R101: =IF(V101="","",(MROUND(IF(T101<=0,0,60/T101),5))) | S101: =IFERROR(INDEX(OB!$K:$K,MATCH('aSC LAYOUT'!$W:$W,OB!$A:$A,0)),"") | T101: =IFERROR(INDEX(OB!$C:$C,MATCH('aSC LAYOUT'!$W:$W,OB!$A:$A,0)),"") | V101: =IFERROR(INDEX(OB!$B:$B,MATCH('aSC LAYOUT'!$W:$W,OB!$A:$A,0)),"") | X101: =IFERROR(INDEX(OB!$G:$G,MATCH('aSC LAYOUT'!$W:$W,OB!$A:$A,0)),"")
E102: =SUM(E99:E101) -> 0 | F102: =SUM(F99:F101) -> 0 | S102: =SUM(S99:S101) -> 0 | T102: =SUM(T99:T101) -> 0
A104: =IFERROR(INDEX(OB!$G:$G,MATCH('aSC LAYOUT'!$B:$B,OB!$A:$A,0)),"") | B104: =+W104+1 -> 76 | C104: =IFERROR(INDEX(OB!$B:$B,MATCH('aSC LAYOUT'!$B:$B,OB!$A:$A,0)),"") | E104: =IFERROR(INDEX(OB!$C:$C,MATCH('aSC LAYOUT'!$B:$B,OB!$A:$A,0)),"") | F104: =IFERROR(INDEX(OB!$K:$K,MATCH('aSC LAYOUT'!$B:$B,OB!$A:$A,0)),"") | G104: =IF(C104="","",(MROUND(IF(E104<=0,0,60/E104),5))) | H104: =E107 -> 0 | Q104: =T107 -> 0 | R104: =IF(V104="","",(MROUND(IF(T104<=0,0,60/T104),5))) | S104: =IFERROR(INDEX(OB!$K:$K,MATCH('aSC LAYOUT'!$W:$W,OB!$A:$A,0)),"") | T104: =IFERROR(INDEX(OB!$C:$C,MATCH('aSC LAYOUT'!$W:$W,OB!$A:$A,0)),"") | V104: =IFERROR(INDEX(OB!$B:$B,MATCH('aSC LAYOUT'!$W:$W,OB!$A:$A,0)),"") | W104: =+W109+1 -> 75 | X104: =IFERROR(INDEX(OB!$G:$G,MATCH('aSC LAYOUT'!$W:$W,OB!$A:$A,0)),"")
A105: =IFERROR(INDEX(OB!$G:$G,MATCH('aSC LAYOUT'!$B:$B,OB!$A:$A,0)),"") | C105: =IFERROR(INDEX(OB!$B:$B,MATCH('aSC LAYOUT'!$B:$B,OB!$A:$A,0)),"") | E105: =IFERROR(INDEX(OB!$C:$C,MATCH('aSC LAYOUT'!$B:$B,OB!$A:$A,0)),"") | F105: =IFERROR(INDEX(OB!$K:$K,MATCH('aSC LAYOUT'!$B:$B,OB!$A:$A,0)),"") | G105: =IF(C105="","",(MROUND(IF(E105<=0,0,60/E105),5))) | I105: WS | P105: WS | R105: =IF(V105="","",(MROUND(IF(T105<=0,0,60/T105),5))) | S105: =IFERROR(INDEX(OB!$K:$K,MATCH('aSC LAYOUT'!$W:$W,OB!$A:$A,0)),"") | T105: =IFERROR(INDEX(OB!$C:$C,MATCH('aSC LAYOUT'!$W:$W,OB!$A:$A,0)),"") | V105: =IFERROR(INDEX(OB!$B:$B,MATCH('aSC LAYOUT'!$W:$W,OB!$A:$A,0)),"") | X105: =IFERROR(INDEX(OB!$G:$G,MATCH('aSC LAYOUT'!$W:$W,OB!$A:$A,0)),"")
A106: =IFERROR(INDEX(OB!$G:$G,MATCH('aSC LAYOUT'!$B:$B,OB!$A:$A,0)),"") | C106: =IFERROR(INDEX(OB!$B:$B,MATCH('aSC LAYOUT'!$B:$B,OB!$A:$A,0)),"") | E106: =IFERROR(INDEX(OB!$C:$C,MATCH('aSC LAYOUT'!$B:$B,OB!$A:$A,0)),"") | F106: =IFERROR(INDEX(OB!$K:$K,MATCH('aSC LAYOUT'!$B:$B,OB!$A:$A,0)),"") | G106: =IF(C106="","",(MROUND(IF(E106<=0,0,60/E106),5))) | H106: =F107 -> 0 | I106: =+P106+1 -> 52 | P106: =+P111+1 -> 51 | Q106: =S107 -> 0 | R106: =IF(V106="","",(MROUND(IF(T106<=0,0,60/T106),5))) | S106: =IFERROR(INDEX(OB!$K:$K,MATCH('aSC LAYOUT'!$W:$W,OB!$A:$A,0)),"") | T106: =IFERROR(INDEX(OB!$C:$C,MATCH('aSC LAYOUT'!$W:$W,OB!$A:$A,0)),"") | V106: =IFERROR(INDEX(OB!$B:$B,MATCH('aSC LAYOUT'!$W:$W,OB!$A:$A,0)),"") | X106: =IFERROR(INDEX(OB!$G:$G,MATCH('aSC LAYOUT'!$W:$W,OB!$A:$A,0)),"")
E107: =SUM(E104:E106) -> 0 | F107: =SUM(F104:F106) -> 0 | S107: =SUM(S104:S106) -> 0 | T107: =SUM(T104:T106) -> 0
A109: =IFERROR(INDEX(OB!$G:$G,MATCH('aSC LAYOUT'!$B:$B,OB!$A:$A,0)),"") | B109: =+B114+1 -> 73 | C109: =IFERROR(INDEX(OB!$B:$B,MATCH('aSC LAYOUT'!$B:$B,OB!$A:$A,0)),"") | E109: =IFERROR(INDEX(OB!$C:$C,MATCH('aSC LAYOUT'!$B:$B,OB!$A:$A,0)),"") | F109: =IFERROR(INDEX(OB!$K:$K,MATCH('aSC LAYOUT'!$B:$B,OB!$A:$A,0)),"") | G109: =IF(C109="","",(MROUND(IF(E109<=0,0,60/E109),5))) | H109: =E112 -> 0 | Q109: =T112 -> 0 | R109: =IF(V109="","",(MROUND(IF(T109<=0,0,60/T109),5))) | S109: =IFERROR(INDEX(OB!$K:$K,MATCH('aSC LAYOUT'!$W:$W,OB!$A:$A,0)),"") | T109: =IFERROR(INDEX(OB!$C:$C,MATCH('aSC LAYOUT'!$W:$W,OB!$A:$A,0)),"") | V109: =IFERROR(INDEX(OB!$B:$B,MATCH('aSC LAYOUT'!$W:$W,OB!$A:$A,0)),"") | W109: =+B109+1 -> 74 | X109: =IFERROR(INDEX(OB!$G:$G,MATCH('aSC LAYOUT'!$W:$W,OB!$A:$A,0)),"")
A110: =IFERROR(INDEX(OB!$G:$G,MATCH('aSC LAYOUT'!$B:$B,OB!$A:$A,0)),"") | C110: =IFERROR(INDEX(OB!$B:$B,MATCH('aSC LAYOUT'!$B:$B,OB!$A:$A,0)),"") | E110: =IFERROR(INDEX(OB!$C:$C,MATCH('aSC LAYOUT'!$B:$B,OB!$A:$A,0)),"") | F110: =IFERROR(INDEX(OB!$K:$K,MATCH('aSC LAYOUT'!$B:$B,OB!$A:$A,0)),"") | G110: =IF(C110="","",(MROUND(IF(E110<=0,0,60/E110),5))) | I110: WS | P110: WS | R110: =IF(V110="","",(MROUND(IF(T110<=0,0,60/T110),5))) | S110: =IFERROR(INDEX(OB!$K:$K,MATCH('aSC LAYOUT'!$W:$W,OB!$A:$A,0)),"") | T110: =IFERROR(INDEX(OB!$C:$C,MATCH('aSC LAYOUT'!$W:$W,OB!$A:$A,0)),"") | V110: =IFERROR(INDEX(OB!$B:$B,MATCH('aSC LAYOUT'!$W:$W,OB!$A:$A,0)),"") | X110: =IFERROR(INDEX(OB!$G:$G,MATCH('aSC LAYOUT'!$W:$W,OB!$A:$A,0)),"")
A111: =IFERROR(INDEX(OB!$G:$G,MATCH('aSC LAYOUT'!$B:$B,OB!$A:$A,0)),"") | C111: =IFERROR(INDEX(OB!$B:$B,MATCH('aSC LAYOUT'!$B:$B,OB!$A:$A,0)),"") | E111: =IFERROR(INDEX(OB!$C:$C,MATCH('aSC LAYOUT'!$B:$B,OB!$A:$A,0)),"") | F111: =IFERROR(INDEX(OB!$K:$K,MATCH('aSC LAYOUT'!$B:$B,OB!$A:$A,0)),"") | G111: =IF(C111="","",(MROUND(IF(E111<=0,0,60/E111),5))) | H111: =F112 -> 0 | I111: =+I116+1 -> 49 | P111: =+I111+1 -> 50 | Q111: =S112 -> 0 | R111: =IF(V111="","",(MROUND(IF(T111<=0,0,60/T111),5))) | S111: =IFERROR(INDEX(OB!$K:$K,MATCH('aSC LAYOUT'!$W:$W,OB!$A:$A,0)),"") | T111: =IFERROR(INDEX(OB!$C:$C,MATCH('aSC LAYOUT'!$W:$W,OB!$A:$A,0)),"") | V111: =IFERROR(INDEX(OB!$B:$B,MATCH('aSC LAYOUT'!$W:$W,OB!$A:$A,0)),"") | X111: =IFERROR(INDEX(OB!$G:$G,MATCH('aSC LAYOUT'!$W:$W,OB!$A:$A,0)),"")
E112: =SUM(E109:E111) -> 0 | F112: =SUM(F109:F111) -> 0 | S112: =SUM(S109:S111) -> 0 | T112: =SUM(T109:T111) -> 0
A114: =IFERROR(INDEX(OB!$G:$G,MATCH('aSC LAYOUT'!$B:$B,OB!$A:$A,0)),"") | B114: =+W114+1 -> 72 | C114: =IFERROR(INDEX(OB!$B:$B,MATCH('aSC LAYOUT'!$B:$B,OB!$A:$A,0)),"") | E114: =IFERROR(INDEX(OB!$C:$C,MATCH('aSC LAYOUT'!$B:$B,OB!$A:$A,0)),"") | F114: =IFERROR(INDEX(OB!$K:$K,MATCH('aSC LAYOUT'!$B:$B,OB!$A:$A,0)),"") | G114: =IF(C114="","",(MROUND(IF(E114<=0,0,60/E114),5))) | H114: =E117 -> 0 | Q114: =T117 -> 0 | R114: =IF(V114="","",(MROUND(IF(T114<=0,0,60/T114),5))) | S114: =IFERROR(INDEX(OB!$K:$K,MATCH('aSC LAYOUT'!$W:$W,OB!$A:$A,0)),"") | T114: =IFERROR(INDEX(OB!$C:$C,MATCH('aSC LAYOUT'!$W:$W,OB!$A:$A,0)),"") | V114: =IFERROR(INDEX(OB!$B:$B,MATCH('aSC LAYOUT'!$W:$W,OB!$A:$A,0)),"") | W114: =+W119+1 -> 71 | X114: =IFERROR(INDEX(OB!$G:$G,MATCH('aSC LAYOUT'!$W:$W,OB!$A:$A,0)),"")
A115: =IFERROR(INDEX(OB!$G:$G,MATCH('aSC LAYOUT'!$B:$B,OB!$A:$A,0)),"") | C115: =IFERROR(INDEX(OB!$B:$B,MATCH('aSC LAYOUT'!$B:$B,OB!$A:$A,0)),"") | E115: =IFERROR(INDEX(OB!$C:$C,MATCH('aSC LAYOUT'!$B:$B,OB!$A:$A,0)),"") | F115: =IFERROR(INDEX(OB!$K:$K,MATCH('aSC LAYOUT'!$B:$B,OB!$A:$A,0)),"") | G115: =IF(C115="","",(MROUND(IF(E115<=0,0,60/E115),5))) | I115: WS | P115: WS | R115: =IF(V115="","",(MROUND(IF(T115<=0,0,60/T115),5))) | S115: =IFERROR(INDEX(OB!$K:$K,MATCH('aSC LAYOUT'!$W:$W,OB!$A:$A,0)),"") | T115: =IFERROR(INDEX(OB!$C:$C,MATCH('aSC LAYOUT'!$W:$W,OB!$A:$A,0)),"") | V115: =IFERROR(INDEX(OB!$B:$B,MATCH('aSC LAYOUT'!$W:$W,OB!$A:$A,0)),"") | X115: =IFERROR(INDEX(OB!$G:$G,MATCH('aSC LAYOUT'!$W:$W,OB!$A:$A,0)),"")
A116: =IFERROR(INDEX(OB!$G:$G,MATCH('aSC LAYOUT'!$B:$B,OB!$A:$A,0)),"") | C116: =IFERROR(INDEX(OB!$B:$B,MATCH('aSC LAYOUT'!$B:$B,OB!$A:$A,0)),"") | E116: =IFERROR(INDEX(OB!$C:$C,MATCH('aSC LAYOUT'!$B:$B,OB!$A:$A,0)),"") | F116: =IFERROR(INDEX(OB!$K:$K,MATCH('aSC LAYOUT'!$B:$B,OB!$A:$A,0)),"") | G116: =IF(C116="","",(MROUND(IF(E116<=0,0,60/E116),5))) | H116: =F117 -> 0 | I116: =+P116+1 -> 48 | P116: =+P121+1 -> 47 | Q116: =S117 -> 0 | R116: =IF(V116="","",(MROUND(IF(T116<=0,0,60/T116),5))) | S116: =IFERROR(INDEX(OB!$K:$K,MATCH('aSC LAYOUT'!$W:$W,OB!$A:$A,0)),"") | T116: =IFERROR(INDEX(OB!$C:$C,MATCH('aSC LAYOUT'!$W:$W,OB!$A:$A,0)),"") | V116: =IFERROR(INDEX(OB!$B:$B,MATCH('aSC LAYOUT'!$W:$W,OB!$A:$A,0)),"") | X116: =IFERROR(INDEX(OB!$G:$G,MATCH('aSC LAYOUT'!$W:$W,OB!$A:$A,0)),"")
E117: =SUM(E114:E116) -> 0 | F117: =SUM(F114:F116) -> 0 | S117: =SUM(S114:S116) -> 0 | T117: =SUM(T114:T116) -> 0
A119: =IFERROR(INDEX(OB!$G:$G,MATCH('aSC LAYOUT'!$B:$B,OB!$A:$A,0)),"") | B119: =+B124+1 -> 69 | C119: =IFERROR(INDEX(OB!$B:$B,MATCH('aSC LAYOUT'!$B:$B,OB!$A:$A,0)),"") | E119: =IFERROR(INDEX(OB!$C:$C,MATCH('aSC LAYOUT'!$B:$B,OB!$A:$A,0)),"") | F119: =IFERROR(INDEX(OB!$K:$K,MATCH('aSC LAYOUT'!$B:$B,OB!$A:$A,0)),"") | G119: =IF(C119="","",(MROUND(IF(E119<=0,0,60/E119),5))) | H119: =E122 -> 0 | Q119: =T122 -> 0 | R119: =IF(V119="","",(MROUND(IF(T119<=0,0,60/T119),5))) | S119: =IFERROR(INDEX(OB!$K:$K,MATCH('aSC LAYOUT'!$W:$W,OB!$A:$A,0)),"") | T119: =IFERROR(INDEX(OB!$C:$C,MATCH('aSC LAYOUT'!$W:$W,OB!$A:$A,0)),"") | V119: =IFERROR(INDEX(OB!$B:$B,MATCH('aSC LAYOUT'!$W:$W,OB!$A:$A,0)),"") | W119: =+B119+1 -> 70 | X119: =IFERROR(INDEX(OB!$G:$G,MATCH('aSC LAYOUT'!$W:$W,OB!$A:$A,0)),"")
A120: =IFERROR(INDEX(OB!$G:$G,MATCH('aSC LAYOUT'!$B:$B,OB!$A:$A,0)),"") | C120: =IFERROR(INDEX(OB!$B:$B,MATCH('aSC LAYOUT'!$B:$B,OB!$A:$A,0)),"") | E120: =IFERROR(INDEX(OB!$C:$C,MATCH('aSC LAYOUT'!$B:$B,OB!$A:$A,0)),"") | F120: =IFERROR(INDEX(OB!$K:$K,MATCH('aSC LAYOUT'!$B:$B,OB!$A:$A,0)),"") | G120: =IF(C120="","",(MROUND(IF(E120<=0,0,60/E120),5))) | I120: WS | P120: WS | R120: =IF(V120="","",(MROUND(IF(T120<=0,0,60/T120),5))) | S120: =IFERROR(INDEX(OB!$K:$K,MATCH('aSC LAYOUT'!$W:$W,OB!$A:$A,0)),"") | T120: =IFERROR(INDEX(OB!$C:$C,MATCH('aSC LAYOUT'!$W:$W,OB!$A:$A,0)),"") | V120: =IFERROR(INDEX(OB!$B:$B,MATCH('aSC LAYOUT'!$W:$W,OB!$A:$A,0)),"") | X120: =IFERROR(INDEX(OB!$G:$G,MATCH('aSC LAYOUT'!$W:$W,OB!$A:$A,0)),"")
A121: =IFERROR(INDEX(OB!$G:$G,MATCH('aSC LAYOUT'!$B:$B,OB!$A:$A,0)),"") | C121: =IFERROR(INDEX(OB!$B:$B,MATCH('aSC LAYOUT'!$B:$B,OB!$A:$A,0)),"") | E121: =IFERROR(INDEX(OB!$C:$C,MATCH('aSC LAYOUT'!$B:$B,OB!$A:$A,0)),"") | F121: =IFERROR(INDEX(OB!$K:$K,MATCH('aSC LAYOUT'!$B:$B,OB!$A:$A,0)),"") | G121: =IF(C121="","",(MROUND(IF(E121<=0,0,60/E121),5))) | H121: =F122 -> 0 | I121: =+I126+1 -> 45 | P121: =+I121+1 -> 46 | Q121: =S122 -> 0 | R121: =IF(V121="","",(MROUND(IF(T121<=0,0,60/T121),5))) | S121: =IFERROR(INDEX(OB!$K:$K,MATCH('aSC LAYOUT'!$W:$W,OB!$A:$A,0)),"") | T121: =IFERROR(INDEX(OB!$C:$C,MATCH('aSC LAYOUT'!$W:$W,OB!$A:$A,0)),"") | V121: =IFERROR(INDEX(OB!$B:$B,MATCH('aSC LAYOUT'!$W:$W,OB!$A:$A,0)),"") | X121: =IFERROR(INDEX(OB!$G:$G,MATCH('aSC LAYOUT'!$W:$W,OB!$A:$A,0)),"")
E122: =SUM(E119:E121) -> 0 | F122: =SUM(F119:F121) -> 0 | S122: =SUM(S119:S121) -> 0 | T122: =SUM(T119:T121) -> 0
A124: =IFERROR(INDEX(OB!$G:$G,MATCH('aSC LAYOUT'!$B:$B,OB!$A:$A,0)),"") | B124: =+W124+1 -> 68 | C124: =IFERROR(INDEX(OB!$B:$B,MATCH('aSC LAYOUT'!$B:$B,OB!$A:$A,0)),"") | E124: =IFERROR(INDEX(OB!$C:$C,MATCH('aSC LAYOUT'!$B:$B,OB!$A:$A,0)),"") | F124: =IFERROR(INDEX(OB!$K:$K,MATCH('aSC LAYOUT'!$B:$B,OB!$A:$A,0)),"") | G124: =IF(C124="","",(MROUND(IF(E124<=0,0,60/E124),5))) | H124: =E127 -> 0 | Q124: =T127 -> 0 | R124: =IF(V124="","",(MROUND(IF(T124<=0,0,60/T124),5))) | S124: =IFERROR(INDEX(OB!$K:$K,MATCH('aSC LAYOUT'!$W:$W,OB!$A:$A,0)),"") | T124: =IFERROR(INDEX(OB!$C:$C,MATCH('aSC LAYOUT'!$W:$W,OB!$A:$A,0)),"") | V124: =IFERROR(INDEX(OB!$B:$B,MATCH('aSC LAYOUT'!$W:$W,OB!$A:$A,0)),"") | W124: =+W129+1 -> 67 | X124: =IFERROR(INDEX(OB!$G:$G,MATCH('aSC LAYOUT'!$W:$W,OB!$A:$A,0)),"")
A125: =IFERROR(INDEX(OB!$G:$G,MATCH('aSC LAYOUT'!$B:$B,OB!$A:$A,0)),"") | C125: =IFERROR(INDEX(OB!$B:$B,MATCH('aSC LAYOUT'!$B:$B,OB!$A:$A,0)),"") | E125: =IFERROR(INDEX(OB!$C:$C,MATCH('aSC LAYOUT'!$B:$B,OB!$A:$A,0)),"") | F125: =IFERROR(INDEX(OB!$K:$K,MATCH('aSC LAYOUT'!$B:$B,OB!$A:$A,0)),"") | G125: =IF(C125="","",(MROUND(IF(E125<=0,0,60/E125),5))) | I125: WS | P125: WS | R125: =IF(V125="","",(MROUND(IF(T125<=0,0,60/T125),5))) | S125: =IFERROR(INDEX(OB!$K:$K,MATCH('aSC LAYOUT'!$W:$W,OB!$A:$A,0)),"") | T125: =IFERROR(INDEX(OB!$C:$C,MATCH('aSC LAYOUT'!$W:$W,OB!$A:$A,0)),"") | V125: =IFERROR(INDEX(OB!$B:$B,MATCH('aSC LAYOUT'!$W:$W,OB!$A:$A,0)),"") | X125: =IFERROR(INDEX(OB!$G:$G,MATCH('aSC LAYOUT'!$W:$W,OB!$A:$A,0)),"")
A126: =IFERROR(INDEX(OB!$G:$G,MATCH('aSC LAYOUT'!$B:$B,OB!$A:$A,0)),"") | C126: =IFERROR(INDEX(OB!$B:$B,MATCH('aSC LAYOUT'!$B:$B,OB!$A:$A,0)),"") | E126: =IFERROR(INDEX(OB!$C:$C,MATCH('aSC LAYOUT'!$B:$B,OB!$A:$A,0)),"") | F126: =IFERROR(INDEX(OB!$K:$K,MATCH('aSC LAYOUT'!$B:$B,OB!$A:$A,0)),"") | G126: =IF(C126="","",(MROUND(IF(E126<=0,0,60/E126),5))) | H126: =F127 -> 0 | I126: =+P126+1 -> 44 | P126: =+P131+1 -> 43 | Q126: =S127 -> 0 | R126: =IF(V126="","",(MROUND(IF(T126<=0,0,60/T126),5))) | S126: =IFERROR(INDEX(OB!$K:$K,MATCH('aSC LAYOUT'!$W:$W,OB!$A:$A,0)),"") | T126: =IFERROR(INDEX(OB!$C:$C,MATCH('aSC LAYOUT'!$W:$W,OB!$A:$A,0)),"") | V126: =IFERROR(INDEX(OB!$B:$B,MATCH('aSC LAYOUT'!$W:$W,OB!$A:$A,0)),"") | X126: =IFERROR(INDEX(OB!$G:$G,MATCH('aSC LAYOUT'!$W:$W,OB!$A:$A,0)),"")
E127: =SUM(E124:E126) -> 0 | F127: =SUM(F124:F126) -> 0 | S127: =SUM(S124:S126) -> 0 | T127: =SUM(T124:T126) -> 0
A129: =IFERROR(INDEX(OB!$G:$G,MATCH('aSC LAYOUT'!$B:$B,OB!$A:$A,0)),"") -> TABLE | B129: =+B134+1 -> 65 | C129: =IFERROR(INDEX(OB!$B:$B,MATCH('aSC LAYOUT'!$B:$B,OB!$A:$A,0)),"") -> SKU + CTN | E129: =IFERROR(INDEX(OB!$C:$C,MATCH('aSC LAYOUT'!$B:$B,OB!$A:$A,0)),"") -> 0.35 | F129: =IFERROR(INDEX(OB!$K:$K,MATCH('aSC LAYOUT'!$B:$B,OB!$A:$A,0)),"") -> 1 | G129: =IF(C129="","",(MROUND(IF(E129<=0,0,60/E129),5))) -> 170 | H129: =E132 -> 0.35 | Q129: =T132 -> 0 | R129: =IF(V129="","",(MROUND(IF(T129<=0,0,60/T129),5))) | S129: =IFERROR(INDEX(OB!$K:$K,MATCH('aSC LAYOUT'!$W:$W,OB!$A:$A,0)),"") | T129: =IFERROR(INDEX(OB!$C:$C,MATCH('aSC LAYOUT'!$W:$W,OB!$A:$A,0)),"") | V129: =IFERROR(INDEX(OB!$B:$B,MATCH('aSC LAYOUT'!$W:$W,OB!$A:$A,0)),"") | W129: =+B129+1 -> 66 | X129: =IFERROR(INDEX(OB!$G:$G,MATCH('aSC LAYOUT'!$W:$W,OB!$A:$A,0)),"")
A130: =IFERROR(INDEX(OB!$G:$G,MATCH('aSC LAYOUT'!$B:$B,OB!$A:$A,0)),"") | C130: =IFERROR(INDEX(OB!$B:$B,MATCH('aSC LAYOUT'!$B:$B,OB!$A:$A,0)),"") | E130: =IFERROR(INDEX(OB!$C:$C,MATCH('aSC LAYOUT'!$B:$B,OB!$A:$A,0)),"") | F130: =IFERROR(INDEX(OB!$K:$K,MATCH('aSC LAYOUT'!$B:$B,OB!$A:$A,0)),"") | G130: =IF(C130="","",(MROUND(IF(E130<=0,0,60/E130),5))) | I130: WS | P130: WS | R130: =IF(V130="","",(MROUND(IF(T130<=0,0,60/T130),5))) | S130: =IFERROR(INDEX(OB!$K:$K,MATCH('aSC LAYOUT'!$W:$W,OB!$A:$A,0)),"") | T130: =IFERROR(INDEX(OB!$C:$C,MATCH('aSC LAYOUT'!$W:$W,OB!$A:$A,0)),"") | V130: =IFERROR(INDEX(OB!$B:$B,MATCH('aSC LAYOUT'!$W:$W,OB!$A:$A,0)),"") | X130: =IFERROR(INDEX(OB!$G:$G,MATCH('aSC LAYOUT'!$W:$W,OB!$A:$A,0)),"")
A131: =IFERROR(INDEX(OB!$G:$G,MATCH('aSC LAYOUT'!$B:$B,OB!$A:$A,0)),"") | C131: =IFERROR(INDEX(OB!$B:$B,MATCH('aSC LAYOUT'!$B:$B,OB!$A:$A,0)),"") | E131: =IFERROR(INDEX(OB!$C:$C,MATCH('aSC LAYOUT'!$B:$B,OB!$A:$A,0)),"") | F131: =IFERROR(INDEX(OB!$K:$K,MATCH('aSC LAYOUT'!$B:$B,OB!$A:$A,0)),"") | G131: =IF(C131="","",(MROUND(IF(E131<=0,0,60/E131),5))) | H131: =F132 -> 1 | I131: =+I136+1 -> 41 | P131: =+I131+1 -> 42 | Q131: =S132 -> 0 | R131: =IF(V131="","",(MROUND(IF(T131<=0,0,60/T131),5))) | S131: =IFERROR(INDEX(OB!$K:$K,MATCH('aSC LAYOUT'!$W:$W,OB!$A:$A,0)),"") | T131: =IFERROR(INDEX(OB!$C:$C,MATCH('aSC LAYOUT'!$W:$W,OB!$A:$A,0)),"") | V131: =IFERROR(INDEX(OB!$B:$B,MATCH('aSC LAYOUT'!$W:$W,OB!$A:$A,0)),"") | X131: =IFERROR(INDEX(OB!$G:$G,MATCH('aSC LAYOUT'!$W:$W,OB!$A:$A,0)),"")
...

Sheet BIHOURLY 
A1: SIDNEY APPARELS L.L.C. , AQABA
A2: STYLE NO | C2: =+OB!C2 -> S2554MESS651WV | D2: LINE: - S-24 | E2: Bihourly
C3: TARGET: | D3: 1000 | I3: NAME: | K3: =OB!M3 -> NAZIR
A4: S NO | B4: OPERATION | C4: OPERATOR | D4: M/C | E4: M/P | F4: BI-HRLY TARGET | G4: Op. WIP | H4: 7.3-9.3 | I4: 9.3-11.45 | J4: 11.45-1.45 | K4: 1.45-4 | L4: 4-6.15
A5: 1 | B5: =IFERROR(INDEX(OB!B:B,MATCH('BIHOURLY '!A:A,OB!A:A,0)),"") -> ATTACH THREE STRIPE | C5: HAJERA | D5: =IFERROR(INDEX(OB!G:G,MATCH('BIHOURLY '!A:A,OB!A:A,0)),"") -> KANSAI | E5: 2 | F5: 100
C6: NAJMOON | F6: 100
A8: =+A5+1 -> 2 | B8: =IFERROR(INDEX(OB!B:B,MATCH('BIHOURLY '!A:A,OB!A:A,0)),"") -> CHECK & TRIM THREE STRIPE | C8: KATHIJA | D8: IRON TABLE | E8: 1 | F8: 200
A10: =+A8+1 -> 3 | B10: =IFERROR(INDEX(OB!B:B,MATCH('BIHOURLY '!A:A,OB!A:A,0)),"") -> JOIN BACK RISE | D10: =IFERROR(INDEX(OB!G:G,MATCH('BIHOURLY '!A:A,OB!A:A,0)),"") -> OL4T | E10: =IFERROR(INDEX(OB!K:K,MATCH('BIHOURLY '!A:A,OB!A:A,0)),"") -> 0.5 | F10: =IFERROR((OB!$K$3/'BIHOURLY '!E10)/5,"") -> 340
A12: =+A10+1 -> 4 | B12: =IFERROR(INDEX(OB!B:B,MATCH('BIHOURLY '!A:A,OB!A:A,0)),"") -> FUSE & CREASE BOTTOM FOR ZIPPER | D12: =IFERROR(INDEX(OB!G:G,MATCH('BIHOURLY '!A:A,OB!A:A,0)),"") -> IRON TABLE | E12: =IFERROR(INDEX(OB!K:K,MATCH('BIHOURLY '!A:A,OB!A:A,0)),"") -> 1.25 | F12: =IFERROR((OB!$K$3/'BIHOURLY '!E12)/5,"") -> 136
A14: =+A12+1 -> 5 | B14: =IFERROR(INDEX(OB!B:B,MATCH('BIHOURLY '!A:A,OB!A:A,0)),"") -> SERGE BOTTOM FOR LEG ZIPPER*2 | D14: =IFERROR(INDEX(OB!G:G,MATCH('BIHOURLY '!A:A,OB!A:A,0)),"") -> OL4T | E14: =IFERROR(INDEX(OB!K:K,MATCH('BIHOURLY '!A:A,OB!A:A,0)),"") -> 0.5 | F14: =IFERROR((OB!$K$3/'BIHOURLY '!E14)/5,"") -> 340
A16: =+A14+1 -> 6 | B16: =IFERROR(INDEX(OB!B:B,MATCH('BIHOURLY '!A:A,OB!A:A,0)),"") -> 0 | D16: =IFERROR(INDEX(OB!G:G,MATCH('BIHOURLY '!A:A,OB!A:A,0)),"") -> 0 | E16: =IFERROR(INDEX(OB!K:K,MATCH('BIHOURLY '!A:A,OB!A:A,0)),"") | F16: =IFERROR((OB!$K$3/'BIHOURLY '!E16)/5,"")
A18: =+A16+1 -> 7 | B18: =IFERROR(INDEX(OB!B:B,MATCH('BIHOURLY '!A:A,OB!A:A,0)),"") -> 0 | D18: =IFERROR(INDEX(OB!G:G,MATCH('BIHOURLY '!A:A,OB!A:A,0)),"") -> 0 | E18: =IFERROR(INDEX(OB!K:K,MATCH('BIHOURLY '!A:A,OB!A:A,0)),"") | F18: =IFERROR((OB!$K$3/'BIHOURLY '!E18)/5,"")
A20: =+A18+1 -> 8 | B20: =IFERROR(INDEX(OB!B:B,MATCH('BIHOURLY '!A:A,OB!A:A,0)),"") -> 0 | D20: =IFERROR(INDEX(OB!G:G,MATCH('BIHOURLY '!A:A,OB!A:A,0)),"") -> 0 | E20: =IFERROR(INDEX(OB!K:K,MATCH('BIHOURLY '!A:A,OB!A:A,0)),"") | F20: =IFERROR((OB!$K$3/'BIHOURLY '!E20)/5,"")
A22: =+A20+1 -> 9 | B22: =IFERROR(INDEX(OB!B:B,MATCH('BIHOURLY '!A:A,OB!A:A,0)),"") -> 0 | D22: =IFERROR(INDEX(OB!G:G,MATCH('BIHOURLY '!A:A,OB!A:A,0)),"") -> 0 | E22: =IFERROR(INDEX(OB!K:K,MATCH('BIHOURLY '!A:A,OB!A:A,0)),"") | F22: =IFERROR((OB!$K$3/'BIHOURLY '!E22)/5,"")
A24: =+A22+1 -> 10 | B24: =IFERROR(INDEX(OB!B:B,MATCH('BIHOURLY '!A:A,OB!A:A,0)),"") -> 0 | D24: =IFERROR(INDEX(OB!G:G,MATCH('BIHOURLY '!A:A,OB!A:A,0)),"") -> 0 | E24: =IFERROR(INDEX(OB!K:K,MATCH('BIHOURLY '!A:A,OB!A:A,0)),"") | F24: =IFERROR((OB!$K$3/'BIHOURLY '!E24)/5,"")
A26: =+A24+1 -> 11 | B26: =IFERROR(INDEX(OB!B:B,MATCH('BIHOURLY '!A:A,OB!A:A,0)),"") -> 0 | D26: =IFERROR(INDEX(OB!G:G,MATCH('BIHOURLY '!A:A,OB!A:A,0)),"") -> 0 | E26: =IFERROR(INDEX(OB!K:K,MATCH('BIHOURLY '!A:A,OB!A:A,0)),"") | F26: =IFERROR((OB!$K$3/'BIHOURLY '!E26)/5,"")
A28: =+A26+1 -> 12 | B28: =IFERROR(INDEX(OB!B:B,MATCH('BIHOURLY '!A:A,OB!A:A,0)),"") -> 0 | D28: =IFERROR(INDEX(OB!G:G,MATCH('BIHOURLY '!A:A,OB!A:A,0)),"") -> 0 | E28: =IFERROR(INDEX(OB!K:K,MATCH('BIHOURLY '!A:A,OB!A:A,0)),"") | F28: =IFERROR((OB!$K$3/'BIHOURLY '!E28)/5,"")
A31: =+A28+1 -> 13 | B31: =IFERROR(INDEX(OB!B:B,MATCH('BIHOURLY '!A:A,OB!A:A,0)),"") -> FUSE & CREASE POCKET MOUTH | C31: JANISH | D31: =IFERROR(INDEX(OB!G:G,MATCH('BIHOURLY '!A:A,OB!A:A,0)),"") -> IRON TABLE | E31: 1 | F31: 200
A33: =+A31+1 -> 14 | B33: =IFERROR(INDEX(OB!B:B,MATCH('BIHOURLY '!A:A,OB!A:A,0)),"") -> ATTACH FACING TO POCKET BAG*2 | C33: SUMI | D33: =IFERROR(INDEX(OB!G:G,MATCH('BIHOURLY '!A:A,OB!A:A,0)),"") -> SNLS | E33: 1 | F33: 200
A35: =+A33+1 -> 15 | B35: =IFERROR(INDEX(OB!B:B,MATCH('BIHOURLY '!A:A,OB!A:A,0)),"") -> ATTACH POCKET BAG TO FRONT | C35: SHAHIDA | D35: =IFERROR(INDEX(OB!G:G,MATCH('BIHOURLY '!A:A,OB!A:A,0)),"") -> SNLS | E35: =IFERROR(INDEX(OB!K:K,MATCH('BIHOURLY '!A:A,OB!A:A,0)),"") -> 1 | F35: 200
B37: PKT SEARGING & BOTTOM SERGING*4 | C37: CHOMPA | D37: OL4T | E37: 1 | F37: 200
A39: =+A35+1 -> 16 | B39: =IFERROR(INDEX(OB!B:B,MATCH('BIHOURLY '!A:A,OB!A:A,0)),"") -> SHADOW STITCH POCKET MOUTH & CUT NOTCH | C39: SHAHIDA | D39: =IFERROR(INDEX(OB!G:G,MATCH('BIHOURLY '!A:A,OB!A:A,0)),"") -> SNLS | E39: =IFERROR(INDEX(OB!K:K,MATCH('BIHOURLY '!A:A,OB!A:A,0)),"") -> 1 | F39: 200
B41: PKT MOUTH IRON | C41: RAPIN | D41: IRON TABLE | E41: 1 | F41: 200
A43: =+A39+1 -> 17 | B43: =IFERROR(INDEX(OB!B:B,MATCH('BIHOURLY '!A:A,OB!A:A,0)),"") -> TACK INNER POCKET BAG | C43: RUKSHANA | D43: =IFERROR(INDEX(OB!G:G,MATCH('BIHOURLY '!A:A,OB!A:A,0)),"") -> SNLS | E43: =IFERROR(INDEX(OB!K:K,MATCH('BIHOURLY '!A:A,OB!A:A,0)),"") -> 1 | F43: 200
A45: =+A43+1 -> 18 | B45: CLOSE PKT BAG & BOTTO PRE OL | C45: MILA | D45: =IFERROR(INDEX(OB!G:G,MATCH('BIHOURLY '!A:A,OB!A:A,0)),"") -> OL4T | E45: =IFERROR(INDEX(OB!K:K,MATCH('BIHOURLY '!A:A,OB!A:A,0)),"") -> 1 | F45: 200
A47: =+A45+1 -> 19 | B47: =IFERROR(INDEX(OB!B:B,MATCH('BIHOURLY '!A:A,OB!A:A,0)),"") -> POCKET BAG SIDE WAIST TACK | C47: SHILA | D47: =IFERROR(INDEX(OB!G:G,MATCH('BIHOURLY '!A:A,OB!A:A,0)),"") -> SNLS | E47: 1 | F47: 200
A49: =+A47+1 -> 20 | B49: BOTTOM FOLD & IRON | C49: JAHANARA | D49: IRON TABLE | E49: 1 | F49: 200
A51: =+A49+1 -> 21 | B51: =IFERROR(INDEX(OB!B:B,MATCH('BIHOURLY '!A:A,OB!A:A,0)),"") -> JOIN FRONT RISE | D51: =IFERROR(INDEX(OB!G:G,MATCH('BIHOURLY '!A:A,OB!A:A,0)),"") -> OL4T | E51: =IFERROR(INDEX(OB!K:K,MATCH('BIHOURLY '!A:A,OB!A:A,0)),"") -> 0.5 | F51: =IFERROR((OB!$K$3/'BIHOURLY '!E51)/5,"") -> 340
A53: =+A51+1 -> 22 | B53: =IFERROR(INDEX(OB!B:B,MATCH('BIHOURLY '!A:A,OB!A:A,0)),"") -> 0 | D53: =IFERROR(INDEX(OB!G:G,MATCH('BIHOURLY '!A:A,OB!A:A,0)),"") -> 0 | E53: =IFERROR(INDEX(OB!K:K,MATCH('BIHOURLY '!A:A,OB!A:A,0)),"") | F53: =IFERROR((OB!$K$3/'BIHOURLY '!E53)/5,"")
A55: =+A53+1 -> 23 | B55: =IFERROR(INDEX(OB!B:B,MATCH('BIHOURLY '!A:A,OB!A:A,0)),"") -> 0 | D55: =IFERROR(INDEX(OB!G:G,MATCH('BIHOURLY '!A:A,OB!A:A,0)),"") -> 0 | E55: =IFERROR(INDEX(OB!K:K,MATCH('BIHOURLY '!A:A,OB!A:A,0)),"") | F55: =IFERROR((OB!$K$3/'BIHOURLY '!E55)/5,"")
A57: =+A55+1 -> 24 | B57: =IFERROR(INDEX(OB!B:B,MATCH('BIHOURLY '!A:A,OB!A:A,0)),"") -> 0 | D57: =IFERROR(INDEX(OB!G:G,MATCH('BIHOURLY '!A:A,OB!A:A,0)),"") -> 0 | E57: =IFERROR(INDEX(OB!K:K,MATCH('BIHOURLY '!A:A,OB!A:A,0)),"") | F57: =IFERROR((OB!$K$3/'BIHOURLY '!E57)/5,"")
A59: =+A57+1 -> 25 | B59: =IFERROR(INDEX(OB!B:B,MATCH('BIHOURLY '!A:A,OB!A:A,0)),"") -> 0 | D59: =IFERROR(INDEX(OB!G:G,MATCH('BIHOURLY '!A:A,OB!A:A,0)),"") -> 0 | E59: =IFERROR(INDEX(OB!K:K,MATCH('BIHOURLY '!A:A,OB!A:A,0)),"") | F59: =IFERROR((OB!$K$3/'BIHOURLY '!E59)/5,"")
A61: =+A59+1 -> 26 | B61: =IFERROR(INDEX(OB!B:B,MATCH('BIHOURLY '!A:A,OB!A:A,0)),"") -> 0 | D61: =IFERROR(INDEX(OB!G:G,MATCH('BIHOURLY '!A:A,OB!A:A,0)),"") -> 0 | E61: =IFERROR(INDEX(OB!K:K,MATCH('BIHOURLY '!A:A,OB!A:A,0)),"") | F61: =IFERROR((OB!$K$3/'BIHOURLY '!E61)/5,"")
A63: =+A61+1 -> 27 | B63: =IFERROR(INDEX(OB!B:B,MATCH('BIHOURLY '!A:A,OB!A:A,0)),"") -> 0 | D63: =IFERROR(INDEX(OB!G:G,MATCH('BIHOURLY '!A:A,OB!A:A,0)),"") -> 0 | E63: =IFERROR(INDEX(OB!K:K,MATCH('BIHOURLY '!A:A,OB!A:A,0)),"") | F63: =IFERROR((OB!$K$3/'BIHOURLY '!E63)/5,"")
A65: =+A63+1 -> 28 | B65: =IFERROR(INDEX(OB!B:B,MATCH('BIHOURLY '!A:A,OB!A:A,0)),"") -> 0 | D65: =IFERROR(INDEX(OB!G:G,MATCH('BIHOURLY '!A:A,OB!A:A,0)),"") -> 0 | E65: =IFERROR(INDEX(OB!K:K,MATCH('BIHOURLY '!A:A,OB!A:A,0)),"") | F65: =IFERROR((OB!$K$3/'BIHOURLY '!E65)/5,"")
A67: =+A65+1 -> 29 | B67: =IFERROR(INDEX(OB!B:B,MATCH('BIHOURLY '!A:A,OB!A:A,0)),"") -> 0 | D67: =IFERROR(INDEX(OB!G:G,MATCH('BIHOURLY '!A:A,OB!A:A,0)),"") -> 0 | E67: =IFERROR(INDEX(OB!K:K,MATCH('BIHOURLY '!A:A,OB!A:A,0)),"") | F67: =IFERROR((OB!$K$3/'BIHOURLY '!E67)/5,"")
A69: =+A67+1 -> 30 | B69: =IFERROR(INDEX(OB!B:B,MATCH('BIHOURLY '!A:A,OB!A:A,0)),"") -> 0 | D69: =IFERROR(INDEX(OB!G:G,MATCH('BIHOURLY '!A:A,OB!A:A,0)),"") -> 0 | E69: =IFERROR(INDEX(OB!K:K,MATCH('BIHOURLY '!A:A,OB!A:A,0)),"") | F69: =IFERROR((OB!$K$3/'BIHOURLY '!E69)/5,"")
B71: BACK RISE & FRANT RISE OL | C71: ARIF | D71: OL5T | E71: 1 | F71: 200
A73: =+A69+1 -> 31 | B73: =IFERROR(INDEX(OB!B:B,MATCH('BIHOURLY '!A:A,OB!A:A,0)),"") -> TACK FRONT & BACK AT INSEAM FOR LEG ZIPPER | C73: SHAMIN | D73: =IFERROR(INDEX(OB!G:G,MATCH('BIHOURLY '!A:A,OB!A:A,0)),"") -> SNLS | E73: 2 | F73: 100
C74: NASRIN | F74: 100
A76: =+A73+1 -> 32 | B76: =IFERROR(INDEX(OB!B:B,MATCH('BIHOURLY '!A:A,OB!A:A,0)),"") -> INSEAM | C76: SHERINA | D76: OL5T | E76: =IFERROR(INDEX(OB!K:K,MATCH('BIHOURLY '!A:A,OB!A:A,0)),"") -> 1 | F76: 200
A78: =+A76+1 -> 33 | B78: =IFERROR(INDEX(OB!B:B,MATCH('BIHOURLY '!A:A,OB!A:A,0)),"") -> TACK LEG ZIPPER | C78: SHABANA | D78: =IFERROR(INDEX(OB!G:G,MATCH('BIHOURLY '!A:A,OB!A:A,0)),"") -> SNLS | E78: 1 | F78: =IFERROR((OB!$K$3/'BIHOURLY '!E78)/5,"") -> 170
A80: =+A78+1 -> 34 | B80: =IFERROR(INDEX(OB!B:B,MATCH('BIHOURLY '!A:A,OB!A:A,0)),"") -> ATTACH LEG ZIPPER | C80: KATHIJA | D80: =IFERROR(INDEX(OB!G:G,MATCH('BIHOURLY '!A:A,OB!A:A,0)),"") -> SNLS | E80: 3 | F80: 85
C81: SHARIMI | F81: 85
C82: BISTA | F82: 85
A84: =+A80+1 -> 35 | B84: =IFERROR(INDEX(OB!B:B,MATCH('BIHOURLY '!A:A,OB!A:A,0)),"") -> TACK FOR SIDE SEAM | C84: SHABANA | D84: =IFERROR(INDEX(OB!G:G,MATCH('BIHOURLY '!A:A,OB!A:A,0)),"") -> SNLS | E84: 2 | F84: 100
C85: AYESHA | F85: 100
A87: =+A84+1 -> 36 | B87: =IFERROR(INDEX(OB!B:B,MATCH('BIHOURLY '!A:A,OB!A:A,0)),"") -> SIDE SEAM | C87: JUTHI | D87: =IFERROR(INDEX(OB!G:G,MATCH('BIHOURLY '!A:A,OB!A:A,0)),"") -> OL4T | E87: 2 | F87: 100
F88: 100
A90: =+A87+1 -> 37 | B90: PKT BKT | C90: RESHMA | D90: BKT | E90: =IFERROR(INDEX(OB!K:K,MATCH('BIHOURLY '!A:A,OB!A:A,0)),"") -> 1 | F90: 200
A92: =+A90+1 -> 38 | B92: =IFERROR(INDEX(OB!B:B,MATCH('BIHOURLY '!A:A,OB!A:A,0)),"") -> MARK FOR HIGH LOW | D92: =IFERROR(INDEX(OB!G:G,MATCH('BIHOURLY '!A:A,OB!A:A,0)),"") -> TABLE | E92: =IFERROR(INDEX(OB!K:K,MATCH('BIHOURLY '!A:A,OB!A:A,0)),"") -> 0.5 | F92: =IFERROR((OB!$K$3/'BIHOURLY '!E92)/5,"") -> 340
A94: =+A92+1 -> 39 | B94: =IFERROR(INDEX(OB!B:B,MATCH('BIHOURLY '!A:A,OB!A:A,0)),"") -> MARK & TACK WB FOR BUTTON HOLE | C94: SALAYA | D94: =IFERROR(INDEX(OB!G:G,MATCH('BIHOURLY '!A:A,OB!A:A,0)),"") -> SNLS | E94: 1 | F94: 200
A96: =+A94+1 -> 40 | B96: =IFERROR(INDEX(OB!B:B,MATCH('BIHOURLY '!A:A,OB!A:A,0)),"") -> CREASE WB JOININGS TO SPLIT | D96: =IFERROR(INDEX(OB!G:G,MATCH('BIHOURLY '!A:A,OB!A:A,0)),"") -> IRON TABLE | E96: =IFERROR(INDEX(OB!K:K,MATCH('BIHOURLY '!A:A,OB!A:A,0)),"") -> 0.75 | F96: =IFERROR((OB!$K$3/'BIHOURLY '!E96)/5,"") -> 226.66667
A98: =+A96+1 -> 41 | B98: =IFERROR(INDEX(OB!B:B,MATCH('BIHOURLY '!A:A,OB!A:A,0)),"") -> TOP STITCH BUTTON HOLE SIDE | C98: THAMANNA | D98: =IFERROR(INDEX(OB!G:G,MATCH('BIHOURLY '!A:A,OB!A:A,0)),"") -> SNLS | E98: 1 | F98: 200
A100: =+A98+1 -> 42 | B100: =IFERROR(INDEX(OB!B:B,MATCH('BIHOURLY '!A:A,OB!A:A,0)),"") -> ATTACH WB TO BODY | C100: SALMA | D100: =IFERROR(INDEX(OB!G:G,MATCH('BIHOURLY '!A:A,OB!A:A,0)),"") -> OL4T | E100: 2 | F100: 100
C101: RESHMA | F101: 100
A103: =+A100+1 -> 43 | B103: =IFERROR(INDEX(OB!B:B,MATCH('BIHOURLY '!A:A,OB!A:A,0)),"") -> MAKE ELASTIC READY | D103: =IFERROR(INDEX(OB!G:G,MATCH('BIHOURLY '!A:A,OB!A:A,0)),"") -> PREP | E103: =IFERROR(INDEX(OB!K:K,MATCH('BIHOURLY '!A:A,OB!A:A,0)),"") -> 0.5 | F103: =IFERROR((OB!$K$3/'BIHOURLY '!E103)/5,"") -> 340
A105: =+A103+1 -> 44 | B105: =IFERROR(INDEX(OB!B:B,MATCH('BIHOURLY '!A:A,OB!A:A,0)),"") -> ATTACH ELASTIC TO WB | C105: THALIMA | D105: =IFERROR(INDEX(OB!G:G,MATCH('BIHOURLY '!A:A,OB!A:A,0)),"") -> FL3T-CB | E105: =IFERROR(INDEX(OB!K:K,MATCH('BIHOURLY '!A:A,OB!A:A,0)),"") -> 1 | F105: 200
A107: =+A105+1 -> 45 | B107: =IFERROR(INDEX(OB!B:B,MATCH('BIHOURLY '!A:A,OB!A:A,0)),"") -> ATTACH LABEL*2 | C107: NAZMA | D107: =IFERROR(INDEX(OB!G:G,MATCH('BIHOURLY '!A:A,OB!A:A,0)),"") -> SNLS | E107: 1 | F107: 200
A109: =+A107+1 -> 46 | B109: =IFERROR(INDEX(OB!B:B,MATCH('BIHOURLY '!A:A,OB!A:A,0)),"") -> VERTICAL TACK WB | C109: JOSNA | D109: =IFERROR(INDEX(OB!G:G,MATCH('BIHOURLY '!A:A,OB!A:A,0)),"") -> SNLS | E109: 1 | F109: 200
A111: =+A109+1 -> 47 | B111: =IFERROR(INDEX(OB!B:B,MATCH('BIHOURLY '!A:A,OB!A:A,0)),"") -> CLOSE WAISTBAND | C111: HASMA | D111: =IFERROR(INDEX(OB!G:G,MATCH('BIHOURLY '!A:A,OB!A:A,0)),"") -> KANSAI | E111: =IFERROR(INDEX(OB!K:K,MATCH('BIHOURLY '!A:A,OB!A:A,0)),"") -> 1 | F111: 200
A113: =+A111+1 -> 48 | B113: =IFERROR(INDEX(OB!B:B,MATCH('BIHOURLY '!A:A,OB!A:A,0)),"") -> REMOVE VERTICAL TACK | C113: THAMANNA | D113: =IFERROR(INDEX(OB!G:G,MATCH('BIHOURLY '!A:A,OB!A:A,0)),"") -> TABLE | E113: =IFERROR(INDEX(OB!K:K,MATCH('BIHOURLY '!A:A,OB!A:A,0)),"") -> 0.5 | F113: =IFERROR((OB!$K$3/'BIHOURLY '!E113)/5,"") -> 340
A115: =+A113+1 -> 49 | B115: =IFERROR(INDEX(OB!B:B,MATCH('BIHOURLY '!A:A,OB!A:A,0)),"") -> CREASE BOTTOM FOR HEM | D115: =IFERROR(INDEX(OB!G:G,MATCH('BIHOURLY '!A:A,OB!A:A,0)),"") -> IRON TABLE | E115: =IFERROR(INDEX(OB!K:K,MATCH('BIHOURLY '!A:A,OB!A:A,0)),"") -> 0.75 | F115: =IFERROR((OB!$K$3/'BIHOURLY '!E115)/5,"") -> 226.66667
A117: =+A115+1 -> 50 | B117: =IFERROR(INDEX(OB!B:B,MATCH('BIHOURLY '!A:A,OB!A:A,0)),"") -> FOLD & TACK BOTTOM WITH ZIPPER FOR HEM | C117: THANJILA | D117: =IFERROR(INDEX(OB!G:G,MATCH('BIHOURLY '!A:A,OB!A:A,0)),"") -> SNLS | E117: =IFERROR(INDEX(OB!K:K,MATCH('BIHOURLY '!A:A,OB!A:A,0)),"") -> 1 | F117: 200
A119: =+A117+1 -> 51 | B119: =IFERROR(INDEX(OB!B:B,MATCH('BIHOURLY '!A:A,OB!A:A,0)),"") -> BOTTOM HEM | C119: SHAHIMA | D119: =IFERROR(INDEX(OB!G:G,MATCH('BIHOURLY '!A:A,OB!A:A,0)),"") -> SNLS | E119: =IFERROR(INDEX(OB!K:K,MATCH('BIHOURLY '!A:A,OB!A:A,0)),"") -> 1 | F119: 200
C120: JOLI
A122: =+A119+1 -> 52 | B122: =IFERROR(INDEX(OB!B:B,MATCH('BIHOURLY '!A:A,OB!A:A,0)),"") -> BARTACK FRONT WB*4 | D122: =IFERROR(INDEX(OB!G:G,MATCH('BIHOURLY '!A:A,OB!A:A,0)),"") -> BRTK | E122: =IFERROR(INDEX(OB!K:K,MATCH('BIHOURLY '!A:A,OB!A:A,0)),"") -> 0.5 | F122: =IFERROR((OB!$K$3/'BIHOURLY '!E122)/5,"") -> 340
A124: =+A122+1 -> 53 | B124: =IFERROR(INDEX(OB!B:B,MATCH('BIHOURLY '!A:A,OB!A:A,0)),"") -> INSERT DRAWCORD | C124: THAMANNA | D124: =IFERROR(INDEX(OB!G:G,MATCH('BIHOURLY '!A:A,OB!A:A,0)),"") -> TABLE | E124: 1 | F124: 200
A126: =+A124+1 -> 54 | B126: =IFERROR(INDEX(OB!B:B,MATCH('BIHOURLY '!A:A,OB!A:A,0)),"") -> BARTACK WB*4, CROTCH*1 & ZIPPER*2 | C126: MALA | D126: =IFERROR(INDEX(OB!G:G,MATCH('BIHOURLY '!A:A,OB!A:A,0)),"") -> BRTK | E126: 1 | F126: 200
A128: =+A126+1 -> 55 | B128: =IFERROR(INDEX(OB!B:B,MATCH('BIHOURLY '!A:A,OB!A:A,0)),"") -> TRIM AND INLINE CHECK | D128: =IFERROR(INDEX(OB!G:G,MATCH('BIHOURLY '!A:A,OB!A:A,0)),"") -> TABLE | E128: =IFERROR(INDEX(OB!K:K,MATCH('BIHOURLY '!A:A,OB!A:A,0)),"") -> 1 | F128: =IFERROR((OB!$K$3/'BIHOURLY '!E128)/5,"") -> 170
A130: =+A128+1 -> 56 | B130: =IFERROR(INDEX(OB!B:B,MATCH('BIHOURLY '!A:A,OB!A:A,0)),"") -> BUFFER | D130: =IFERROR(INDEX(OB!G:G,MATCH('BIHOURLY '!A:A,OB!A:A,0)),"") -> 0 | E130: =IFERROR(INDEX(OB!K:K,MATCH('BIHOURLY '!A:A,OB!A:A,0)),"") -> 11.25 | F130: =IFERROR((OB!$K$3/'BIHOURLY '!E130)/5,"") -> 15.111111
A132: =+A130+1 -> 57 | B132: =IFERROR(INDEX(OB!B:B,MATCH('BIHOURLY '!A:A,OB!A:A,0)),"") -> 0 | D132: =IFERROR(INDEX(OB!G:G,MATCH('BIHOURLY '!A:A,OB!A:A,0)),"") -> 0 | E132: =IFERROR(INDEX(OB!K:K,MATCH('BIHOURLY '!A:A,OB!A:A,0)),"") | F132: =IFERROR((OB!$K$3/'BIHOURLY '!E132)/5,"")
A134: =+A132+1 -> 58 | B134: =IFERROR(INDEX(OB!B:B,MATCH('BIHOURLY '!A:A,OB!A:A,0)),"") -> 0 | D134: =IFERROR(INDEX(OB!G:G,MATCH('BIHOURLY '!A:A,OB!A:A,0)),"") -> 0 | E134: =IFERROR(INDEX(OB!K:K,MATCH('BIHOURLY '!A:A,OB!A:A,0)),"") | F134: =IFERROR((OB!$K$3/'BIHOURLY '!E134)/5,"")
B136: THRAED TRIMING | C136: NAZMA | D136: TABLE | E136: 2 | F136: 100
C137: KTHIJA | F137: 100
A139: =+A134+1 -> 59 | B139: =IFERROR(INDEX(OB!B:B,MATCH('BIHOURLY '!A:A,OB!A:A,0)),"") -> QUALITY CHECKER | C139: HAWA | D139: =IFERROR(INDEX(OB!G:G,MATCH('BIHOURLY '!A:A,OB!A:A,0)),"") -> TABLE | E139: =IFERROR(INDEX(OB!K:K,MATCH('BIHOURLY '!A:A,OB!A:A,0)),"") | F139: 200
C140: SANYA
A142: =+A139+1 -> 60 | B142: =IFERROR(INDEX(OB!B:B,MATCH('BIHOURLY '!A:A,OB!A:A,0)),"") -> IRONING GARMENT + W/BAND | C142: JUWEL | D142: =IFERROR(INDEX(OB!G:G,MATCH('BIHOURLY '!A:A,OB!A:A,0)),"") -> IRON TABLE | E142: =IFERROR(INDEX(OB!K:K,MATCH('BIHOURLY '!A:A,OB!A:A,0)),"") -> 1 | F142: 200
A145: =+A142+1 -> 61 | B145: =IFERROR(INDEX(OB!B:B,MATCH('BIHOURLY '!A:A,OB!A:A,0)),"") -> SPEC & PRESENTATION QC | C145: MONIKA | D145: =IFERROR(INDEX(OB!G:G,MATCH('BIHOURLY '!A:A,OB!A:A,0)),"") -> TABLE | E145: =IFERROR(INDEX(OB!K:K,MATCH('BIHOURLY '!A:A,OB!A:A,0)),"") | F145: 200
A147: =+A145+1 -> 62 | B147: =IFERROR(INDEX(OB!B:B,MATCH('BIHOURLY '!A:A,OB!A:A,0)),"") -> MATCHBOOK | C147: RUNA | D147: =IFERROR(INDEX(OB!G:G,MATCH('BIHOURLY '!A:A,OB!A:A,0)),"") -> BA | E147: =IFERROR(INDEX(OB!K:K,MATCH('BIHOURLY '!A:A,OB!A:A,0)),"") -> 1 | F147: 200
A149: =+A147+1 -> 63 | B149: =IFERROR(INDEX(OB!B:B,MATCH('BIHOURLY '!A:A,OB!A:A,0)),"") -> HANGTAG | C149: ALA | D149: =IFERROR(INDEX(OB!G:G,MATCH('BIHOURLY '!A:A,OB!A:A,0)),"") -> TAG GUN | E149: 1 | F149: 200
A151: =+A149+1 -> 64 | B151: =IFERROR(INDEX(OB!B:B,MATCH('BIHOURLY '!A:A,OB!A:A,0)),"") -> FOLDING + POLYBAG | C151: SHIMA | D151: =IFERROR(INDEX(OB!G:G,MATCH('BIHOURLY '!A:A,OB!A:A,0)),"") -> TABLE | E151: =IFERROR(INDEX(OB!K:K,MATCH('BIHOURLY '!A:A,OB!A:A,0)),"") -> 1 | F151: 200
A153: =+A151+1 -> 65 | B153: =IFERROR(INDEX(OB!B:B,MATCH('BIHOURLY '!A:A,OB!A:A,0)),"") -> SKU + CTN | C153: KAUSAR | D153: =IFERROR(INDEX(OB!G:G,MATCH('BIHOURLY '!A:A,OB!A:A,0)),"") -> TABLE | E153: =IFERROR(INDEX(OB!K:K,MATCH('BIHOURLY '!A:A,OB!A:A,0)),"") -> 1 | F153: 20
A155: =+A153+1 -> 66 | B155: =IFERROR(INDEX(OB!B:B,MATCH('BIHOURLY '!A:A,OB!A:A,0)),"") | D155: =IFERROR(INDEX(OB!G:G,MATCH('BIHOURLY '!A:A,OB!A:A,0)),"") | E155: =IFERROR(INDEX(OB!K:K,MATCH('BIHOURLY '!A:A,OB!A:A,0)),"") | F155: =IFERROR((OB!$K$3/'BIHOURLY '!E155)/5,"")
A157: =+A155+1 -> 67 | B157: =IFERROR(INDEX(OB!B:B,MATCH('BIHOURLY '!A:A,OB!A:A,0)),"") | D157: =IFERROR(INDEX(OB!G:G,MATCH('BIHOURLY '!A:A,OB!A:A,0)),"") | E157: =IFERROR(INDEX(OB!K:K,MATCH('BIHOURLY '!A:A,OB!A:A,0)),"") | F157: =IFERROR((OB!$K$3/'BIHOURLY '!E157)/5,"")
A159: =+A157+1 -> 68 | B159: =IFERROR(INDEX(OB!B:B,MATCH('BIHOURLY '!A:A,OB!A:A,0)),"") | D159: =IFERROR(INDEX(OB!G:G,MATCH('BIHOURLY '!A:A,OB!A:A,0)),"") | E159: =IFERROR(INDEX(OB!K:K,MATCH('BIHOURLY '!A:A,OB!A:A,0)),"") | F159: =IFERROR((OB!$K$3/'BIHOURLY '!E159)/5,"")
A161: =+A159+1 -> 69 | B161: =IFERROR(INDEX(OB!B:B,MATCH('BIHOURLY '!A:A,OB!A:A,0)),"") | D161: =IFERROR(INDEX(OB!G:G,MATCH('BIHOURLY '!A:A,OB!A:A,0)),"") | E161: =IFERROR(INDEX(OB!K:K,MATCH('BIHOURLY '!A:A,OB!A:A,0)),"") | F161: =IFERROR((OB!$K$3/'BIHOURLY '!E161)/5,"")
A163: =+A161+1 -> 70 | B163: =IFERROR(INDEX(OB!B:B,MATCH('BIHOURLY '!A:A,OB!A:A,0)),"") | D163: =IFERROR(INDEX(OB!G:G,MATCH('BIHOURLY '!A:A,OB!A:A,0)),"") | E163: =IFERROR(INDEX(OB!K:K,MATCH('BIHOURLY '!A:A,OB!A:A,0)),"") | F163: =IFERROR((OB!$K$3/'BIHOURLY '!E163)/5,"")
A165: =+A163+1 -> 71 | B165: =IFERROR(INDEX(OB!B:B,MATCH('BIHOURLY '!A:A,OB!A:A,0)),"") | D165: =IFERROR(INDEX(OB!G:G,MATCH('BIHOURLY '!A:A,OB!A:A,0)),"") | E165: =IFERROR(INDEX(OB!K:K,MATCH('BIHOURLY '!A:A,OB!A:A,0)),"") | F165: =IFERROR((OB!$K$3/'BIHOURLY '!E165)/5,"")
A167: =+A165+1 -> 72 | B167: =IFERROR(INDEX(OB!B:B,MATCH('BIHOURLY '!A:A,OB!A:A,0)),"") | D167: =IFERROR(INDEX(OB!G:G,MATCH('BIHOURLY '!A:A,OB!A:A,0)),"") | E167: =IFERROR(INDEX(OB!K:K,MATCH('BIHOURLY '!A:A,OB!A:A,0)),"") | F167: =IFERROR((OB!$K$3/'BIHOURLY '!E167)/5,"")
A169: =+A167+1 -> 73 | B169: =IFERROR(INDEX(OB!B:B,MATCH('BIHOURLY '!A:A,OB!A:A,0)),"") | D169: =IFERROR(INDEX(OB!G:G,MATCH('BIHOURLY '!A:A,OB!A:A,0)),"") | E169: =IFERROR(INDEX(OB!K:K,MATCH('BIHOURLY '!A:A,OB!A:A,0)),"") | F169: =IFERROR((OB!$K$3/'BIHOURLY '!E169)/5,"")
A171: =+A169+1 -> 74 | B171: =IFERROR(INDEX(OB!B:B,MATCH('BIHOURLY '!A:A,OB!A:A,0)),"") | D171: =IFERROR(INDEX(OB!G:G,MATCH('BIHOURLY '!A:A,OB!A:A,0)),"") | E171: =IFERROR(INDEX(OB!K:K,MATCH('BIHOURLY '!A:A,OB!A:A,0)),"") | F171: =IFERROR((OB!$K$3/'BIHOURLY '!E171)/5,"")
A173: =+A171+1 -> 75 | B173: =IFERROR(INDEX(OB!B:B,MATCH('BIHOURLY '!A:A,OB!A:A,0)),"") | D173: =IFERROR(INDEX(OB!G:G,MATCH('BIHOURLY '!A:A,OB!A:A,0)),"") | E173: =IFERROR(INDEX(OB!K:K,MATCH('BIHOURLY '!A:A,OB!A:A,0)),"") | F173: =IFERROR((OB!$K$3/'BIHOURLY '!E173)/5,"")
A175: =+A173+1 -> 76 | B175: =IFERROR(INDEX(OB!B:B,MATCH('BIHOURLY '!A:A,OB!A:A,0)),"") | D175: =IFERROR(INDEX(OB!G:G,MATCH('BIHOURLY '!A:A,OB!A:A,0)),"") | E175: =IFERROR(INDEX(OB!K:K,MATCH('BIHOURLY '!A:A,OB!A:A,0)),"") | F175: =IFERROR((OB!$K$3/'BIHOURLY '!E175)/5,"")
A177: =+A175+1 -> 77 | B177: =IFERROR(INDEX(OB!B:B,MATCH('BIHOURLY '!A:A,OB!A:A,0)),"") | D177: =IFERROR(INDEX(OB!G:G,MATCH('BIHOURLY '!A:A,OB!A:A,0)),"") | E177: =IFERROR(INDEX(OB!K:K,MATCH('BIHOURLY '!A:A,OB!A:A,0)),"") | F177: =IFERROR((OB!$K$3/'BIHOURLY '!E177)/5,"")
... A203: =+A201+1 -> 90 | B203: =IFERROR(INDEX(OB!B:B,MATCH('BIHOURLY '!A:A,OB!A:A,0)),"") | D203: =IFERROR(INDEX(OB!G:G,MATCH('BIHOURLY '!A:A,OB!A:A,0)),"") | E203: =IFERROR(INDEX(OB!K:K,MATCH('BIHOURLY '!A:A,OB!A:A,0)),"") | F203: =IFERROR((OB!$K$3/'BIHOURLY '!E203)/5,"")

Sheet BIHOURLY  (2)
A1: SIDNEY APPARELS L.L.C. , AQABA
A2: STYLE NO | C2: =+OB!C2 -> S2554MESS651WV | D2: LINE: - S-24 | E2: Bihourly
C3: TARGET: | D3: 1000 | I3: NAME: | K3: wasana
A4: S NO | B4: OPERATION | C4: OPERATOR | D4: M/C | E4: M/P | F4: BI-HRLY TARGET | G4: Op. WIP | H4: 7.3-9.3 | I4: 9.3-11.45 | J4: 11.45-1.45 | K4: 1.45-4 | L4: 4-6.15
A5: 1 | B5: =IFERROR(INDEX(OB!B:B,MATCH('BIHOURLY (2)'!A:A,OB!A:A,0)),"") -> ATTACH THREE STRIPE | D5: =IFERROR(INDEX(OB!G:G,MATCH('BIHOURLY (2)'!A:A,OB!A:A,0)),"") -> KANSAI | E5: 2 | F5: 100
F6: 100
A8: =+A5+1 -> 2 | B8: =IFERROR(INDEX(OB!B:B,MATCH('BIHOURLY (2)'!A:A,OB!A:A,0)),"") -> CHECK & TRIM THREE STRIPE | D8: IRON TABLE | E8: 1 | F8: 200
A10: =+A8+1 -> 3 | B10: =IFERROR(INDEX(OB!B:B,MATCH('BIHOURLY (2)'!A:A,OB!A:A,0)),"") -> JOIN BACK RISE | D10: =IFERROR(INDEX(OB!G:G,MATCH('BIHOURLY (2)'!A:A,OB!A:A,0)),"") -> OL4T | E10: =IFERROR(INDEX(OB!K:K,MATCH('BIHOURLY (2)'!A:A,OB!A:A,0)),"") -> 0.5 | F10: =IFERROR((OB!$K$3/'BIHOURLY (2)'!E10)/5,"") -> 340
A12: =+A10+1 -> 4 | B12: =IFERROR(INDEX(OB!B:B,MATCH('BIHOURLY (2)'!A:A,OB!A:A,0)),"") -> FUSE & CREASE BOTTOM FOR ZIPPER | D12: =IFERROR(INDEX(OB!G:G,MATCH('BIHOURLY (2)'!A:A,OB!A:A,0)),"") -> IRON TABLE | E12: =IFERROR(INDEX(OB!K:K,MATCH('BIHOURLY (2)'!A:A,OB!A:A,0)),"") -> 1.25 | F12: =IFERROR((OB!$K$3/'BIHOURLY (2)'!E12)/5,"") -> 136
A14: =+A12+1 -> 5 | B14: =IFERROR(INDEX(OB!B:B,MATCH('BIHOURLY (2)'!A:A,OB!A:A,0)),"") -> SERGE BOTTOM FOR LEG ZIPPER*2 | D14: =IFERROR(INDEX(OB!G:G,MATCH('BIHOURLY (2)'!A:A,OB!A:A,0)),"") -> OL4T | E14: =IFERROR(INDEX(OB!K:K,MATCH('BIHOURLY (2)'!A:A,OB!A:A,0)),"") -> 0.5 | F14: =IFERROR((OB!$K$3/'BIHOURLY (2)'!E14)/5,"") -> 340
A16: =+A14+1 -> 6 | B16: =IFERROR(INDEX(OB!B:B,MATCH('BIHOURLY (2)'!A:A,OB!A:A,0)),"") -> 0 | D16: =IFERROR(INDEX(OB!G:G,MATCH('BIHOURLY (2)'!A:A,OB!A:A,0)),"") -> 0 | E16: =IFERROR(INDEX(OB!K:K,MATCH('BIHOURLY (2)'!A:A,OB!A:A,0)),"") | F16: =IFERROR((OB!$K$3/'BIHOURLY (2)'!E16)/5,"")
A18: =+A16+1 -> 7 | B18: =IFERROR(INDEX(OB!B:B,MATCH('BIHOURLY (2)'!A:A,OB!A:A,0)),"") -> 0 | D18: =IFERROR(INDEX(OB!G:G,MATCH('BIHOURLY (2)'!A:A,OB!A:A,0)),"") -> 0 | E18: =IFERROR(INDEX(OB!K:K,MATCH('BIHOURLY (2)'!A:A,OB!A:A,0)),"") | F18: =IFERROR((OB!$K$3/'BIHOURLY (2)'!E18)/5,"")
A20: =+A18+1 -> 8 | B20: =IFERROR(INDEX(OB!B:B,MATCH('BIHOURLY (2)'!A:A,OB!A:A,0)),"") -> 0 | D20: =IFERROR(INDEX(OB!G:G,MATCH('BIHOURLY (2)'!A:A,OB!A:A,0)),"") -> 0 | E20: =IFERROR(INDEX(OB!K:K,MATCH('BIHOURLY (2)'!A:A,OB!A:A,0)),"") | F20: =IFERROR((OB!$K$3/'BIHOURLY (2)'!E20)/5,"")
A22: =+A20+1 -> 9 | B22: =IFERROR(INDEX(OB!B:B,MATCH('BIHOURLY (2)'!A:A,OB!A:A,0)),"") -> 0 | D22: =IFERROR(INDEX(OB!G:G,MATCH('BIHOURLY (2)'!A:A,OB!A:A,0)),"") -> 0 | E22: =IFERROR(INDEX(OB!K:K,MATCH('BIHOURLY (2)'!A:A,OB!A:A,0)),"") | F22: =IFERROR((OB!$K$3/'BIHOURLY (2)'!E22)/5,"")
A24: =+A22+1 -> 10 | B24: =IFERROR(INDEX(OB!B:B,MATCH('BIHOURLY (2)'!A:A,OB!A:A,0)),"") -> 0 | D24: =IFERROR(INDEX(OB!G:G,MATCH('BIHOURLY (2)'!A:A,OB!A:A,0)),"") -> 0 | E24: =IFERROR(INDEX(OB!K:K,MATCH('BIHOURLY (2)'!A:A,OB!A:A,0)),"") | F24: =IFERROR((OB!$K$3/'BIHOURLY (2)'!E24)/5,"")
A26: =+A24+1 -> 11 | B26: =IFERROR(INDEX(OB!B:B,MATCH('BIHOURLY (2)'!A:A,OB!A:A,0)),"") -> 0 | D26: =IFERROR(INDEX(OB!G:G,MATCH('BIHOURLY (2)'!A:A,OB!A:A,0)),"") -> 0 | E26: =IFERROR(INDEX(OB!K:K,MATCH('BIHOURLY (2)'!A:A,OB!A:A,0)),"") | F26: =IFERROR((OB!$K$3/'BIHOURLY (2)'!E26)/5,"")
A28: =+A26+1 -> 12 | B28: =IFERROR(INDEX(OB!B:B,MATCH('BIHOURLY (2)'!A:A,OB!A:A,0)),"") -> 0 | D28: =IFERROR(INDEX(OB!G:G,MATCH('BIHOURLY (2)'!A:A,OB!A:A,0)),"") -> 0 | E28: =IFERROR(INDEX(OB!K:K,MATCH('BIHOURLY (2)'!A:A,OB!A:A,0)),"") | F28: =IFERROR((OB!$K$3/'BIHOURLY (2)'!E28)/5,"")
A31: =+A28+1 -> 13 | B31: =IFERROR(INDEX(OB!B:B,MATCH('BIHOURLY (2)'!A:A,OB!A:A,0)),"") -> FUSE & CREASE POCKET MOUTH | D31: =IFERROR(INDEX(OB!G:G,MATCH('BIHOURLY (2)'!A:A,OB!A:A,0)),"") -> IRON TABLE | E31: 1 | F31: 200
A33: =+A31+1 -> 14 | B33: =IFERROR(INDEX(OB!B:B,MATCH('BIHOURLY (2)'!A:A,OB!A:A,0)),"") -> ATTACH FACING TO POCKET BAG*2 | D33: =IFERROR(INDEX(OB!G:G,MATCH('BIHOURLY (2)'!A:A,OB!A:A,0)),"") -> SNLS | E33: 1 | F33: 200
A35: =+A33+1 -> 15 | B35: =IFERROR(INDEX(OB!B:B,MATCH('BIHOURLY (2)'!A:A,OB!A:A,0)),"") -> ATTACH POCKET BAG TO FRONT | D35: =IFERROR(INDEX(OB!G:G,MATCH('BIHOURLY (2)'!A:A,OB!A:A,0)),"") -> SNLS | E35: =IFERROR(INDEX(OB!K:K,MATCH('BIHOURLY (2)'!A:A,OB!A:A,0)),"") -> 1 | F35: 200
B37: PKT SEARGING & BOTTOM SERGING*4 | D37: OL4T | E37: 1 | F37: 200
A39: =+A35+1 -> 16 | B39: =IFERROR(INDEX(OB!B:B,MATCH('BIHOURLY (2)'!A:A,OB!A:A,0)),"") -> SHADOW STITCH POCKET MOUTH & CUT NOTCH | D39: =IFERROR(INDEX(OB!G:G,MATCH('BIHOURLY (2)'!A:A,OB!A:A,0)),"") -> SNLS | E39: =IFERROR(INDEX(OB!K:K,MATCH('BIHOURLY (2)'!A:A,OB!A:A,0)),"") -> 1 | F39: 200
B41: PKT MOUTH IRON | D41: IRON TABLE | E41: 1 | F41: 200
A43: =+A39+1 -> 17 | B43: =IFERROR(INDEX(OB!B:B,MATCH('BIHOURLY (2)'!A:A,OB!A:A,0)),"") -> TACK INNER POCKET BAG | D43: =IFERROR(INDEX(OB!G:G,MATCH('BIHOURLY (2)'!A:A,OB!A:A,0)),"") -> SNLS | E43: =IFERROR(INDEX(OB!K:K,MATCH('BIHOURLY (2)'!A:A,OB!A:A,0)),"") -> 1 | F43: 200
A45: =+A43+1 -> 18 | B45: CLOSE PKT BAG & BOTTO PRE OL | D45: =IFERROR(INDEX(OB!G:G,MATCH('BIHOURLY (2)'!A:A,OB!A:A,0)),"") -> OL4T | E45: =IFERROR(INDEX(OB!K:K,MATCH('BIHOURLY (2)'!A:A,OB!A:A,0)),"") -> 1 | F45: 200
A47: =+A45+1 -> 19 | B47: =IFERROR(INDEX(OB!B:B,MATCH('BIHOURLY (2)'!A:A,OB!A:A,0)),"") -> POCKET BAG SIDE WAIST TACK | D47: =IFERROR(INDEX(OB!G:G,MATCH('BIHOURLY (2)'!A:A,OB!A:A,0)),"") -> SNLS | E47: 1 | F47: 200
A49: =+A47+1 -> 20 | B49: BOTTOM FOLD & IRON | D49: IRON TABLE | E49: 1 | F49: 200
A51: =+A49+1 -> 21 | B51: =IFERROR(INDEX(OB!B:B,MATCH('BIHOURLY (2)'!A:A,OB!A:A,0)),"") -> JOIN FRONT RISE | D51: =IFERROR(INDEX(OB!G:G,MATCH('BIHOURLY (2)'!A:A,OB!A:A,0)),"") -> OL4T | E51: =IFERROR(INDEX(OB!K:K,MATCH('BIHOURLY (2)'!A:A,OB!A:A,0)),"") -> 0.5 | F51: =IFERROR((OB!$K$3/'BIHOURLY (2)'!E51)/5,"") -> 340
A53: =+A51+1 -> 22 | B53: =IFERROR(INDEX(OB!B:B,MATCH('BIHOURLY (2)'!A:A,OB!A:A,0)),"") -> 0 | D53: =IFERROR(INDEX(OB!G:G,MATCH('BIHOURLY (2)'!A:A,OB!A:A,0)),"") -> 0 | E53: =IFERROR(INDEX(OB!K:K,MATCH('BIHOURLY (2)'!A:A,OB!A:A,0)),"") | F53: =IFERROR((OB!$K$3/'BIHOURLY (2)'!E53)/5,"")
A55: =+A53+1 -> 23 | B55: =IFERROR(INDEX(OB!B:B,MATCH('BIHOURLY (2)'!A:A,OB!A:A,0)),"") -> 0 | D55: =IFERROR(INDEX(OB!G:G,MATCH('BIHOURLY (2)'!A:A,OB!A:A,0)),"") -> 0 | E55: =IFERROR(INDEX(OB!K:K,MATCH('BIHOURLY (2)'!A:A,OB!A:A,0)),"") | F55: =IFERROR((OB!$K$3/'BIHOURLY (2)'!E55)/5,"")
A57: =+A55+1 -> 24 | B57: =IFERROR(INDEX(OB!B:B,MATCH('BIHOURLY (2)'!A:A,OB!A:A,0)),"") -> 0 | D57: =IFERROR(INDEX(OB!G:G,MATCH('BIHOURLY (2)'!A:A,OB!A:A,0)),"") -> 0 | E57: =IFERROR(INDEX(OB!K:K,MATCH('BIHOURLY (2)'!A:A,OB!A:A,0)),"") | F57: =IFERROR((OB!$K$3/'BIHOURLY (2)'!E57)/5,"")
A59: =+A57+1 -> 25 | B59: =IFERROR(INDEX(OB!B:B,MATCH('BIHOURLY (2)'!A:A,OB!A:A,0)),"") -> 0 | D59: =IFERROR(INDEX(OB!G:G,MATCH('BIHOURLY (2)'!A:A,OB!A:A,0)),"") -> 0 | E59: =IFERROR(INDEX(OB!K:K,MATCH('BIHOURLY (2)'!A:A,OB!A:A,0)),"") | F59: =IFERROR((OB!$K$3/'BIHOURLY (2)'!E59)/5,"")
A61: =+A59+1 -> 26 | B61: =IFERROR(INDEX(OB!B:B,MATCH('BIHOURLY (2)'!A:A,OB!A:A,0)),"") -> 0 | D61: =IFERROR(INDEX(OB!G:G,MATCH('BIHOURLY (2)'!A:A,OB!A:A,0)),"") -> 0 | E61: =IFERROR(INDEX(OB!K:K,MATCH('BIHOURLY (2)'!A:A,OB!A:A,0)),"") | F61: =IFERROR((OB!$K$3/'BIHOURLY (2)'!E61)/5,"")
A63: =+A61+1 -> 27 | B63: =IFERROR(INDEX(OB!B:B,MATCH('BIHOURLY (2)'!A:A,OB!A:A,0)),"") -> 0 | D63: =IFERROR(INDEX(OB!G:G,MATCH('BIHOURLY (2)'!A:A,OB!A:A,0)),"") -> 0 | E63: =IFERROR(INDEX(OB!K:K,MATCH('BIHOURLY (2)'!A:A,OB!A:A,0)),"") | F63: =IFERROR((OB!$K$3/'BIHOURLY (2)'!E63)/5,"")
A65: =+A63+1 -> 28 | B65: =IFERROR(INDEX(OB!B:B,MATCH('BIHOURLY (2)'!A:A,OB!A:A,0)),"") -> 0 | D65: =IFERROR(INDEX(OB!G:G,MATCH('BIHOURLY (2)'!A:A,OB!A:A,0)),"") -> 0 | E65: =IFERROR(INDEX(OB!K:K,MATCH('BIHOURLY (2)'!A:A,OB!A:A,0)),"") | F65: =IFERROR((OB!$K$3/'BIHOURLY (2)'!E65)/5,"")
A67: =+A65+1 -> 29 | B67: =IFERROR(INDEX(OB!B:B,MATCH('BIHOURLY (2)'!A:A,OB!A:A,0)),"") -> 0 | D67: =IFERROR(INDEX(OB!G:G,MATCH('BIHOURLY (2)'!A:A,OB!A:A,0)),"") -> 0 | E67: =IFERROR(INDEX(OB!K:K,MATCH('BIHOURLY (2)'!A:A,OB!A:A,0)),"") | F67: =IFERROR((OB!$K$3/'BIHOURLY (2)'!E67)/5,"")
A69: =+A67+1 -> 30 | B69: =IFERROR(INDEX(OB!B:B,MATCH('BIHOURLY (2)'!A:A,OB!A:A,0)),"") -> 0 | D69: =IFERROR(INDEX(OB!G:G,MATCH('BIHOURLY (2)'!A:A,OB!A:A,0)),"") -> 0 | E69: =IFERROR(INDEX(OB!K:K,MATCH('BIHOURLY (2)'!A:A,OB!A:A,0)),"") | F69: =IFERROR((OB!$K$3/'BIHOURLY (2)'!E69)/5,"")
B71: BACK RISE & FRANT RISE OL | D71: OL5T | E71: 1 | F71: 200
A73: =+A69+1 -> 31 | B73: =IFERROR(INDEX(OB!B:B,MATCH('BIHOURLY (2)'!A:A,OB!A:A,0)),"") -> TACK FRONT & BACK AT INSEAM FOR LEG ZIPPER | D73: =IFERROR(INDEX(OB!G:G,MATCH('BIHOURLY (2)'!A:A,OB!A:A,0)),"") -> SNLS | E73: 2 | F73: 100
F74: 100
A76: =+A73+1 -> 32 | B76: =IFERROR(INDEX(OB!B:B,MATCH('BIHOURLY (2)'!A:A,OB!A:A,0)),"") -> INSEAM | D76: OL5T | E76: =IFERROR(INDEX(OB!K:K,MATCH('BIHOURLY (2)'!A:A,OB!A:A,0)),"") -> 1 | F76: 200
A78: =+A76+1 -> 33 | B78: =IFERROR(INDEX(OB!B:B,MATCH('BIHOURLY (2)'!A:A,OB!A:A,0)),"") -> TACK LEG ZIPPER | D78: =IFERROR(INDEX(OB!G:G,MATCH('BIHOURLY (2)'!A:A,OB!A:A,0)),"") -> SNLS | E78: 1 | F78: =IFERROR((OB!$K$3/'BIHOURLY (2)'!E78)/5,"") -> 170
A80: =+A78+1 -> 34 | B80: =IFERROR(INDEX(OB!B:B,MATCH('BIHOURLY (2)'!A:A,OB!A:A,0)),"") -> ATTACH LEG ZIPPER | D80: =IFERROR(INDEX(OB!G:G,MATCH('BIHOURLY (2)'!A:A,OB!A:A,0)),"") -> SNLS | E80: 3 | F80: 85
F81: 85
F82: 85
A84: =+A80+1 -> 35 | B84: =IFERROR(INDEX(OB!B:B,MATCH('BIHOURLY (2)'!A:A,OB!A:A,0)),"") -> TACK FOR SIDE SEAM | D84: =IFERROR(INDEX(OB!G:G,MATCH('BIHOURLY (2)'!A:A,OB!A:A,0)),"") -> SNLS | E84: 2 | F84: 100
F85: 100
A87: =+A84+1 -> 36 | B87: =IFERROR(INDEX(OB!B:B,MATCH('BIHOURLY (2)'!A:A,OB!A:A,0)),"") -> SIDE SEAM | D87: =IFERROR(INDEX(OB!G:G,MATCH('BIHOURLY (2)'!A:A,OB!A:A,0)),"") -> OL4T | E87: 2 | F87: 100
F88: 100
A90: =+A87+1 -> 37 | B90: PKT BKT | D90: BKT | E90: =IFERROR(INDEX(OB!K:K,MATCH('BIHOURLY (2)'!A:A,OB!A:A,0)),"") -> 1 | F90: 200
A92: =+A90+1 -> 38 | B92: =IFERROR(INDEX(OB!B:B,MATCH('BIHOURLY (2)'!A:A,OB!A:A,0)),"") -> MARK FOR HIGH LOW | D92: =IFERROR(INDEX(OB!G:G,MATCH('BIHOURLY (2)'!A:A,OB!A:A,0)),"") -> TABLE | E92: =IFERROR(INDEX(OB!K:K,MATCH('BIHOURLY (2)'!A:A,OB!A:A,0)),"") -> 0.5 | F92: =IFERROR((OB!$K$3/'BIHOURLY (2)'!E92)/5,"") -> 340
A94: =+A92+1 -> 39 | B94: =IFERROR(INDEX(OB!B:B,MATCH('BIHOURLY (2)'!A:A,OB!A:A,0)),"") -> MARK & TACK WB FOR BUTTON HOLE | D94: =IFERROR(INDEX(OB!G:G,MATCH('BIHOURLY (2)'!A:A,OB!A:A,0)),"") -> SNLS | E94: 1 | F94: 200
A96: =+A94+1 -> 40 | B96: =IFERROR(INDEX(OB!B:B,MATCH('BIHOURLY (2)'!A:A,OB!A:A,0)),"") -> CREASE WB JOININGS TO SPLIT | D96: =IFERROR(INDEX(OB!G:G,MATCH('BIHOURLY (2)'!A:A,OB!A:A,0)),"") -> IRON TABLE | E96: =IFERROR(INDEX(OB!K:K,MATCH('BIHOURLY (2)'!A:A,OB!A:A,0)),"") -> 0.75 | F96: =IFERROR((OB!$K$3/'BIHOURLY (2)'!E96)/5,"") -> 226.66667
A98: =+A96+1 -> 41 | B98: =IFERROR(INDEX(OB!B:B,MATCH('BIHOURLY (2)'!A:A,OB!A:A,0)),"") -> TOP STITCH BUTTON HOLE SIDE | D98: =IFERROR(INDEX(OB!G:G,MATCH('BIHOURLY (2)'!A:A,OB!A:A,0)),"") -> SNLS | E98: 1 | F98: 200
A100: =+A98+1 -> 42 | B100: =IFERROR(INDEX(OB!B:B,MATCH('BIHOURLY (2)'!A:A,OB!A:A,0)),"") -> ATTACH WB TO BODY | D100: =IFERROR(INDEX(OB!G:G,MATCH('BIHOURLY (2)'!A:A,OB!A:A,0)),"") -> OL4T | E100: 2 | F100: 100
F101: 100
A103: =+A100+1 -> 43 | B103: =IFERROR(INDEX(OB!B:B,MATCH('BIHOURLY (2)'!A:A,OB!A:A,0)),"") -> MAKE ELASTIC READY | D103: =IFERROR(INDEX(OB!G:G,MATCH('BIHOURLY (2)'!A:A,OB!A:A,0)),"") -> PREP | E103: =IFERROR(INDEX(OB!K:K,MATCH('BIHOURLY (2)'!A:A,OB!A:A,0)),"") -> 0.5 | F103: =IFERROR((OB!$K$3/'BIHOURLY (2)'!E103)/5,"") -> 340
A105: =+A103+1 -> 44 | B105: =IFERROR(INDEX(OB!B:B,MATCH('BIHOURLY (2)'!A:A,OB!A:A,0)),"") -> ATTACH ELASTIC TO WB | D105: =IFERROR(INDEX(OB!G:G,MATCH('BIHOURLY (2)'!A:A,OB!A:A,0)),"") -> FL3T-CB | E105: =IFERROR(INDEX(OB!K:K,MATCH('BIHOURLY (2)'!A:A,OB!A:A,0)),"") -> 1 | F105: 200
A107: =+A105+1 -> 45 | B107: =IFERROR(INDEX(OB!B:B,MATCH('BIHOURLY (2)'!A:A,OB!A:A,0)),"") -> ATTACH LABEL*2 | D107: =IFERROR(INDEX(OB!G:G,MATCH('BIHOURLY (2)'!A:A,OB!A:A,0)),"") -> SNLS | E107: 1 | F107: 200
A109: =+A107+1 -> 46 | B109: =IFERROR(INDEX(OB!B:B,MATCH('BIHOURLY (2)'!A:A,OB!A:A,0)),"") -> VERTICAL TACK WB | D109: =IFERROR(INDEX(OB!G:G,MATCH('BIHOURLY (2)'!A:A,OB!A:A,0)),"") -> SNLS | E109: 1 | F109: 200
A111: =+A109+1 -> 47 | B111: =IFERROR(INDEX(OB!B:B,MATCH('BIHOURLY (2)'!A:A,OB!A:A,0)),"") -> CLOSE WAISTBAND | D111: =IFERROR(INDEX(OB!G:G,MATCH('BIHOURLY (2)'!A:A,OB!A:A,0)),"") -> KANSAI | E111: =IFERROR(INDEX(OB!K:K,MATCH('BIHOURLY (2)'!A:A,OB!A:A,0)),"") -> 1 | F111: 200
A113: =+A111+1 -> 48 | B113: =IFERROR(INDEX(OB!B:B,MATCH('BIHOURLY (2)'!A:A,OB!A:A,0)),"") -> REMOVE VERTICAL TACK | D113: =IFERROR(INDEX(OB!G:G,MATCH('BIHOURLY (2)'!A:A,OB!A:A,0)),"") -> TABLE | E113: =IFERROR(INDEX(OB!K:K,MATCH('BIHOURLY (2)'!A:A,OB!A:A,0)),"") -> 0.5 | F113: =IFERROR((OB!$K$3/'BIHOURLY (2)'!E113)/5,"") -> 340
A115: =+A113+1 -> 49 | B115: =IFERROR(INDEX(OB!B:B,MATCH('BIHOURLY (2)'!A:A,OB!A:A,0)),"") -> CREASE BOTTOM FOR HEM | D115: =IFERROR(INDEX(OB!G:G,MATCH('BIHOURLY (2)'!A:A,OB!A:A,0)),"") -> IRON TABLE | E115: =IFERROR(INDEX(OB!K:K,MATCH('BIHOURLY (2)'!A:A,OB!A:A,0)),"") -> 0.75 | F115: =IFERROR((OB!$K$3/'BIHOURLY (2)'!E115)/5,"") -> 226.66667
A117: =+A115+1 -> 50 | B117: =IFERROR(INDEX(OB!B:B,MATCH('BIHOURLY (2)'!A:A,OB!A:A,0)),"") -> FOLD & TACK BOTTOM WITH ZIPPER FOR HEM | D117: =IFERROR(INDEX(OB!G:G,MATCH('BIHOURLY (2)'!A:A,OB!A:A,0)),"") -> SNLS | E117: =IFERROR(INDEX(OB!K:K,MATCH('BIHOURLY (2)'!A:A,OB!A:A,0)),"") -> 1 | F117: 200
A119: =+A117+1 -> 51 | B119: =IFERROR(INDEX(OB!B:B,MATCH('BIHOURLY (2)'!A:A,OB!A:A,0)),"") -> BOTTOM HEM | D119: =IFERROR(INDEX(OB!G:G,MATCH('BIHOURLY (2)'!A:A,OB!A:A,0)),"") -> SNLS | E119: =IFERROR(INDEX(OB!K:K,MATCH('BIHOURLY (2)'!A:A,OB!A:A,0)),"") -> 1 | F119: 200
A122: =+A119+1 -> 52 | B122: =IFERROR(INDEX(OB!B:B,MATCH('BIHOURLY (2)'!A:A,OB!A:A,0)),"") -> BARTACK FRONT WB*4 | D122: =IFERROR(INDEX(OB!G:G,MATCH('BIHOURLY (2)'!A:A,OB!A:A,0)),"") -> BRTK | E122: =IFERROR(INDEX(OB!K:K,MATCH('BIHOURLY (2)'!A:A,OB!A:A,0)),"") -> 0.5 | F122: =IFERROR((OB!$K$3/'BIHOURLY (2)'!E122)/5,"") -> 340
A124: =+A122+1 -> 53 | B124: =IFERROR(INDEX(OB!B:B,MATCH('BIHOURLY (2)'!A:A,OB!A:A,0)),"") -> INSERT DRAWCORD | D124: =IFERROR(INDEX(OB!G:G,MATCH('BIHOURLY (2)'!A:A,OB!A:A,0)),"") -> TABLE | E124: 1 | F124: 200
A126: =+A124+1 -> 54 | B126: =IFERROR(INDEX(OB!B:B,MATCH('BIHOURLY (2)'!A:A,OB!A:A,0)),"") -> BARTACK WB*4, CROTCH*1 & ZIPPER*2 | D126: =IFERROR(INDEX(OB!G:G,MATCH('BIHOURLY (2)'!A:A,OB!A:A,0)),"") -> BRTK | E126: 1 | F126: 200
A128: =+A126+1 -> 55 | B128: =IFERROR(INDEX(OB!B:B,MATCH('BIHOURLY (2)'!A:A,OB!A:A,0)),"") -> TRIM AND INLINE CHECK | D128: =IFERROR(INDEX(OB!G:G,MATCH('BIHOURLY (2)'!A:A,OB!A:A,0)),"") -> TABLE | E128: =IFERROR(INDEX(OB!K:K,MATCH('BIHOURLY (2)'!A:A,OB!A:A,0)),"") -> 1 | F128: =IFERROR((OB!$K$3/'BIHOURLY (2)'!E128)/5,"") -> 170
A130: =+A128+1 -> 56 | B130: =IFERROR(INDEX(OB!B:B,MATCH('BIHOURLY (2)'!A:A,OB!A:A,0)),"") -> BUFFER | D130: =IFERROR(INDEX(OB!G:G,MATCH('BIHOURLY (2)'!A:A,OB!A:A,0)),"") -> 0 | E130: =IFERROR(INDEX(OB!K:K,MATCH('BIHOURLY (2)'!A:A,OB!A:A,0)),"") -> 11.25 | F130: =IFERROR((OB!$K$3/'BIHOURLY (2)'!E130)/5,"") -> 15.111111
A132: =+A130+1 -> 57 | B132: =IFERROR(INDEX(OB!B:B,MATCH('BIHOURLY (2)'!A:A,OB!A:A,0)),"") -> 0 | D132: =IFERROR(INDEX(OB!G:G,MATCH('BIHOURLY (2)'!A:A,OB!A:A,0)),"") -> 0 | E132: =IFERROR(INDEX(OB!K:K,MATCH('BIHOURLY (2)'!A:A,OB!A:A,0)),"") | F132: =IFERROR((OB!$K$3/'BIHOURLY (2)'!E132)/5,"")
A134: =+A132+1 -> 58 | B134: =IFERROR(INDEX(OB!B:B,MATCH('BIHOURLY (2)'!A:A,OB!A:A,0)),"") -> 0 | D134: =IFERROR(INDEX(OB!G:G,MATCH('BIHOURLY (2)'!A:A,OB!A:A,0)),"") -> 0 | E134: =IFERROR(INDEX(OB!K:K,MATCH('BIHOURLY (2)'!A:A,OB!A:A,0)),"") | F134: =IFERROR((OB!$K$3/'BIHOURLY (2)'!E134)/5,"")
B136: THRAED TRIMING | D136: TABLE | E136: 2 | F136: 100
F137: 100
A139: =+A134+1 -> 59 | B139: =IFERROR(INDEX(OB!B:B,MATCH('BIHOURLY (2)'!A:A,OB!A:A,0)),"") -> QUALITY CHECKER | D139: =IFERROR(INDEX(OB!G:G,MATCH('BIHOURLY (2)'!A:A,OB!A:A,0)),"") -> TABLE | E139: =IFERROR(INDEX(OB!K:K,MATCH('BIHOURLY (2)'!A:A,OB!A:A,0)),"") | F139: 200
A142: =+A139+1 -> 60 | B142: =IFERROR(INDEX(OB!B:B,MATCH('BIHOURLY (2)'!A:A,OB!A:A,0)),"") -> IRONING GARMENT + W/BAND | D142: =IFERROR(INDEX(OB!G:G,MATCH('BIHOURLY (2)'!A:A,OB!A:A,0)),"") -> IRON TABLE | E142: =IFERROR(INDEX(OB!K:K,MATCH('BIHOURLY (2)'!A:A,OB!A:A,0)),"") -> 1 | F142: 200
A145: =+A142+1 -> 61 | B145: =IFERROR(INDEX(OB!B:B,MATCH('BIHOURLY (2)'!A:A,OB!A:A,0)),"") -> SPEC & PRESENTATION QC | D145: =IFERROR(INDEX(OB!G:G,MATCH('BIHOURLY (2)'!A:A,OB!A:A,0)),"") -> TABLE | E145: =IFERROR(INDEX(OB!K:K,MATCH('BIHOURLY (2)'!A:A,OB!A:A,0)),"") | F145: 200
A147: =+A145+1 -> 62 | B147: =IFERROR(INDEX(OB!B:B,MATCH('BIHOURLY (2)'!A:A,OB!A:A,0)),"") -> MATCHBOOK | D147: =IFERROR(INDEX(OB!G:G,MATCH('BIHOURLY (2)'!A:A,OB!A:A,0)),"") -> BA | E147: =IFERROR(INDEX(OB!K:K,MATCH('BIHOURLY (2)'!A:A,OB!A:A,0)),"") -> 1 | F147: 200
A149: =+A147+1 -> 63 | B149: =IFERROR(INDEX(OB!B:B,MATCH('BIHOURLY (2)'!A:A,OB!A:A,0)),"") -> HANGTAG | D149: =IFERROR(INDEX(OB!G:G,MATCH('BIHOURLY (2)'!A:A,OB!A:A,0)),"") -> TAG GUN | E149: 1 | F149: 200
A151: =+A149+1 -> 64 | B151: =IFERROR(INDEX(OB!B:B,MATCH('BIHOURLY (2)'!A:A,OB!A:A,0)),"") -> FOLDING + POLYBAG | D151: =IFERROR(INDEX(OB!G:G,MATCH('BIHOURLY (2)'!A:A,OB!A:A,0)),"") -> TABLE | E151: =IFERROR(INDEX(OB!K:K,MATCH('BIHOURLY (2)'!A:A,OB!A:A,0)),"") -> 1 | F151: 200
A153: =+A151+1 -> 65 | B153: =IFERROR(INDEX(OB!B:B,MATCH('BIHOURLY (2)'!A:A,OB!A:A,0)),"") -> SKU + CTN | D153: =IFERROR(INDEX(OB!G:G,MATCH('BIHOURLY (2)'!A:A,OB!A:A,0)),"") -> TABLE | E153: =IFERROR(INDEX(OB!K:K,MATCH('BIHOURLY (2)'!A:A,OB!A:A,0)),"") -> 1 | F153: 20
A155: =+A153+1 -> 66 | B155: =IFERROR(INDEX(OB!B:B,MATCH('BIHOURLY (2)'!A:A,OB!A:A,0)),"") | D155: =IFERROR(INDEX(OB!G:G,MATCH('BIHOURLY (2)'!A:A,OB!A:A,0)),"") | E155: =IFERROR(INDEX(OB!K:K,MATCH('BIHOURLY (2)'!A:A,OB!A:A,0)),"") | F155: =IFERROR((OB!$K$3/'BIHOURLY (2)'!E155)/5,"")
A157: =+A155+1 -> 67 | B157: =IFERROR(INDEX(OB!B:B,MATCH('BIHOURLY (2)'!A:A,OB!A:A,0)),"") | D157: =IFERROR(INDEX(OB!G:G,MATCH('BIHOURLY (2)'!A:A,OB!A:A,0)),"") | E157: =IFERROR(INDEX(OB!K:K,MATCH('BIHOURLY (2)'!A:A,OB!A:A,0)),"") | F157: =IFERROR((OB!$K$3/'BIHOURLY (2)'!E157)/5,"")
A159: =+A157+1 -> 68 | B159: =IFERROR(INDEX(OB!B:B,MATCH('BIHOURLY (2)'!A:A,OB!A:A,0)),"") | D159: =IFERROR(INDEX(OB!G:G,MATCH('BIHOURLY (2)'!A:A,OB!A:A,0)),"") | E159: =IFERROR(INDEX(OB!K:K,MATCH('BIHOURLY (2)'!A:A,OB!A:A,0)),"") | F159: =IFERROR((OB!$K$3/'BIHOURLY (2)'!E159)/5,"")
A161: =+A159+1 -> 69 | B161: =IFERROR(INDEX(OB!B:B,MATCH('BIHOURLY (2)'!A:A,OB!A:A,0)),"") | D161: =IFERROR(INDEX(OB!G:G,MATCH('BIHOURLY (2)'!A:A,OB!A:A,0)),"") | E161: =IFERROR(INDEX(OB!K:K,MATCH('BIHOURLY (2)'!A:A,OB!A:A,0)),"") | F161: =IFERROR((OB!$K$3/'BIHOURLY (2)'!E161)/5,"")
A163: =+A161+1 -> 70 | B163: =IFERROR(INDEX(OB!B:B,MATCH('BIHOURLY (2)'!A:A,OB!A:A,0)),"") | D163: =IFERROR(INDEX(OB!G:G,MATCH('BIHOURLY (2)'!A:A,OB!A:A,0)),"") | E163: =IFERROR(INDEX(OB!K:K,MATCH('BIHOURLY (2)'!A:A,OB!A:A,0)),"") | F163: =IFERROR((OB!$K$3/'BIHOURLY (2)'!E163)/5,"")
A165: =+A163+1 -> 71 | B165: =IFERROR(INDEX(OB!B:B,MATCH('BIHOURLY (2)'!A:A,OB!A:A,0)),"") | D165: =IFERROR(INDEX(OB!G:G,MATCH('BIHOURLY (2)'!A:A,OB!A:A,0)),"") | E165: =IFERROR(INDEX(OB!K:K,MATCH('BIHOURLY (2)'!A:A,OB!A:A,0)),"") | F165: =IFERROR((OB!$K$3/'BIHOURLY (2)'!E165)/5,"")
A167: =+A165+1 -> 72 | B167: =IFERROR(INDEX(OB!B:B,MATCH('BIHOURLY (2)'!A:A,OB!A:A,0)),"") | D167: =IFERROR(INDEX(OB!G:G,MATCH('BIHOURLY (2)'!A:A,OB!A:A,0)),"") | E167: =IFERROR(INDEX(OB!K:K,MATCH('BIHOURLY (2)'!A:A,OB!A:A,0)),"") | F167: =IFERROR((OB!$K$3/'BIHOURLY (2)'!E167)/5,"")
A169: =+A167+1 -> 73 | B169: =IFERROR(INDEX(OB!B:B,MATCH('BIHOURLY (2)'!A:A,OB!A:A,0)),"") | D169: =IFERROR(INDEX(OB!G:G,MATCH('BIHOURLY (2)'!A:A,OB!A:A,0)),"") | E169: =IFERROR(INDEX(OB!K:K,MATCH('BIHOURLY (2)'!A:A,OB!A:A,0)),"") | F169: =IFERROR((OB!$K$3/'BIHOURLY (2)'!E169)/5,"")
A171: =+A169+1 -> 74 | B171: =IFERROR(INDEX(OB!B:B,MATCH('BIHOURLY (2)'!A:A,OB!A:A,0)),"") | D171: =IFERROR(INDEX(OB!G:G,MATCH('BIHOURLY (2)'!A:A,OB!A:A,0)),"") | E171: =IFERROR(INDEX(OB!K:K,MATCH('BIHOURLY (2)'!A:A,OB!A:A,0)),"") | F171: =IFERROR((OB!$K$3/'BIHOURLY (2)'!E171)/5,"")
A173: =+A171+1 -> 75 | B173: =IFERROR(INDEX(OB!B:B,MATCH('BIHOURLY (2)'!A:A,OB!A:A,0)),"") | D173: =IFERROR(INDEX(OB!G:G,MATCH('BIHOURLY (2)'!A:A,OB!A:A,0)),"") | E173: =IFERROR(INDEX(OB!K:K,MATCH('BIHOURLY (2)'!A:A,OB!A:A,0)),"") | F173: =IFERROR((OB!$K$3/'BIHOURLY (2)'!E173)/5,"")
A175: =+A173+1 -> 76 | B175: =IFERROR(INDEX(OB!B:B,MATCH('BIHOURLY (2)'!A:A,OB!A:A,0)),"") | D175: =IFERROR(INDEX(OB!G:G,MATCH('BIHOURLY (2)'!A:A,OB!A:A,0)),"") | E175: =IFERROR(INDEX(OB!K:K,MATCH('BIHOURLY (2)'!A:A,OB!A:A,0)),"") | F175: =IFERROR((OB!$K$3/'BIHOURLY (2)'!E175)/5,"")
A177: =+A175+1 -> 77 | B177: =IFERROR(INDEX(OB!B:B,MATCH('BIHOURLY (2)'!A:A,OB!A:A,0)),"") | D177: =IFERROR(INDEX(OB!G:G,MATCH('BIHOURLY (2)'!A:A,OB!A:A,0)),"") | E177: =IFERROR(INDEX(OB!K:K,MATCH('BIHOURLY (2)'!A:A,OB!A:A,0)),"") | F177: =IFERROR((OB!$K$3/'BIHOURLY (2)'!E177)/5,"")
... A203: =+A201+1 -> 90 | B203: =IFERROR(INDEX(OB!B:B,MATCH('BIHOURLY (2)'!A:A,OB!A:A,0)),"") | D203: =IFERROR(INDEX(OB!G:G,MATCH('BIHOURLY (2)'!A:A,OB!A:A,0)),"") | E203: =IFERROR(INDEX(OB!K:K,MATCH('BIHOURLY (2)'!A:A,OB!A:A,0)),"") | F203: =IFERROR((OB!$K$3/'BIHOURLY (2)'!E203)/5,"")

Sheet MACHINE REQURMENT
A1: MACHINE REQUIREMENT FOR STYLE CHANGE FROM | H1: TO | I1: =+OB!C2 -> S2554MESS651WV | J1: Line No | M1: INPUT DATE | N1: 45698
A2: BACK SECTION | E2: FRONT SECTION | I2: WAISTBAND & ASSEMBLY SECTION | M2: SUMMARY
A3: M/C | B3: =+G1 -> 0 | C3: =+I1 -> S2554MESS651WV | D3: Req | E3: M/C | F3: =+G1 -> 0 | G3: =+I1 -> S2554MESS651WV | H3: Req | I3: M/C | J3: =+G1 -> 0 | K3: =+I1 -> S2554MESS651WV | L3: Req | M3: MACHINE TYPE | N3: Req to start style | O3: Requirement | P3: Remarks
A4: SNLS | C4: =+IFERROR(SUMIF(OB!$G$10:$G$25,'MACHINE REQURMENT'!A4,OB!$J$10:$J$25),"0") -> 0 | D4: =C4-B4 -> 0 | E4: SNLS | G4: =+IFERROR(SUMIF(OB!$G$27:$G$44,'MACHINE REQURMENT'!E4,OB!$J$27:$J$44),"0") -> 5 | H4: =G4-F4 -> 5 | I4: SNLS | K4: =+IFERROR(SUMIF(OB!$G$46:$G$83,'MACHINE REQURMENT'!I4,OB!$J$46:$J$83),"0") -> 16 | L4: =K4-J4 -> 16 | M4: SNLS | N4: =D4+H4+L4 -> 21 | O4: =D4+H4+L4 -> 21 | R4: =C4+G4+K4 -> 21
A5: SNEC | C5: =+IFERROR(SUMIF(OB!$G$10:$G$25,'MACHINE REQURMENT'!A5,OB!$J$10:$J$25),"0") -> 0 | D5: =C5-B5 -> 0 | E5: SNEC | G5: =+IFERROR(SUMIF(OB!$G$27:$G$44,'MACHINE REQURMENT'!E5,OB!$J$27:$J$44),"0") -> 0 | H5: =G5-F5 -> 0 | I5: SNEC | K5: =+IFERROR(SUMIF(OB!$G$46:$G$83,'MACHINE REQURMENT'!I5,OB!$J$46:$J$83),"0") -> 0 | L5: =K5-J5 -> 0 | M5: SNEC | N5: =D5+H5+L5 -> 0 | O5: =D5+H5+L5 -> 0 | R5: =C5+G5+K5 -> 0
A6: APW | C6: =+IFERROR(SUMIF(OB!$G$10:$G$25,'MACHINE REQURMENT'!A6,OB!$J$10:$J$25),"0") -> 0 | D6: =C6-B6 -> 0 | E6: APW | G6: =+IFERROR(SUMIF(OB!$G$27:$G$44,'MACHINE REQURMENT'!E6,OB!$J$27:$J$44),"0") -> 0 | H6: =G6-F6 -> 0 | I6: APW | K6: =+IFERROR(SUMIF(OB!$G$46:$G$83,'MACHINE REQURMENT'!I6,OB!$J$46:$J$83),"0") -> 0 | L6: =K6-J6 -> 0 | M6: APW | N6: =D6+H6+L6 -> 0 | O6: =D6+H6+L6 -> 0 | R6: =C6+G6+K6 -> 0
A7: OL3T | C7: =+IFERROR(SUMIF(OB!$G$10:$G$25,'MACHINE REQURMENT'!A7,OB!$J$10:$J$25),"0") -> 0 | D7: =C7-B7 -> 0 | E7: OL3T | G7: =+IFERROR(SUMIF(OB!$G$27:$G$44,'MACHINE REQURMENT'!E7,OB!$J$27:$J$44),"0") -> 0 | H7: =G7-F7 -> 0 | I7: OL3T | K7: =+IFERROR(SUMIF(OB!$G$46:$G$83,'MACHINE REQURMENT'!I7,OB!$J$46:$J$83),"0") -> 0 | L7: =K7-J7 -> 0 | M7: OL3T | N7: =D7+H7+L7 -> 0 | O7: =D7+H7+L7 -> 0 | R7: =C7+G7+K7 -> 0
A8: OL4T | C8: =+IFERROR(SUMIF(OB!$G$10:$G$25,'MACHINE REQURMENT'!A8,OB!$J$10:$J$25),"0") -> 2 | D8: =C8-B8 -> 2 | E8: OL4T | G8: =+IFERROR(SUMIF(OB!$G$27:$G$44,'MACHINE REQURMENT'!E8,OB!$J$27:$J$44),"0") -> 2 | H8: =G8-F8 -> 2 | I8: OL4T | K8: =+IFERROR(SUMIF(OB!$G$46:$G$83,'MACHINE REQURMENT'!I8,OB!$J$46:$J$83),"0") -> 4 | L8: =K8-J8 -> 4 | M8: OL4T | N8: =D8+H8+L8 -> 8 | O8: =D8+H8+L8 -> 8 | R8: =C8+G8+K8 -> 8
A9: OL5T | C9: =+IFERROR(SUMIF(OB!$G$10:$G$25,'MACHINE REQURMENT'!A9,OB!$J$10:$J$25),"0") -> 0 | D9: =C9-B9 -> 0 | E9: OL5T | G9: =+IFERROR(SUMIF(OB!$G$27:$G$44,'MACHINE REQURMENT'!E9,OB!$J$27:$J$44),"0") -> 0 | H9: =G9-F9 -> 0 | I9: OL5T | K9: =+IFERROR(SUMIF(OB!$G$46:$G$83,'MACHINE REQURMENT'!I9,OB!$J$46:$J$83),"0") -> 0 | L9: =K9-J9 -> 0 | M9: OL5T | N9: =D9+H9+L9 -> 0 | O9: =D9+H9+L9 -> 0 | R9: =C9+G9+K9 -> 0
A10: DNLS | C10: =+IFERROR(SUMIF(OB!$G$10:$G$25,'MACHINE REQURMENT'!A10,OB!$J$10:$J$25),"0") -> 0 | D10: =C10-B10 -> 0 | E10: DNLS | G10: =+IFERROR(SUMIF(OB!$G$27:$G$44,'MACHINE REQURMENT'!E10,OB!$J$27:$J$44),"0") -> 0 | H10: =G10-F10 -> 0 | I10: DNLS | K10: =+IFERROR(SUMIF(OB!$G$46:$G$83,'MACHINE REQURMENT'!I10,OB!$J$46:$J$83),"0") -> 0 | L10: =K10-J10 -> 0 | M10: DNLS | N10: =D10+H10+L10 -> 0 | O10: =D10+H10+L10 -> 0 | R10: =C10+G10+K10 -> 0
A11: SNCS | C11: =+IFERROR(SUMIF(OB!$G$10:$G$25,'MACHINE REQURMENT'!A11,OB!$J$10:$J$25),"0") -> 0 | D11: =C11-B11 -> 0 | E11: SNCS | G11: =+IFERROR(SUMIF(OB!$G$27:$G$44,'MACHINE REQURMENT'!E11,OB!$J$27:$J$44),"0") -> 0 | H11: =G11-F11 -> 0 | I11: SNCS | K11: =+IFERROR(SUMIF(OB!$G$46:$G$83,'MACHINE REQURMENT'!I11,OB!$J$46:$J$83),"0") -> 0 | L11: =K11-J11 -> 0 | M11: SNCS | N11: =D11+H11+L11 -> 0 | O11: =D11+H11+L11 -> 0 | R11: =C11+G11+K11 -> 0
A12: DNCS | C12: =+IFERROR(SUMIF(OB!$G$10:$G$25,'MACHINE REQURMENT'!A12,OB!$J$10:$J$25),"0") -> 0 | D12: =C12-B12 -> 0 | E12: DNCS | G12: =+IFERROR(SUMIF(OB!$G$27:$G$44,'MACHINE REQURMENT'!E12,OB!$J$27:$J$44),"0") -> 0 | H12: =G12-F12 -> 0 | I12: DNCS | K12: =+IFERROR(SUMIF(OB!$G$46:$G$83,'MACHINE REQURMENT'!I12,OB!$J$46:$J$83),"0") -> 0 | L12: =K12-J12 -> 0 | M12: DNCS | N12: =D12+H12+L12 -> 0 | O12: =D12+H12+L12 -> 0 | R12: =C12+G12+K12 -> 0
A13: KANSAI | C13: =+IFERROR(SUMIF(OB!$G$10:$G$25,'MACHINE REQURMENT'!A13,OB!$J$10:$J$25),"0") -> 2 | D13: =C13-B13 -> 2 | E13: KANSAI | G13: =+IFERROR(SUMIF(OB!$G$27:$G$44,'MACHINE REQURMENT'!E13,OB!$J$27:$J$44),"0") -> 0 | H13: =G13-F13 -> 0 | I13: KANSAI | K13: =+IFERROR(SUMIF(OB!$G$46:$G$83,'MACHINE REQURMENT'!I13,OB!$J$46:$J$83),"0") -> 1 | L13: =K13-J13 -> 1 | M13: KANSAI | N13: =D13+H13+L13 -> 3 | O13: =D13+H13+L13 -> 3 | R13: =C13+G13+K13 -> 3
A14: BRTK | C14: =+IFERROR(SUMIF(OB!$G$10:$G$25,'MACHINE REQURMENT'!A14,OB!$J$10:$J$25),"0") -> 0 | D14: =C14-B14 -> 0 | E14: BRTK | G14: =+IFERROR(SUMIF(OB!$G$27:$G$44,'MACHINE REQURMENT'!E14,OB!$J$27:$J$44),"0") -> 1 | H14: =G14-F14 -> 1 | I14: BRTK | K14: =+IFERROR(SUMIF(OB!$G$46:$G$83,'MACHINE REQURMENT'!I14,OB!$J$46:$J$83),"0") -> 2 | L14: =K14-J14 -> 2 | M14: BRTK | N14: =D14+H14+L14 -> 3 | O14: =D14+H14+L14 -> 3 | R14: =C14+G14+K14 -> 3
A15: KEYHOLE | C15: =+IFERROR(SUMIF(OB!$G$10:$G$25,'MACHINE REQURMENT'!A15,OB!$J$10:$J$25),"0") -> 0 | D15: =C15-B15 -> 0 | E15: KEYHOLE | G15: =+IFERROR(SUMIF(OB!$G$27:$G$44,'MACHINE REQURMENT'!E15,OB!$J$27:$J$44),"0") -> 0 | H15: =G15-F15 -> 0 | I15: KEYHOLE | K15: =+IFERROR(SUMIF(OB!$G$46:$G$83,'MACHINE REQURMENT'!I15,OB!$J$46:$J$83),"0") -> 0 | L15: =K15-J15 -> 0 | M15: KEYHOLE | N15: =D15+H15+L15 -> 0 | O15: =D15+H15+L15 -> 0 | R15: =C15+G15+K15 -> 0
... A21: BLIND HEM | C21: =+IFERROR(SUMIF(OB!$G$10:$G$25,'MACHINE REQURMENT'!A21,OB!$J$10:$J$25),"0") -> 0 | D21: =C21-B21 -> 0 | E21: BLIND HEM | G21: =+IFERROR(SUMIF(OB!$G$27:$G$44,'MACHINE REQURMENT'!E21,OB!$J$27:$J$44),"0") -> 0 | H21: =G21-F21 -> 0 | I21: BLIND HEM | K21: =+IFERROR(SUMIF(OB!$G$46:$G$83,'MACHINE REQURMENT'!I21,OB!$J$46:$J$83),"0") -> 0 | L21: =K21-J21 -> 0 | M21: BLIND HEM | N21: =D21+H21+L21 -> 0 | O21: =D21+H21+L21 -> 0 | R21: =C21+G21+K21 -> 0
A22: FL2T-FB | C22: =+IFERROR(SUMIF(OB!$G$10:$G$25,'MACHINE REQURMENT'!A22,OB!$J$10:$J$25),"0") -> 0 | D22: =C22-B22 -> 0 | E22: FL2T-FB | G22: =+IFERROR(SUMIF(OB!$G$27:$G$44,'MACHINE REQURMENT'!E22,OB!$J$27:$J$44),"0") -> 0 | H22: =G22-F22 -> 0 | I22: FL2T-FB | K22: =+IFERROR(SUMIF(OB!$G$46:$G$83,'MACHINE REQURMENT'!I22,OB!$J$46:$J$83),"0") -> 0 | L22: =K22-J22 -> 0 | M22: FL2T-FB | N22: =D22+H22+L22 -> 0 | O22: 0 | R22: =C22+G22+K22 -> 0
A23: FL3T-FB | C23: =+IFERROR(SUMIF(OB!$G$10:$G$25,'MACHINE REQURMENT'!A23,OB!$J$10:$J$25),"0") -> 0 | D23: =C23-B23 -> 0 | E23: FL3T-FB | G23: =+IFERROR(SUMIF(OB!$G$27:$G$44,'MACHINE REQURMENT'!E23,OB!$J$27:$J$44),"0") -> 0 | H23: =G23-F23 -> 0 | I23: FL3T-FB | K23: =+IFERROR(SUMIF(OB!$G$46:$G$83,'MACHINE REQURMENT'!I23,OB!$J$46:$J$83),"0") -> 0 | L23: =K23-J23 -> 0 | M23: FL3T-FB | N23: =D23+H23+L23 -> 0 | O23: =D23+H23+L23 -> 0 | R23: =C23+G23+K23 -> 0
A24: FL4T-FB | C24: =+IFERROR(SUMIF(OB!$G$10:$G$25,'MACHINE REQURMENT'!A24,OB!$J$10:$J$25),"0") -> 0 | D24: =C24-B24 -> 0 | E24: FL4T-FB | G24: =+IFERROR(SUMIF(OB!$G$27:$G$44,'MACHINE REQURMENT'!E24,OB!$J$27:$J$44),"0") -> 0 | H24: =G24-F24 -> 0 | I24: FL4T-FB | K24: =+IFERROR(SUMIF(OB!$G$46:$G$83,'MACHINE REQURMENT'!I24,OB!$J$46:$J$83),"0") -> 0 | L24: =K24-J24 -> 0 | M24: FL4T-FB | N24: =D24+H24+L24 -> 0 | O24: =D24+H24+L24 -> 0 | R24: =C24+G24+K24 -> 0
A25: FL5T-FB | C25: =+IFERROR(SUMIF(OB!$G$10:$G$25,'MACHINE REQURMENT'!A25,OB!$J$10:$J$25),"0") -> 0 | D25: =C25-B25 -> 0 | E25: FL5T-FB | G25: =+IFERROR(SUMIF(OB!$G$27:$G$44,'MACHINE REQURMENT'!E25,OB!$J$27:$J$44),"0") -> 0 | H25: =G25-F25 -> 0 | I25: FL5T-FB | K25: =+IFERROR(SUMIF(OB!$G$46:$G$83,'MACHINE REQURMENT'!I25,OB!$J$46:$J$83),"0") -> 0 | L25: =K25-J25 -> 0 | M25: FL5T-FB | N25: =D25+H25+L25 -> 0 | O25: =D25+H25+L25 -> 0 | Q25: =B25+F25+J25 -> 0 | R25: =C25+G25+K25 -> 0
A26: FL6T-FB | C26: =+IFERROR(SUMIF(OB!$G$10:$G$25,'MACHINE REQURMENT'!A26,OB!$J$10:$J$25),"0") -> 0 | D26: =C26-B26 -> 0 | E26: FL6T-FB | G26: =+IFERROR(SUMIF(OB!$G$27:$G$44,'MACHINE REQURMENT'!E26,OB!$J$27:$J$44),"0") -> 0 | H26: =G26-F26 -> 0 | I26: FL6T-FB | K26: =+IFERROR(SUMIF(OB!$G$46:$G$83,'MACHINE REQURMENT'!I26,OB!$J$46:$J$83),"0") -> 0 | L26: =K26-J26 -> 0 | M26: FL6T-FB | N26: =D26+H26+L26 -> 0 | O26: =D26+H26+L26 -> 0 | Q26: =B26+F26+J26 -> 0 | R26: =C26+G26+K26 -> 0
A27: FL2T-CB | C27: =+IFERROR(SUMIF(OB!$G$10:$G$25,'MACHINE REQURMENT'!A27,OB!$J$10:$J$25),"0") -> 0 | D27: =C27-B27 -> 0 | E27: FL2T-CB | G27: =+IFERROR(SUMIF(OB!$G$27:$G$44,'MACHINE REQURMENT'!E27,OB!$J$27:$J$44),"0") -> 0 | H27: =G27-F27 -> 0 | I27: FL2T-CB | K27: =+IFERROR(SUMIF(OB!$G$46:$G$83,'MACHINE REQURMENT'!I27,OB!$J$46:$J$83),"0") -> 0 | L27: =K27-J27 -> 0 | M27: FL2T-CB | N27: =D27+H27+L27 -> 0 | O27: =D27+H27+L27 -> 0 | Q27: =B27+F27+J27 -> 0 | R27: =C27+G27+K27 -> 0
A28: FL3T-CB | C28: =+IFERROR(SUMIF(OB!$G$10:$G$25,'MACHINE REQURMENT'!A28,OB!$J$10:$J$25),"0") -> 0 | D28: =C28-B28 -> 0 | E28: FL3T-CB | G28: =+IFERROR(SUMIF(OB!$G$27:$G$44,'MACHINE REQURMENT'!E28,OB!$J$27:$J$44),"0") -> 0 | H28: =G28-F28 -> 0 | I28: FL3T-CB | K28: =+IFERROR(SUMIF(OB!$G$46:$G$83,'MACHINE REQURMENT'!I28,OB!$J$46:$J$83),"0") -> 1 | L28: =K28-J28 -> 1 | M28: FL3T-CB | N28: =D28+H28+L28 -> 1 | O28: =D28+H28+L28 -> 1 | Q28: =B28+F28+J28 -> 0 | R28: =C28+G28+K28 -> 1
A29: FL4T-CB | C29: =+IFERROR(SUMIF(OB!$G$10:$G$25,'MACHINE REQURMENT'!A29,OB!$J$10:$J$25),"0") -> 0 | D29: =C29-B29 -> 0 | E29: FL4T-CB | G29: =+IFERROR(SUMIF(OB!$G$27:$G$44,'MACHINE REQURMENT'!E29,OB!$J$27:$J$44),"0") -> 0 | H29: =G29-F29 -> 0 | I29: FL4T-CB | K29: =+IFERROR(SUMIF(OB!$G$46:$G$83,'MACHINE REQURMENT'!I29,OB!$J$46:$J$83),"0") -> 0 | L29: =K29-J29 -> 0 | M29: FL4T-CB | N29: =D29+H29+L29 -> 0 | O29: =D29+H29+L29 -> 0 | Q29: =B29+F29+J29 -> 0 | R29: =C29+G29+K29 -> 0
A30: FL5T-CB | C30: =+IFERROR(SUMIF(OB!$G$10:$G$25,'MACHINE REQURMENT'!A30,OB!$J$10:$J$25),"0") -> 0 | D30: =C30-B30 -> 0 | E30: FL5T-CB | G30: =+IFERROR(SUMIF(OB!$G$27:$G$44,'MACHINE REQURMENT'!E30,OB!$J$27:$J$44),"0") -> 0 | H30: =G30-F30 -> 0 | I30: FL5T-CB | K30: =+IFERROR(SUMIF(OB!$G$46:$G$83,'MACHINE REQURMENT'!I30,OB!$J$46:$J$83),"0") -> 0 | L30: =K30-J30 -> 0 | M30: FL5T-CB | N30: =D30+H30+L30 -> 0 | O30: =D30+H30+L30 -> 0 | Q30: =B30+F30+J30 -> 0 | R30: =C30+G30+K30 -> 0
A31: FL6T-CB | C31: =+IFERROR(SUMIF(OB!$G$10:$G$25,'MACHINE REQURMENT'!A31,OB!$J$10:$J$25),"0") -> 0 | D31: =C31-B31 -> 0 | E31: FL6T-CB | G31: =+IFERROR(SUMIF(OB!$G$27:$G$44,'MACHINE REQURMENT'!E31,OB!$J$27:$J$44),"0") -> 0 | H31: =G31-F31 -> 0 | I31: FL6T-CB | K31: =+IFERROR(SUMIF(OB!$G$46:$G$83,'MACHINE REQURMENT'!I31,OB!$J$46:$J$83),"0") -> 0 | L31: =K31-J31 -> 0 | M31: FL6T-CB | N31: =D31+H31+L31 -> 0 | O31: =D31+H31+L31 -> 0 | Q31: =B31+F31+J31 -> 0 | R31: =C31+G31+K31 -> 0
A32: BLIND LOOP | C32: =+IFERROR(SUMIF(OB!$G$10:$G$25,'MACHINE REQURMENT'!A32,OB!$J$10:$J$25),"0") -> 0 | D32: =C32-B32 -> 0 | E32: BLIND LOOP | G32: =+IFERROR(SUMIF(OB!$G$27:$G$44,'MACHINE REQURMENT'!E32,OB!$J$27:$J$44),"0") -> 0 | H32: =G32-F32 -> 0 | I32: BLIND LOOP | K32: =+IFERROR(SUMIF(OB!$G$46:$G$83,'MACHINE REQURMENT'!I32,OB!$J$46:$J$83),"0") -> 0 | L32: =K32-J32 -> 0 | M32: BLIND LOOP | N32: =D32+H32+L32 -> 0 | O32: =D32+H32+L32 -> 0 | Q32: =B32+F32+J32 -> 0 | R32: =C32+G32+K32 -> 0
A33: FLAT LOOP | C33: =+IFERROR(SUMIF(OB!$G$10:$G$25,'MACHINE REQURMENT'!A33,OB!$J$10:$J$25),"0") -> 0 | D33: =C33-B33 -> 0 | E33: FLAT LOOP | G33: =+IFERROR(SUMIF(OB!$G$27:$G$44,'MACHINE REQURMENT'!E33,OB!$J$27:$J$44),"0") -> 0 | H33: =G33-F33 -> 0 | I33: FLAT LOOP | K33: =+IFERROR(SUMIF(OB!$G$46:$G$83,'MACHINE REQURMENT'!I33,OB!$J$46:$J$83),"0") -> 0 | L33: =K33-J33 -> 0 | M33: FLAT LOOP | N33: =D33+H33+L33 -> 0 | O33: =D33+H33+L33 -> 0 | Q33: =B33+F33+J33 -> 0 | R33: =C33+G33+K33 -> 0
A34: KANSAI LOOP | C34: =+IFERROR(SUMIF(OB!$G$10:$G$25,'MACHINE REQURMENT'!A34,OB!$J$10:$J$25),"0") -> 0 | D34: =C34-B34 -> 0 | E34: KANSAI LOOP | G34: =+IFERROR(SUMIF(OB!$G$27:$G$44,'MACHINE REQURMENT'!E34,OB!$J$27:$J$44),"0") -> 0 | H34: =G34-F34 -> 0 | I34: KANSAI LOOP | K34: =+IFERROR(SUMIF(OB!$G$46:$G$83,'MACHINE REQURMENT'!I34,OB!$J$46:$J$83),"0") -> 0 | L34: =K34-J34 -> 0 | M34: KANSAI LOOP | N34: =D34+H34+L34 -> 0 | O34: =D34+H34+L34 -> 0 | Q34: =B34+F34+J34 -> 0 | R34: =C34+G34+K34 -> 0
A35: HEAT SEAL | C35: =+IFERROR(SUMIF(OB!$G$10:$G$25,'MACHINE REQURMENT'!A35,OB!$J$10:$J$25),"0") -> 0 | D35: =C35-B35 -> 0 | E35: HEAT SEAL | G35: =+IFERROR(SUMIF(OB!$G$27:$G$44,'MACHINE REQURMENT'!E35,OB!$J$27:$J$44),"0") -> 0 | H35: =G35-F35 -> 0 | I35: HEAT SEAL | K35: =+IFERROR(SUMIF(OB!$G$46:$G$83,'MACHINE REQURMENT'!I35,OB!$J$46:$J$83),"0") -> 0 | L35: =K35-J35 -> 0 | M35: HEAT SEAL | N35: =D35+H35+L35 -> 0 | O35: =D35+H35+L35 -> 0 | Q35: =B35+F35+J35 -> 0 | R35: =C35+G35+K35 -> 0
A36: AUTO LOOP | C36: =+IFERROR(SUMIF(OB!$G$10:$G$25,'MACHINE REQURMENT'!A36,OB!$J$10:$J$25),"0") -> 0 | D36: =C36-B36 -> 0 | E36: AUTO LOOP | G36: =+IFERROR(SUMIF(OB!$G$27:$G$44,'MACHINE REQURMENT'!E36,OB!$J$27:$J$44),"0") -> 0 | H36: =G36-F36 -> 0 | I36: AUTO LOOP | K36: =+IFERROR(SUMIF(OB!$G$46:$G$83,'MACHINE REQURMENT'!I36,OB!$J$46:$J$83),"0") -> 0 | L36: =K36-J36 -> 0 | M36: AUTO LOOP | N36: =D36+H36+L36 -> 0 | O36: =D36+H36+L36 -> 0 | Q36: =B36+F36+J36 -> 0 | R36: =C36+G36+K36 -> 0
... A39: IRON TABLE | C39: =+IFERROR(SUMIF(OB!$G$10:$G$25,'MACHINE REQURMENT'!A39,OB!$J$10:$J$25),"0") -> 2 | D39: =C39-B39 -> 2 | E39: IRON TABLE | G39: =+IFERROR(SUMIF(OB!$G$27:$G$44,'MACHINE REQURMENT'!E39,OB!$J$27:$J$44),"0") -> 1 | H39: =G39-F39 -> 1 | I39: IRON TABLE | K39: =+IFERROR(SUMIF(OB!$G$46:$G$83,'MACHINE REQURMENT'!I39,OB!$J$46:$J$83),"0") -> 4 | L39: =K39-J39 -> 4 | M39: IRON TABLE | N39: =D39+H39+L39 -> 7 | O39: =D39+H39+L39 -> 7 | Q39: =B39+F39+J39 -> 0 | R39: =C39+G39+K39 -> 7
B40: =SUM(B4:B39) -> 0 | C40: =SUM(C4:C39) -> 7 | D40: =SUM(D4:D39) -> 7 | F40: =SUM(F4:F39) -> 0 | G40: =SUM(G4:G39) -> 9 | H40: =SUM(H4:H39) -> 9 | J40: =SUM(J4:J39) -> 0 | K40: =SUM(K4:K39) -> 36 | L40: =SUM(L4:L39) -> 36 | N40: =SUM(N4:N39) -> 52 | O40: =SUM(O4:O39) -> 52 | Q40: =B40+F40+J40 -> 0 | R40: =C40+G40+K40 -> 52

Sheet STARTUP DRIVE REPORT
A1: SIDNEY APPARELS START UP DRIVE REPORT - SUMMARY
A2: IE | B2: =OB!M4 -> SHANAKA | C2: Style | D2: =OB!C2 -> S2554MESS651WV | E2: Time Start | I2: Total time | K2: =IFERROR(IF(AND(G2<>"",G3<>""),(G3-G2)*1440,""),"") | M2: CAPACITY CHECK | S2: MAINTANANCE DETAILS | AI2: TECHNICAL AND QUALITY DETAILS
A3: SUP | B3: =OB!M3 -> NAZIR | C3: Changeover Type | E3: Time End | I3: COPT | K3: =IFERROR(K2/OB!C3,"")
A4: S # | B4: Operation Name | C4: Operator Name | D4: Op Id | E4: Time In sec 1 | F4: Time In sec 2 | G4: Time In sec 3 | H4: Time In sec 4 | I4: Time In sec 5 | J4: Line Target | K4: TOTAL ALLOTED MANPOWER | L4: TOTAL ACHIVED | M4: Avg Time | N4: Bi-Hourly Target | O4: Bi-Hourly Capacity with allw% | P4: Percentage of Capacity against Target | Q4: ACHIVED % | R4: Remarks 1 | S4: MACHINE Verification | T4: PROCESS Experience | U4: SIMILAR PROCESS Experience | V4: MACHINE Experience | W4: M/C Type | X4: Presser Foot | Y4: Special Attachment | Z4: Bobbin tension | AA4: Needle Tension | AB4: SPI | AC4: Threading | AD4: Needle Size / Point | AE4: M/C Speed | AF4: Wiper | AG4: Saftey | AH4: Remarks 2 | AI4: # of pcs checked | AJ4: # of defects | AK4: Description of defect | AL4: Reason | AM4: Corrective Action | AP4: A
A5: 1 | B5: =IF(IFERROR(INDEX(OB!$B:$B,MATCH('STARTUP DRIVE REPORT'!$A:$A,OB!$A:$A,0)),"")=0,"",IFERROR(INDEX(OB!$B:$B,MATCH('STARTUP DRIVE REPORT'!$A:$A,OB!$A:$A,0)),"")) -> ATTACH THREE STRIPE | J5: =IFERROR((IF(B5="","",OB!$K$3)),"") -> 850 | K5: =IF(IFERROR(INDEX(OB!$K:$K,MATCH('STARTUP DRIVE REPORT'!$A:$A,OB!$A:$A,0)),"")=0,"",IFERROR(INDEX(OB!$K:$K,MATCH('STARTUP DRIVE REPORT'!$A:$A,OB!$A:$A,0)),"")) -> 1.25 | M5: =IFERROR(AVERAGE(E5:I5),"") | N5: =IF(OR(J5="",K5=""),"",J5/(K5*5)) -> 136 | O5: =IFERROR((IF(W5="4TOL",((7200/M5)*87%),IF(W5="SNLS",((7200/M5)*88%),IF(W5="KANSAI",((7200/M5)*85%),IF(W5="3TFLCB",((7200/M5)*87%),IF(W5="2TFLFB",((7200/M5)*87%),IF(W5="2TFLCB",((7200/M5)*87%),IF(W5="BH",((7200/M5)*90%),IF(W5="BT",((7200/M5)*90%),((7200/M5)*92%)))))))))),"") | P5: =IFERROR(O5/N5,"") | Q5: =IFERROR(K5*L5/J5,"") -> 0 | R5: =IFERROR(IF((Q5>P5),"DATA ERROR",IF((P5-Q5)>5%,"CHECK FEEDING","")),"") | W5: =IF(IFERROR(INDEX(OB!$G:$G,MATCH('STARTUP DRIVE REPORT'!$A:$A,OB!$A:$A,0)),"")=0,"",IFERROR(INDEX(OB!$G:$G,MATCH('STARTUP DRIVE REPORT'!$A:$A,OB!$A:$A,0)),"")) -> KANSAI | AP5: B | AQ5: 1
A6: =+A5+1 -> 2 | B6: =IF(IFERROR(INDEX(OB!$B:$B,MATCH('STARTUP DRIVE REPORT'!$A:$A,OB!$A:$A,0)),"")=0,"",IFERROR(INDEX(OB!$B:$B,MATCH('STARTUP DRIVE REPORT'!$A:$A,OB!$A:$A,0)),"")) -> CHECK & TRIM THREE STRIPE | J6: =IFERROR((IF(B6="","",OB!$K$3)),"") -> 850 | K6: =IF(IFERROR(INDEX(OB!$K:$K,MATCH('STARTUP DRIVE REPORT'!$A:$A,OB!$A:$A,0)),"")=0,"",IFERROR(INDEX(OB!$K:$K,MATCH('STARTUP DRIVE REPORT'!$A:$A,OB!$A:$A,0)),"")) -> 0.75 | M6: =IFERROR(AVERAGE(E6:I6),"") | N6: =IF(OR(J6="",K6=""),"",J6/(K6*5)) -> 226.66667 | O6: =IFERROR((IF(W6="4TOL",((7200/M6)*87%),IF(W6="SNLS",((7200/M6)*88%),IF(W6="KANSAI",((7200/M6)*85%),IF(W6="3TFLCB",((7200/M6)*87%),IF(W6="2TFLFB",((7200/M6)*87%),IF(W6="2TFLCB",((7200/M6)*87%),IF(W6="BH",((7200/M6)*90%),IF(W6="BT",((7200/M6)*90%),((7200/M6)*92%)))))))))),"") | P6: =IFERROR(O6/N6,"") | Q6: =IFERROR(K6*L6/J6,"") -> 0 | R6: =IFERROR(IF((Q6>P6),"DATA ERROR",IF((P6-Q6)>5%,"CHECK FEEDING","")),"") | W6: =IF(IFERROR(INDEX(OB!$G:$G,MATCH('STARTUP DRIVE REPORT'!$A:$A,OB!$A:$A,0)),"")=0,"",IFERROR(INDEX(OB!$G:$G,MATCH('STARTUP DRIVE REPORT'!$A:$A,OB!$A:$A,0)),"")) -> TABLE | AP6: C | AQ6: 2
A7: =+A6+1 -> 3 | B7: =IF(IFERROR(INDEX(OB!$B:$B,MATCH('STARTUP DRIVE REPORT'!$A:$A,OB!$A:$A,0)),"")=0,"",IFERROR(INDEX(OB!$B:$B,MATCH('STARTUP DRIVE REPORT'!$A:$A,OB!$A:$A,0)),"")) -> JOIN BACK RISE | J7: =IFERROR((IF(B7="","",OB!$K$3)),"") -> 850 | K7: =IF(IFERROR(INDEX(OB!$K:$K,MATCH('STARTUP DRIVE REPORT'!$A:$A,OB!$A:$A,0)),"")=0,"",IFERROR(INDEX(OB!$K:$K,MATCH('STARTUP DRIVE REPORT'!$A:$A,OB!$A:$A,0)),"")) -> 0.5 | M7: =IFERROR(AVERAGE(E7:I7),"") | N7: =IF(OR(J7="",K7=""),"",J7/(K7*5)) -> 340 | O7: =IFERROR((IF(W7="4TOL",((7200/M7)*87%),IF(W7="SNLS",((7200/M7)*88%),IF(W7="KANSAI",((7200/M7)*85%),IF(W7="3TFLCB",((7200/M7)*87%),IF(W7="2TFLFB",((7200/M7)*87%),IF(W7="2TFLCB",((7200/M7)*87%),IF(W7="BH",((7200/M7)*90%),IF(W7="BT",((7200/M7)*90%),((7200/M7)*92%)))))))))),"") | P7: =IFERROR(O7/N7,"") | Q7: =IFERROR(K7*L7/J7,"") -> 0 | R7: =IFERROR(IF((Q7>P7),"DATA ERROR",IF((P7-Q7)>5%,"CHECK FEEDING","")),"") | W7: =IF(IFERROR(INDEX(OB!$G:$G,MATCH('STARTUP DRIVE REPORT'!$A:$A,OB!$A:$A,0)),"")=0,"",IFERROR(INDEX(OB!$G:$G,MATCH('STARTUP DRIVE REPORT'!$A:$A,OB!$A:$A,0)),"")) -> OL4T | AQ7: 2
A8: =+A7+1 -> 4 | B8: =IF(IFERROR(INDEX(OB!$B:$B,MATCH('STARTUP DRIVE REPORT'!$A:$A,OB!$A:$A,0)),"")=0,"",IFERROR(INDEX(OB!$B:$B,MATCH('STARTUP DRIVE REPORT'!$A:$A,OB!$A:$A,0)),"")) -> FUSE & CREASE BOTTOM FOR ZIPPER | J8: =IFERROR((IF(B8="","",OB!$K$3)),"") -> 850 | K8: =IF(IFERROR(INDEX(OB!$K:$K,MATCH('STARTUP DRIVE REPORT'!$A:$A,OB!$A:$A,0)),"")=0,"",IFERROR(INDEX(OB!$K:$K,MATCH('STARTUP DRIVE REPORT'!$A:$A,OB!$A:$A,0)),"")) -> 1.25 | M8: =IFERROR(AVERAGE(E8:I8),"") | N8: =IF(OR(J8="",K8=""),"",J8/(K8*5)) -> 136 | O8: =IFERROR((IF(W8="4TOL",((7200/M8)*87%),IF(W8="SNLS",((7200/M8)*88%),IF(W8="KANSAI",((7200/M8)*85%),IF(W8="3TFLCB",((7200/M8)*87%),IF(W8="2TFLFB",((7200/M8)*87%),IF(W8="2TFLCB",((7200/M8)*87%),IF(W8="BH",((7200/M8)*90%),IF(W8="BT",((7200/M8)*90%),((7200/M8)*92%)))))))))),"") | P8: =IFERROR(O8/N8,"") | Q8: =IFERROR(K8*L8/J8,"") -> 0 | R8: =IFERROR(IF((Q8>P8),"DATA ERROR",IF((P8-Q8)>5%,"CHECK FEEDING","")),"") | W8: =IF(IFERROR(INDEX(OB!$G:$G,MATCH('STARTUP DRIVE REPORT'!$A:$A,OB!$A:$A,0)),"")=0,"",IFERROR(INDEX(OB!$G:$G,MATCH('STARTUP DRIVE REPORT'!$A:$A,OB!$A:$A,0)),"")) -> IRON TABLE | AQ8: 2
A9: =+A8+1 -> 5 | B9: =IF(IFERROR(INDEX(OB!$B:$B,MATCH('STARTUP DRIVE REPORT'!$A:$A,OB!$A:$A,0)),"")=0,"",IFERROR(INDEX(OB!$B:$B,MATCH('STARTUP DRIVE REPORT'!$A:$A,OB!$A:$A,0)),"")) -> SERGE BOTTOM FOR LEG ZIPPER*2 | J9: =IFERROR((IF(B9="","",OB!$K$3)),"") -> 850 | K9: =IF(IFERROR(INDEX(OB!$K:$K,MATCH('STARTUP DRIVE REPORT'!$A:$A,OB!$A:$A,0)),"")=0,"",IFERROR(INDEX(OB!$K:$K,MATCH('STARTUP DRIVE REPORT'!$A:$A,OB!$A:$A,0)),"")) -> 0.5 | M9: =IFERROR(AVERAGE(E9:I9),"") | N9: =IF(OR(J9="",K9=""),"",J9/(K9*5)) -> 340 | O9: =IFERROR((IF(W9="4TOL",((7200/M9)*87%),IF(W9="SNLS",((7200/M9)*88%),IF(W9="KANSAI",((7200/M9)*85%),IF(W9="3TFLCB",((7200/M9)*87%),IF(W9="2TFLFB",((7200/M9)*87%),IF(W9="2TFLCB",((7200/M9)*87%),IF(W9="BH",((7200/M9)*90%),IF(W9="BT",((7200/M9)*90%),((7200/M9)*92%)))))))))),"") | P9: =IFERROR(O9/N9,"") | Q9: =IFERROR(K9*L9/J9,"") -> 0 | R9: =IFERROR(IF((Q9>P9),"DATA ERROR",IF((P9-Q9)>5%,"CHECK FEEDING","")),"") | W9: =IF(IFERROR(INDEX(OB!$G:$G,MATCH('STARTUP DRIVE REPORT'!$A:$A,OB!$A:$A,0)),"")=0,"",IFERROR(INDEX(OB!$G:$G,MATCH('STARTUP DRIVE REPORT'!$A:$A,OB!$A:$A,0)),"")) -> OL4T | AQ9: 2
A10: =+A9+1 -> 6 | B10: =IF(IFERROR(INDEX(OB!$B:$B,MATCH('STARTUP DRIVE REPORT'!$A:$A,OB!$A:$A,0)),"")=0,"",IFERROR(INDEX(OB!$B:$B,MATCH('STARTUP DRIVE REPORT'!$A:$A,OB!$A:$A,0)),"")) | J10: =IFERROR((IF(B10="","",OB!$K$3)),"") | K10: =IF(IFERROR(INDEX(OB!$K:$K,MATCH('STARTUP DRIVE REPORT'!$A:$A,OB!$A:$A,0)),"")=0,"",IFERROR(INDEX(OB!$K:$K,MATCH('STARTUP DRIVE REPORT'!$A:$A,OB!$A:$A,0)),"")) | M10: =IFERROR(AVERAGE(E10:I10),"") | N10: =IF(OR(J10="",K10=""),"",J10/(K10*5)) | O10: =IFERROR((IF(W10="4TOL",((7200/M10)*87%),IF(W10="SNLS",((7200/M10)*88%),IF(W10="KANSAI",((7200/M10)*85%),IF(W10="3TFLCB",((7200/M10)*87%),IF(W10="2TFLFB",((7200/M10)*87%),IF(W10="2TFLCB",((7200/M10)*87%),IF(W10="BH",((7200/M10)*90%),IF(W10="BT",((7200/M10)*90%),((7200/M10)*92%)))))))))),"") | P10: =IFERROR(O10/N10,"") | Q10: =IFERROR(K10*L10/J10,"") | R10: =IFERROR(IF((Q10>P10),"DATA ERROR",IF((P10-Q10)>5%,"CHECK FEEDING","")),"") | W10: =IF(IFERROR(INDEX(OB!$G:$G,MATCH('STARTUP DRIVE REPORT'!$A:$A,OB!$A:$A,0)),"")=0,"",IFERROR(INDEX(OB!$G:$G,MATCH('STARTUP DRIVE REPORT'!$A:$A,OB!$A:$A,0)),"")) | AQ10: 2
A11: =+A10+1 -> 7 | B11: =IF(IFERROR(INDEX(OB!$B:$B,MATCH('STARTUP DRIVE REPORT'!$A:$A,OB!$A:$A,0)),"")=0,"",IFERROR(INDEX(OB!$B:$B,MATCH('STARTUP DRIVE REPORT'!$A:$A,OB!$A:$A,0)),"")) | J11: =IFERROR((IF(B11="","",OB!$K$3)),"") | K11: =IF(IFERROR(INDEX(OB!$K:$K,MATCH('STARTUP DRIVE REPORT'!$A:$A,OB!$A:$A,0)),"")=0,"",IFERROR(INDEX(OB!$K:$K,MATCH('STARTUP DRIVE REPORT'!$A:$A,OB!$A:$A,0)),"")) | M11: =IFERROR(AVERAGE(E11:I11),"") | N11: =IF(OR(J11="",K11=""),"",J11/(K11*5)) | O11: =IFERROR((IF(W11="4TOL",((7200/M11)*87%),IF(W11="SNLS",((7200/M11)*88%),IF(W11="KANSAI",((7200/M11)*85%),IF(W11="3TFLCB",((7200/M11)*87%),IF(W11="2TFLFB",((7200/M11)*87%),IF(W11="2TFLCB",((7200/M11)*87%),IF(W11="BH",((7200/M11)*90%),IF(W11="BT",((7200/M11)*90%),((7200/M11)*92%)))))))))),"") | P11: =IFERROR(O11/N11,"") | Q11: =IFERROR(K11*L11/J11,"") | R11: =IFERROR(IF((Q11>P11),"DATA ERROR",IF((P11-Q11)>5%,"CHECK FEEDING","")),"") | W11: =IF(IFERROR(INDEX(OB!$G:$G,MATCH('STARTUP DRIVE REPORT'!$A:$A,OB!$A:$A,0)),"")=0,"",IFERROR(INDEX(OB!$G:$G,MATCH('STARTUP DRIVE REPORT'!$A:$A,OB!$A:$A,0)),"")) | AQ11: 2
A12: =+A11+1 -> 8 | B12: =IF(IFERROR(INDEX(OB!$B:$B,MATCH('STARTUP DRIVE REPORT'!$A:$A,OB!$A:$A,0)),"")=0,"",IFERROR(INDEX(OB!$B:$B,MATCH('STARTUP DRIVE REPORT'!$A:$A,OB!$A:$A,0)),"")) | J12: =IFERROR((IF(B12="","",OB!$K$3)),"") | K12: =IF(IFERROR(INDEX(OB!$K:$K,MATCH('STARTUP DRIVE REPORT'!$A:$A,OB!$A:$A,0)),"")=0,"",IFERROR(INDEX(OB!$K:$K,MATCH('STARTUP DRIVE REPORT'!$A:$A,OB!$A:$A,0)),"")) | M12: =IFERROR(AVERAGE(E12:I12),"") | N12: =IF(OR(J12="",K12=""),"",J12/(K12*5)) | O12: =IFERROR((IF(W12="4TOL",((7200/M12)*87%),IF(W12="SNLS",((7200/M12)*88%),IF(W12="KANSAI",((7200/M12)*85%),IF(W12="3TFLCB",((7200/M12)*87%),IF(W12="2TFLFB",((7200/M12)*87%),IF(W12="2TFLCB",((7200/M12)*87%),IF(W12="BH",((7200/M12)*90%),IF(W12="BT",((7200/M12)*90%),((7200/M12)*92%)))))))))),"") | P12: =IFERROR(O12/N12,"") | Q12: =IFERROR(K12*L12/J12,"") | R12: =IFERROR(IF((Q12>P12),"DATA ERROR",IF((P12-Q12)>5%,"CHECK FEEDING","")),"") | W12: =IF(IFERROR(INDEX(OB!$G:$G,MATCH('STARTUP DRIVE REPORT'!$A:$A,OB!$A:$A,0)),"")=0,"",IFERROR(INDEX(OB!$G:$G,MATCH('STARTUP DRIVE REPORT'!$A:$A,OB!$A:$A,0)),"")) | AQ12: 2
A13: =+A12+1 -> 9 | B13: =IF(IFERROR(INDEX(OB!$B:$B,MATCH('STARTUP DRIVE REPORT'!$A:$A,OB!$A:$A,0)),"")=0,"",IFERROR(INDEX(OB!$B:$B,MATCH('STARTUP DRIVE REPORT'!$A:$A,OB!$A:$A,0)),"")) | J13: =IFERROR((IF(B13="","",OB!$K$3)),"") | K13: =IF(IFERROR(INDEX(OB!$K:$K,MATCH('STARTUP DRIVE REPORT'!$A:$A,OB!$A:$A,0)),"")=0,"",IFERROR(INDEX(OB!$K:$K,MATCH('STARTUP DRIVE REPORT'!$A:$A,OB!$A:$A,0)),"")) | M13: =IFERROR(AVERAGE(E13:I13),"") | N13: =IF(OR(J13="",K13=""),"",J13/(K13*5)) | O13: =IFERROR((IF(W13="4TOL",((7200/M13)*87%),IF(W13="SNLS",((7200/M13)*88%),IF(W13="KANSAI",((7200/M13)*85%),IF(W13="3TFLCB",((7200/M13)*87%),IF(W13="2TFLFB",((7200/M13)*87%),IF(W13="2TFLCB",((7200/M13)*87%),IF(W13="BH",((7200/M13)*90%),IF(W13="BT",((7200/M13)*90%),((7200/M13)*92%)))))))))),"") | P13: =IFERROR(O13/N13,"") | Q13: =IFERROR(K13*L13/J13,"") | R13: =IFERROR(IF((Q13>P13),"DATA ERROR",IF((P13-Q13)>5%,"CHECK FEEDING","")),"") | W13: =IF(IFERROR(INDEX(OB!$G:$G,MATCH('STARTUP DRIVE REPORT'!$A:$A,OB!$A:$A,0)),"")=0,"",IFERROR(INDEX(OB!$G:$G,MATCH('STARTUP DRIVE REPORT'!$A:$A,OB!$A:$A,0)),"")) | AQ13: 2
A14: =+A13+1 -> 10 | B14: =IF(IFERROR(INDEX(OB!$B:$B,MATCH('STARTUP DRIVE REPORT'!$A:$A,OB!$A:$A,0)),"")=0,"",IFERROR(INDEX(OB!$B:$B,MATCH('STARTUP DRIVE REPORT'!$A:$A,OB!$A:$A,0)),"")) | J14: =IFERROR((IF(B14="","",OB!$K$3)),"") | K14: =IF(IFERROR(INDEX(OB!$K:$K,MATCH('STARTUP DRIVE REPORT'!$A:$A,OB!$A:$A,0)),"")=0,"",IFERROR(INDEX(OB!$K:$K,MATCH('STARTUP DRIVE REPORT'!$A:$A,OB!$A:$A,0)),"")) | M14: =IFERROR(AVERAGE(E14:I14),"") | N14: =IF(OR(J14="",K14=""),"",J14/(K14*5)) | O14: =IFERROR((IF(W14="4TOL",((7200/M14)*87%),IF(W14="SNLS",((7200/M14)*88%),IF(W14="KANSAI",((7200/M14)*85%),IF(W14="3TFLCB",((7200/M14)*87%),IF(W14="2TFLFB",((7200/M14)*87%),IF(W14="2TFLCB",((7200/M14)*87%),IF(W14="BH",((7200/M14)*90%),IF(W14="BT",((7200/M14)*90%),((7200/M14)*92%)))))))))),"") | P14: =IFERROR(O14/N14,"") | Q14: =IFERROR(K14*L14/J14,"") | R14: =IFERROR(IF((Q14>P14),"DATA ERROR",IF((P14-Q14)>5%,"CHECK FEEDING","")),"") | W14: =IF(IFERROR(INDEX(OB!$G:$G,MATCH('STARTUP DRIVE REPORT'!$A:$A,OB!$A:$A,0)),"")=0,"",IFERROR(INDEX(OB!$G:$G,MATCH('STARTUP DRIVE REPORT'!$A:$A,OB!$A:$A,0)),"")) | AQ14: 2
A15: =+A14+1 -> 11 | B15: =IF(IFERROR(INDEX(OB!$B:$B,MATCH('STARTUP DRIVE REPORT'!$A:$A,OB!$A:$A,0)),"")=0,"",IFERROR(INDEX(OB!$B:$B,MATCH('STARTUP DRIVE REPORT'!$A:$A,OB!$A:$A,0)),"")) | J15: =IFERROR((IF(B15="","",OB!$K$3)),"") | K15: =IF(IFERROR(INDEX(OB!$K:$K,MATCH('STARTUP DRIVE REPORT'!$A:$A,OB!$A:$A,0)),"")=0,"",IFERROR(INDEX(OB!$K:$K,MATCH('STARTUP DRIVE REPORT'!$A:$A,OB!$A:$A,0)),"")) | M15: =IFERROR(AVERAGE(E15:I15),"") | N15: =IF(OR(J15="",K15=""),"",J15/(K15*5)) | O15: =IFERROR((IF(W15="4TOL",((7200/M15)*87%),IF(W15="SNLS",((7200/M15)*88%),IF(W15="KANSAI",((7200/M15)*85%),IF(W15="3TFLCB",((7200/M15)*87%),IF(W15="2TFLFB",((7200/M15)*87%),IF(W15="2TFLCB",((7200/M15)*87%),IF(W15="BH",((7200/M15)*90%),IF(W15="BT",((7200/M15)*90%),((7200/M15)*92%)))))))))),"") | P15: =IFERROR(O15/N15,"") | Q15: =IFERROR(K15*L15/J15,"") | R15: =IFERROR(IF((Q15>P15),"DATA ERROR",IF((P15-Q15)>5%,"CHECK FEEDING","")),"") | W15: =IF(IFERROR(INDEX(OB!$G:$G,MATCH('STARTUP DRIVE REPORT'!$A:$A,OB!$A:$A,0)),"")=0,"",IFERROR(INDEX(OB!$G:$G,MATCH('STARTUP DRIVE REPORT'!$A:$A,OB!$A:$A,0)),"")) | AQ15: 2
A16: =+A15+1 -> 12 | B16: =IF(IFERROR(INDEX(OB!$B:$B,MATCH('STARTUP DRIVE REPORT'!$A:$A,OB!$A:$A,0)),"")=0,"",IFERROR(INDEX(OB!$B:$B,MATCH('STARTUP DRIVE REPORT'!$A:$A,OB!$A:$A,0)),"")) | J16: =IFERROR((IF(B16="","",OB!$K$3)),"") | K16: =IF(IFERROR(INDEX(OB!$K:$K,MATCH('STARTUP DRIVE REPORT'!$A:$A,OB!$A:$A,0)),"")=0,"",IFERROR(INDEX(OB!$K:$K,MATCH('STARTUP DRIVE REPORT'!$A:$A,OB!$A:$A,0)),"")) | M16: =IFERROR(AVERAGE(E16:I16),"") | N16: =IF(OR(J16="",K16=""),"",J16/(K16*5)) | O16: =IFERROR((IF(W16="4TOL",((7200/M16)*87%),IF(W16="SNLS",((7200/M16)*88%),IF(W16="KANSAI",((7200/M16)*85%),IF(W16="3TFLCB",((7200/M16)*87%),IF(W16="2TFLFB",((7200/M16)*87%),IF(W16="2TFLCB",((7200/M16)*87%),IF(W16="BH",((7200/M16)*90%),IF(W16="BT",((7200/M16)*90%),((7200/M16)*92%)))))))))),"") | P16: =IFERROR(O16/N16,"") | Q16: =IFERROR(K16*L16/J16,"") | R16: =IFERROR(IF((Q16>P16),"DATA ERROR",IF((P16-Q16)>5%,"CHECK FEEDING","")),"") | W16: =IF(IFERROR(INDEX(OB!$G:$G,MATCH('STARTUP DRIVE REPORT'!$A:$A,OB!$A:$A,0)),"")=0,"",IFERROR(INDEX(OB!$G:$G,MATCH('STARTUP DRIVE REPORT'!$A:$A,OB!$A:$A,0)),"")) | AQ16: 2
A17: =+A16+1 -> 13 | B17: =IF(IFERROR(INDEX(OB!$B:$B,MATCH('STARTUP DRIVE REPORT'!$A:$A,OB!$A:$A,0)),"")=0,"",IFERROR(INDEX(OB!$B:$B,MATCH('STARTUP DRIVE REPORT'!$A:$A,OB!$A:$A,0)),"")) -> FUSE & CREASE POCKET MOUTH | J17: =IFERROR((IF(B17="","",OB!$K$3)),"") -> 850 | K17: =IF(IFERROR(INDEX(OB!$K:$K,MATCH('STARTUP DRIVE REPORT'!$A:$A,OB!$A:$A,0)),"")=0,"",IFERROR(INDEX(OB!$K:$K,MATCH('STARTUP DRIVE REPORT'!$A:$A,OB!$A:$A,0)),"")) -> 0.75 | M17: =IFERROR(AVERAGE(E17:I17),"") | N17: =IF(OR(J17="",K17=""),"",J17/(K17*5)) -> 226.66667 | O17: =IFERROR((IF(W17="4TOL",((7200/M17)*87%),IF(W17="SNLS",((7200/M17)*88%),IF(W17="KANSAI",((7200/M17)*85%),IF(W17="3TFLCB",((7200/M17)*87%),IF(W17="2TFLFB",((7200/M17)*87%),IF(W17="2TFLCB",((7200/M17)*87%),IF(W17="BH",((7200/M17)*90%),IF(W17="BT",((7200/M17)*90%),((7200/M17)*92%)))))))))),"") | P17: =IFERROR(O17/N17,"") | Q17: =IFERROR(K17*L17/J17,"") -> 0 | R17: =IFERROR(IF((Q17>P17),"DATA ERROR",IF((P17-Q17)>5%,"CHECK FEEDING","")),"") | W17: =IF(IFERROR(INDEX(OB!$G:$G,MATCH('STARTUP DRIVE REPORT'!$A:$A,OB!$A:$A,0)),"")=0,"",IFERROR(INDEX(OB!$G:$G,MATCH('STARTUP DRIVE REPORT'!$A:$A,OB!$A:$A,0)),"")) -> IRON TABLE | AQ17: 2
A18: =+A17+1 -> 14 | B18: =IF(IFERROR(INDEX(OB!$B:$B,MATCH('STARTUP DRIVE REPORT'!$A:$A,OB!$A:$A,0)),"")=0,"",IFERROR(INDEX(OB!$B:$B,MATCH('STARTUP DRIVE REPORT'!$A:$A,OB!$A:$A,0)),"")) -> ATTACH FACING TO POCKET BAG*2 | J18: =IFERROR((IF(B18="","",OB!$K$3)),"") -> 850 | K18: =IF(IFERROR(INDEX(OB!$K:$K,MATCH('STARTUP DRIVE REPORT'!$A:$A,OB!$A:$A,0)),"")=0,"",IFERROR(INDEX(OB!$K:$K,MATCH('STARTUP DRIVE REPORT'!$A:$A,OB!$A:$A,0)),"")) -> 0.5 | M18: =IFERROR(AVERAGE(E18:I18),"") | N18: =IF(OR(J18="",K18=""),"",J18/(K18*5)) -> 340 | O18: =IFERROR((IF(W18="4TOL",((7200/M18)*87%),IF(W18="SNLS",((7200/M18)*88%),IF(W18="KANSAI",((7200/M18)*85%),IF(W18="3TFLCB",((7200/M18)*87%),IF(W18="2TFLFB",((7200/M18)*87%),IF(W18="2TFLCB",((7200/M18)*87%),IF(W18="BH",((7200/M18)*90%),IF(W18="BT",((7200/M18)*90%),((7200/M18)*92%)))))))))),"") | P18: =IFERROR(O18/N18,"") | Q18: =IFERROR(K18*L18/J18,"") -> 0 | R18: =IFERROR(IF((Q18>P18),"DATA ERROR",IF((P18-Q18)>5%,"CHECK FEEDING","")),"") | W18: =IF(IFERROR(INDEX(OB!$G:$G,MATCH('STARTUP DRIVE REPORT'!$A:$A,OB!$A:$A,0)),"")=0,"",IFERROR(INDEX(OB!$G:$G,MATCH('STARTUP DRIVE REPORT'!$A:$A,OB!$A:$A,0)),"")) -> SNLS | AQ18: 2
... A94: =+A93+1 -> 90 | B94: =IF(IFERROR(INDEX(OB!$B:$B,MATCH('STARTUP DRIVE REPORT'!$A:$A,OB!$A:$A,0)),"")=0,"",IFERROR(INDEX(OB!$B:$B,MATCH('STARTUP DRIVE REPORT'!$A:$A,OB!$A:$A,0)),"")) | J94: =IFERROR((IF(B94="","",OB!$K$3)),"") | K94: =IF(IFERROR(INDEX(OB!$K:$K,MATCH('STARTUP DRIVE REPORT'!$A:$A,OB!$A:$A,0)),"")=0,"",IFERROR(INDEX(OB!$K:$K,MATCH('STARTUP DRIVE REPORT'!$A:$A,OB!$A:$A,0)),"")) | M94: =IFERROR(AVERAGE(E94:I94),"") | N94: =IF(OR(J94="",K94=""),"",J94/(K94*5)) | O94: =IFERROR((IF(W94="4TOL",((7200/M94)*87%),IF(W94="SNLS",((7200/M94)*88%),IF(W94="KANSAI",((7200/M94)*85%),IF(W94="3TFLCB",((7200/M94)*87%),IF(W94="2TFLFB",((7200/M94)*87%),IF(W94="2TFLCB",((7200/M94)*87%),IF(W94="BH",((7200/M94)*90%),IF(W94="BT",((7200/M94)*90%),((7200/M94)*92%)))))))))),"") | P94: =IFERROR(O94/N94,"") | Q94: =IFERROR(K94*L94/J94,"") | R94: =IFERROR(IF((Q94>P94),"DATA ERROR",IF((P94-Q94)>5%,"CHECK FEEDING","")),"") | W94: =IF(IFERROR(INDEX(OB!$G:$G,MATCH('STARTUP DRIVE REPORT'!$A:$A,OB!$A:$A,0)),"")=0,"",IFERROR(INDEX(OB!$G:$G,MATCH('STARTUP DRIVE REPORT'!$A:$A,OB!$A:$A,0)),"")) | AQ94: 2

Sheet STARTUP LOSS
A1: STYLE STARTUP LOSS REPORT | N1: STYLE STARTUP LOSS SUMMARY
A3: S.NO | B3: OPERATION | C3: M/C | D3: OPERATION SET DATE | E3: OPERATION SET START TIME | F3: OPERATION SET END TIME | G3: TIME TAKEN | H3: LOST TIME (IF ANY)(in min) | I3: DEPARTMENT | J3: REMARKS | N3: STYLE | O3: =OB!E2&" "&OB!C2 -> ADIDAS S2554MESS651WV | P3: TOTAL TIME TAKEN FOR CHANGEOVER COMPLETION (IN MIN) | Q3: =SUM(G4:G93) -> 155
A4: 1 | B4: =IFERROR(IF((INDEX(OB!$B:$B,MATCH('STARTUP LOSS'!$A:$A,OB!$A:$A,0)))=0,"",(INDEX(OB!$B:$B,MATCH('STARTUP LOSS'!$A:$A,OB!$A:$A,0)))),"") -> ATTACH THREE STRIPE | C4: =IFERROR(IF((INDEX(OB!$G:$G,MATCH('STARTUP LOSS'!$A:$A,OB!$A:$A,0)))=0,"",(INDEX(OB!$G:$G,MATCH('STARTUP LOSS'!$A:$A,OB!$A:$A,0)))),"") -> KANSAI | D4: 45894 | E4: 0.375 | F4: 0.41666667 | G4: =IFERROR(IF(AND(E4<>"",F4<>""),(F4-E4)*1440,""),"") -> 60 | H4: 40 | I4: TRIMS | L4: TRIMS
A5: =+A4+1 -> 2 | B5: =IFERROR(IF((INDEX(OB!$B:$B,MATCH('STARTUP LOSS'!$A:$A,OB!$A:$A,0)))=0,"",(INDEX(OB!$B:$B,MATCH('STARTUP LOSS'!$A:$A,OB!$A:$A,0)))),"") -> CHECK & TRIM THREE STRIPE | C5: =IFERROR(IF((INDEX(OB!$G:$G,MATCH('STARTUP LOSS'!$A:$A,OB!$A:$A,0)))=0,"",(INDEX(OB!$G:$G,MATCH('STARTUP LOSS'!$A:$A,OB!$A:$A,0)))),"") -> TABLE | D5: 45894 | E5: 0.41666667 | F5: 0.48263889 | G5: =IFERROR(IF(AND(E5<>"",F5<>""),(F5-E5)*1440,""),"") -> 95 | H5: 20 | I5: CUTTING | L5: CUTTING | N5: DATE | O5: =OB!I90 -> 45955 | P5: TOTAL TIME TAKEN FOR CHANGEOVER COMPLETION (IN HRS) | Q5: =+Q3/60 -> 2.5833333
A6: =+A5+1 -> 3 | B6: =IFERROR(IF((INDEX(OB!$B:$B,MATCH('STARTUP LOSS'!$A:$A,OB!$A:$A,0)))=0,"",(INDEX(OB!$B:$B,MATCH('STARTUP LOSS'!$A:$A,OB!$A:$A,0)))),"") -> JOIN BACK RISE | C6: =IFERROR(IF((INDEX(OB!$G:$G,MATCH('STARTUP LOSS'!$A:$A,OB!$A:$A,0)))=0,"",(INDEX(OB!$G:$G,MATCH('STARTUP LOSS'!$A:$A,OB!$A:$A,0)))),"") -> OL4T | G6: =IFERROR(IF(AND(E6<>"",F6<>""),(F6-E6)*1440,""),"") | L6: PRODUCTION
A7: =+A6+1 -> 4 | B7: =IFERROR(IF((INDEX(OB!$B:$B,MATCH('STARTUP LOSS'!$A:$A,OB!$A:$A,0)))=0,"",(INDEX(OB!$B:$B,MATCH('STARTUP LOSS'!$A:$A,OB!$A:$A,0)))),"") -> FUSE & CREASE BOTTOM FOR ZIPPER | C7: =IFERROR(IF((INDEX(OB!$G:$G,MATCH('STARTUP LOSS'!$A:$A,OB!$A:$A,0)))=0,"",(INDEX(OB!$G:$G,MATCH('STARTUP LOSS'!$A:$A,OB!$A:$A,0)))),"") -> IRON TABLE | G7: =IFERROR(IF(AND(E7<>"",F7<>""),(F7-E7)*1440,""),"") | L7: MERCHANDISER | N7: TOTAL LOST TIME (IN MIN) | O7: =SUM(H4:H93) -> 60 | P7: IE | Q7: =OB!M4 -> SHANAKA
A8: =+A7+1 -> 5 | B8: =IFERROR(IF((INDEX(OB!$B:$B,MATCH('STARTUP LOSS'!$A:$A,OB!$A:$A,0)))=0,"",(INDEX(OB!$B:$B,MATCH('STARTUP LOSS'!$A:$A,OB!$A:$A,0)))),"") -> SERGE BOTTOM FOR LEG ZIPPER*2 | C8: =IFERROR(IF((INDEX(OB!$G:$G,MATCH('STARTUP LOSS'!$A:$A,OB!$A:$A,0)))=0,"",(INDEX(OB!$G:$G,MATCH('STARTUP LOSS'!$A:$A,OB!$A:$A,0)))),"") -> OL4T | G8: =IFERROR(IF(AND(E8<>"",F8<>""),(F8-E8)*1440,""),"") | L8: IE
A9: =+A8+1 -> 6 | B9: =IFERROR(IF((INDEX(OB!$B:$B,MATCH('STARTUP LOSS'!$A:$A,OB!$A:$A,0)))=0,"",(INDEX(OB!$B:$B,MATCH('STARTUP LOSS'!$A:$A,OB!$A:$A,0)))),"") | C9: =IFERROR(IF((INDEX(OB!$G:$G,MATCH('STARTUP LOSS'!$A:$A,OB!$A:$A,0)))=0,"",(INDEX(OB!$G:$G,MATCH('STARTUP LOSS'!$A:$A,OB!$A:$A,0)))),"") | G9: =IFERROR(IF(AND(E9<>"",F9<>""),(F9-E9)*1440,""),"") | L9: TECHNICAL | N9: TOTAL TIME TAKEN PER OPERATION (IN MIN | O9: =$Q$3/COUNTA(B4:B93) -> 1.7222222 | P9: SUPERVISOR | Q9: =OB!M3 -> NAZIR
A10: =+A9+1 -> 7 | B10: =IFERROR(IF((INDEX(OB!$B:$B,MATCH('STARTUP LOSS'!$A:$A,OB!$A:$A,0)))=0,"",(INDEX(OB!$B:$B,MATCH('STARTUP LOSS'!$A:$A,OB!$A:$A,0)))),"") | C10: =IFERROR(IF((INDEX(OB!$G:$G,MATCH('STARTUP LOSS'!$A:$A,OB!$A:$A,0)))=0,"",(INDEX(OB!$G:$G,MATCH('STARTUP LOSS'!$A:$A,OB!$A:$A,0)))),"") | G10: =IFERROR(IF(AND(E10<>"",F10<>""),(F10-E10)*1440,""),"") | L10: MAINTENANCE
A11: =+A10+1 -> 8 | B11: =IFERROR(IF((INDEX(OB!$B:$B,MATCH('STARTUP LOSS'!$A:$A,OB!$A:$A,0)))=0,"",(INDEX(OB!$B:$B,MATCH('STARTUP LOSS'!$A:$A,OB!$A:$A,0)))),"") | C11: =IFERROR(IF((INDEX(OB!$G:$G,MATCH('STARTUP LOSS'!$A:$A,OB!$A:$A,0)))=0,"",(INDEX(OB!$G:$G,MATCH('STARTUP LOSS'!$A:$A,OB!$A:$A,0)))),"") | G11: =IFERROR(IF(AND(E11<>"",F11<>""),(F11-E11)*1440,""),"") | N11: LOSS TIME BREAKDOWN
A12: =+A11+1 -> 9 | B12: =IFERROR(IF((INDEX(OB!$B:$B,MATCH('STARTUP LOSS'!$A:$A,OB!$A:$A,0)))=0,"",(INDEX(OB!$B:$B,MATCH('STARTUP LOSS'!$A:$A,OB!$A:$A,0)))),"") | C12: =IFERROR(IF((INDEX(OB!$G:$G,MATCH('STARTUP LOSS'!$A:$A,OB!$A:$A,0)))=0,"",(INDEX(OB!$G:$G,MATCH('STARTUP LOSS'!$A:$A,OB!$A:$A,0)))),"") | G12: =IFERROR(IF(AND(E12<>"",F12<>""),(F12-E12)*1440,""),"")
A13: =+A12+1 -> 10 | B13: =IFERROR(IF((INDEX(OB!$B:$B,MATCH('STARTUP LOSS'!$A:$A,OB!$A:$A,0)))=0,"",(INDEX(OB!$B:$B,MATCH('STARTUP LOSS'!$A:$A,OB!$A:$A,0)))),"") | C13: =IFERROR(IF((INDEX(OB!$G:$G,MATCH('STARTUP LOSS'!$A:$A,OB!$A:$A,0)))=0,"",(INDEX(OB!$G:$G,MATCH('STARTUP LOSS'!$A:$A,OB!$A:$A,0)))),"") | G13: =IFERROR(IF(AND(E13<>"",F13<>""),(F13-E13)*1440,""),"") | N13: DEPARTMENT | O13: LOSS TIME (IN MIN) | P13: REVENUE LOSS | Q13: LOSS TIME %
A14: =+A13+1 -> 11 | B14: =IFERROR(IF((INDEX(OB!$B:$B,MATCH('STARTUP LOSS'!$A:$A,OB!$A:$A,0)))=0,"",(INDEX(OB!$B:$B,MATCH('STARTUP LOSS'!$A:$A,OB!$A:$A,0)))),"") | C14: =IFERROR(IF((INDEX(OB!$G:$G,MATCH('STARTUP LOSS'!$A:$A,OB!$A:$A,0)))=0,"",(INDEX(OB!$G:$G,MATCH('STARTUP LOSS'!$A:$A,OB!$A:$A,0)))),"") | G14: =IFERROR(IF(AND(E14<>"",F14<>""),(F14-E14)*1440,""),"") | N14: TRIMS | O14: =IFERROR(IF((SUMIF($I$4:$I$93,$N14,$H$4:$H$93))=0,"",(SUMIF($I$4:$I$93,$N14,$H$4:$H$93))),"") -> 40 | P14: =IFERROR(Table2[[#This Row],[LOSS TIME (IN MIN)]]*0.11*OB!$C$94,"") -> 238.7 | Q14: =IFERROR(O14/$O$21,"") -> 0.66666667
A15: =+A14+1 -> 12 | B15: =IFERROR(IF((INDEX(OB!$B:$B,MATCH('STARTUP LOSS'!$A:$A,OB!$A:$A,0)))=0,"",(INDEX(OB!$B:$B,MATCH('STARTUP LOSS'!$A:$A,OB!$A:$A,0)))),"") | C15: =IFERROR(IF((INDEX(OB!$G:$G,MATCH('STARTUP LOSS'!$A:$A,OB!$A:$A,0)))=0,"",(INDEX(OB!$G:$G,MATCH('STARTUP LOSS'!$A:$A,OB!$A:$A,0)))),"") | G15: =IFERROR(IF(AND(E15<>"",F15<>""),(F15-E15)*1440,""),"") | N15: CUTTING | O15: =IFERROR(IF((SUMIF($I$4:$I$93,$N15,$H$4:$H$93))=0,"",(SUMIF($I$4:$I$93,$N15,$H$4:$H$93))),"") -> 20 | P15: =IFERROR(Table2[[#This Row],[LOSS TIME (IN MIN)]]*0.11*OB!$C$94,"") -> 119.35 | Q15: =IFERROR(O15/$O$21,"") -> 0.33333333
A16: =+A15+1 -> 13 | B16: =IFERROR(IF((INDEX(OB!$B:$B,MATCH('STARTUP LOSS'!$A:$A,OB!$A:$A,0)))=0,"",(INDEX(OB!$B:$B,MATCH('STARTUP LOSS'!$A:$A,OB!$A:$A,0)))),"") -> FUSE & CREASE POCKET MOUTH | C16: =IFERROR(IF((INDEX(OB!$G:$G,MATCH('STARTUP LOSS'!$A:$A,OB!$A:$A,0)))=0,"",(INDEX(OB!$G:$G,MATCH('STARTUP LOSS'!$A:$A,OB!$A:$A,0)))),"") -> IRON TABLE | G16: =IFERROR(IF(AND(E16<>"",F16<>""),(F16-E16)*1440,""),"") | N16: PRODUCTION | O16: =IFERROR(IF((SUMIF($I$4:$I$93,$N16,$H$4:$H$93))=0,"",(SUMIF($I$4:$I$93,$N16,$H$4:$H$93))),"") | P16: =IFERROR(Table2[[#This Row],[LOSS TIME (IN MIN)]]*0.11*OB!$C$94,"") | Q16: =IFERROR(O16/$O$21,"")
A17: =+A16+1 -> 14 | B17: =IFERROR(IF((INDEX(OB!$B:$B,MATCH('STARTUP LOSS'!$A:$A,OB!$A:$A,0)))=0,"",(INDEX(OB!$B:$B,MATCH('STARTUP LOSS'!$A:$A,OB!$A:$A,0)))),"") -> ATTACH FACING TO POCKET BAG*2 | C17: =IFERROR(IF((INDEX(OB!$G:$G,MATCH('STARTUP LOSS'!$A:$A,OB!$A:$A,0)))=0,"",(INDEX(OB!$G:$G,MATCH('STARTUP LOSS'!$A:$A,OB!$A:$A,0)))),"") -> SNLS | G17: =IFERROR(IF(AND(E17<>"",F17<>""),(F17-E17)*1440,""),"") | N17: MERCHANDISER | O17: =IFERROR(IF((SUMIF($I$4:$I$93,$N17,$H$4:$H$93))=0,"",(SUMIF($I$4:$I$93,$N17,$H$4:$H$93))),"") | P17: =IFERROR(Table2[[#This Row],[LOSS TIME (IN MIN)]]*0.11*OB!$C$94,"") | Q17: =IFERROR(O17/$O$21,"")
A18: =+A17+1 -> 15 | B18: =IFERROR(IF((INDEX(OB!$B:$B,MATCH('STARTUP LOSS'!$A:$A,OB!$A:$A,0)))=0,"",(INDEX(OB!$B:$B,MATCH('STARTUP LOSS'!$A:$A,OB!$A:$A,0)))),"") -> ATTACH POCKET BAG TO FRONT | C18: =IFERROR(IF((INDEX(OB!$G:$G,MATCH('STARTUP LOSS'!$A:$A,OB!$A:$A,0)))=0,"",(INDEX(OB!$G:$G,MATCH('STARTUP LOSS'!$A:$A,OB!$A:$A,0)))),"") -> SNLS | G18: =IFERROR(IF(AND(E18<>"",F18<>""),(F18-E18)*1440,""),"") | N18: IE | O18: =IFERROR(IF((SUMIF($I$4:$I$93,$N18,$H$4:$H$93))=0,"",(SUMIF($I$4:$I$93,$N18,$H$4:$H$93))),"") | P18: =IFERROR(Table2[[#This Row],[LOSS TIME (IN MIN)]]*0.11*OB!$C$94,"") | Q18: =IFERROR(O18/$O$21,"")
A19: =+A18+1 -> 16 | B19: =IFERROR(IF((INDEX(OB!$B:$B,MATCH('STARTUP LOSS'!$A:$A,OB!$A:$A,0)))=0,"",(INDEX(OB!$B:$B,MATCH('STARTUP LOSS'!$A:$A,OB!$A:$A,0)))),"") -> SHADOW STITCH POCKET MOUTH & CUT NOTCH | C19: =IFERROR(IF((INDEX(OB!$G:$G,MATCH('STARTUP LOSS'!$A:$A,OB!$A:$A,0)))=0,"",(INDEX(OB!$G:$G,MATCH('STARTUP LOSS'!$A:$A,OB!$A:$A,0)))),"") -> SNLS | G19: =IFERROR(IF(AND(E19<>"",F19<>""),(F19-E19)*1440,""),"") | N19: TECHNICAL | O19: =IFERROR(IF((SUMIF($I$4:$I$93,$N19,$H$4:$H$93))=0,"",(SUMIF($I$4:$I$93,$N19,$H$4:$H$93))),"") | P19: =IFERROR(Table2[[#This Row],[LOSS TIME (IN MIN)]]*0.11*OB!$C$94,"") | Q19: =IFERROR(O19/$O$21,"")
A20: =+A19+1 -> 17 | B20: =IFERROR(IF((INDEX(OB!$B:$B,MATCH('STARTUP LOSS'!$A:$A,OB!$A:$A,0)))=0,"",(INDEX(OB!$B:$B,MATCH('STARTUP LOSS'!$A:$A,OB!$A:$A,0)))),"") -> TACK INNER POCKET BAG | C20: =IFERROR(IF((INDEX(OB!$G:$G,MATCH('STARTUP LOSS'!$A:$A,OB!$A:$A,0)))=0,"",(INDEX(OB!$G:$G,MATCH('STARTUP LOSS'!$A:$A,OB!$A:$A,0)))),"") -> SNLS | G20: =IFERROR(IF(AND(E20<>"",F20<>""),(F20-E20)*1440,""),"") | N20: MAINTENANCE | O20: =IFERROR(IF((SUMIF($I$4:$I$93,$N20,$H$4:$H$93))=0,"",(SUMIF($I$4:$I$93,$N20,$H$4:$H$93))),"") | P20: =IFERROR(Table2[[#This Row],[LOSS TIME (IN MIN)]]*0.11*OB!$C$94,"") | Q20: =IFERROR(O20/$O$21,"")
A21: =+A20+1 -> 18 | B21: =IFERROR(IF((INDEX(OB!$B:$B,MATCH('STARTUP LOSS'!$A:$A,OB!$A:$A,0)))=0,"",(INDEX(OB!$B:$B,MATCH('STARTUP LOSS'!$A:$A,OB!$A:$A,0)))),"") -> CLOSE POCKET BAG | C21: =IFERROR(IF((INDEX(OB!$G:$G,MATCH('STARTUP LOSS'!$A:$A,OB!$A:$A,0)))=0,"",(INDEX(OB!$G:$G,MATCH('STARTUP LOSS'!$A:$A,OB!$A:$A,0)))),"") -> OL4T | G21: =IFERROR(IF(AND(E21<>"",F21<>""),(F21-E21)*1440,""),"") | N21: TOTAL | O21: =SUM(O14:O20) -> 60 | P21: =SUM(P14:P20) -> 358.05 | Q21: =SUM(Q14:Q20) -> 1
A22: =+A21+1 -> 19 | B22: =IFERROR(IF((INDEX(OB!$B:$B,MATCH('STARTUP LOSS'!$A:$A,OB!$A:$A,0)))=0,"",(INDEX(OB!$B:$B,MATCH('STARTUP LOSS'!$A:$A,OB!$A:$A,0)))),"") -> POCKET BAG SIDE WAIST TACK | C22: =IFERROR(IF((INDEX(OB!$G:$G,MATCH('STARTUP LOSS'!$A:$A,OB!$A:$A,0)))=0,"",(INDEX(OB!$G:$G,MATCH('STARTUP LOSS'!$A:$A,OB!$A:$A,0)))),"") -> SNLS | G22: =IFERROR(IF(AND(E22<>"",F22<>""),(F22-E22)*1440,""),"") | N22: LOSS TIME CHART
A23: =+A22+1 -> 20 | B23: =IFERROR(IF((INDEX(OB!$B:$B,MATCH('STARTUP LOSS'!$A:$A,OB!$A:$A,0)))=0,"",(INDEX(OB!$B:$B,MATCH('STARTUP LOSS'!$A:$A,OB!$A:$A,0)))),"") -> BARTACK POCKET*6 | C23: =IFERROR(IF((INDEX(OB!$G:$G,MATCH('STARTUP LOSS'!$A:$A,OB!$A:$A,0)))=0,"",(INDEX(OB!$G:$G,MATCH('STARTUP LOSS'!$A:$A,OB!$A:$A,0)))),"") -> BRTK | G23: =IFERROR(IF(AND(E23<>"",F23<>""),(F23-E23)*1440,""),"")
A24: =+A23+1 -> 21 | B24: =IFERROR(IF((INDEX(OB!$B:$B,MATCH('STARTUP LOSS'!$A:$A,OB!$A:$A,0)))=0,"",(INDEX(OB!$B:$B,MATCH('STARTUP LOSS'!$A:$A,OB!$A:$A,0)))),"") -> JOIN FRONT RISE | C24: =IFERROR(IF((INDEX(OB!$G:$G,MATCH('STARTUP LOSS'!$A:$A,OB!$A:$A,0)))=0,"",(INDEX(OB!$G:$G,MATCH('STARTUP LOSS'!$A:$A,OB!$A:$A,0)))),"") -> OL4T | G24: =IFERROR(IF(AND(E24<>"",F24<>""),(F24-E24)*1440,""),"")
A25: =+A24+1 -> 22 | B25: =IFERROR(IF((INDEX(OB!$B:$B,MATCH('STARTUP LOSS'!$A:$A,OB!$A:$A,0)))=0,"",(INDEX(OB!$B:$B,MATCH('STARTUP LOSS'!$A:$A,OB!$A:$A,0)))),"") | C25: =IFERROR(IF((INDEX(OB!$G:$G,MATCH('STARTUP LOSS'!$A:$A,OB!$A:$A,0)))=0,"",(INDEX(OB!$G:$G,MATCH('STARTUP LOSS'!$A:$A,OB!$A:$A,0)))),"") | G25: =IFERROR(IF(AND(E25<>"",F25<>""),(F25-E25)*1440,""),"")
A26: =+A25+1 -> 23 | B26: =IFERROR(IF((INDEX(OB!$B:$B,MATCH('STARTUP LOSS'!$A:$A,OB!$A:$A,0)))=0,"",(INDEX(OB!$B:$B,MATCH('STARTUP LOSS'!$A:$A,OB!$A:$A,0)))),"") | C26: =IFERROR(IF((INDEX(OB!$G:$G,MATCH('STARTUP LOSS'!$A:$A,OB!$A:$A,0)))=0,"",(INDEX(OB!$G:$G,MATCH('STARTUP LOSS'!$A:$A,OB!$A:$A,0)))),"") | G26: =IFERROR(IF(AND(E26<>"",F26<>""),(F26-E26)*1440,""),"")
A27: =+A26+1 -> 24 | B27: =IFERROR(IF((INDEX(OB!$B:$B,MATCH('STARTUP LOSS'!$A:$A,OB!$A:$A,0)))=0,"",(INDEX(OB!$B:$B,MATCH('STARTUP LOSS'!$A:$A,OB!$A:$A,0)))),"") | C27: =IFERROR(IF((INDEX(OB!$G:$G,MATCH('STARTUP LOSS'!$A:$A,OB!$A:$A,0)))=0,"",(INDEX(OB!$G:$G,MATCH('STARTUP LOSS'!$A:$A,OB!$A:$A,0)))),"") | G27: =IFERROR(IF(AND(E27<>"",F27<>""),(F27-E27)*1440,""),"")
A28: =+A27+1 -> 25 | B28: =IFERROR(IF((INDEX(OB!$B:$B,MATCH('STARTUP LOSS'!$A:$A,OB!$A:$A,0)))=0,"",(INDEX(OB!$B:$B,MATCH('STARTUP LOSS'!$A:$A,OB!$A:$A,0)))),"") | C28: =IFERROR(IF((INDEX(OB!$G:$G,MATCH('STARTUP LOSS'!$A:$A,OB!$A:$A,0)))=0,"",(INDEX(OB!$G:$G,MATCH('STARTUP LOSS'!$A:$A,OB!$A:$A,0)))),"") | G28: =IFERROR(IF(AND(E28<>"",F28<>""),(F28-E28)*1440,""),"")
A29: =+A28+1 -> 26 | B29: =IFERROR(IF((INDEX(OB!$B:$B,MATCH('STARTUP LOSS'!$A:$A,OB!$A:$A,0)))=0,"",(INDEX(OB!$B:$B,MATCH('STARTUP LOSS'!$A:$A,OB!$A:$A,0)))),"") | C29: =IFERROR(IF((INDEX(OB!$G:$G,MATCH('STARTUP LOSS'!$A:$A,OB!$A:$A,0)))=0,"",(INDEX(OB!$G:$G,MATCH('STARTUP LOSS'!$A:$A,OB!$A:$A,0)))),"") | G29: =IFERROR(IF(AND(E29<>"",F29<>""),(F29-E29)*1440,""),"")
A30: =+A29+1 -> 27 | B30: =IFERROR(IF((INDEX(OB!$B:$B,MATCH('STARTUP LOSS'!$A:$A,OB!$A:$A,0)))=0,"",(INDEX(OB!$B:$B,MATCH('STARTUP LOSS'!$A:$A,OB!$A:$A,0)))),"") | C30: =IFERROR(IF((INDEX(OB!$G:$G,MATCH('STARTUP LOSS'!$A:$A,OB!$A:$A,0)))=0,"",(INDEX(OB!$G:$G,MATCH('STARTUP LOSS'!$A:$A,OB!$A:$A,0)))),"") | G30: =IFERROR(IF(AND(E30<>"",F30<>""),(F30-E30)*1440,""),"")
A31: =+A30+1 -> 28 | B31: =IFERROR(IF((INDEX(OB!$B:$B,MATCH('STARTUP LOSS'!$A:$A,OB!$A:$A,0)))=0,"",(INDEX(OB!$B:$B,MATCH('STARTUP LOSS'!$A:$A,OB!$A:$A,0)))),"") | C31: =IFERROR(IF((INDEX(OB!$G:$G,MATCH('STARTUP LOSS'!$A:$A,OB!$A:$A,0)))=0,"",(INDEX(OB!$G:$G,MATCH('STARTUP LOSS'!$A:$A,OB!$A:$A,0)))),"") | G31: =IFERROR(IF(AND(E31<>"",F31<>""),(F31-E31)*1440,""),"")
A32: =+A31+1 -> 29 | B32: =IFERROR(IF((INDEX(OB!$B:$B,MATCH('STARTUP LOSS'!$A:$A,OB!$A:$A,0)))=0,"",(INDEX(OB!$B:$B,MATCH('STARTUP LOSS'!$A:$A,OB!$A:$A,0)))),"") | C32: =IFERROR(IF((INDEX(OB!$G:$G,MATCH('STARTUP LOSS'!$A:$A,OB!$A:$A,0)))=0,"",(INDEX(OB!$G:$G,MATCH('STARTUP LOSS'!$A:$A,OB!$A:$A,0)))),"") | G32: =IFERROR(IF(AND(E32<>"",F32<>""),(F32-E32)*1440,""),"")
A33: =+A32+1 -> 30 | B33: =IFERROR(IF((INDEX(OB!$B:$B,MATCH('STARTUP LOSS'!$A:$A,OB!$A:$A,0)))=0,"",(INDEX(OB!$B:$B,MATCH('STARTUP LOSS'!$A:$A,OB!$A:$A,0)))),"") | C33: =IFERROR(IF((INDEX(OB!$G:$G,MATCH('STARTUP LOSS'!$A:$A,OB!$A:$A,0)))=0,"",(INDEX(OB!$G:$G,MATCH('STARTUP LOSS'!$A:$A,OB!$A:$A,0)))),"") | G33: =IFERROR(IF(AND(E33<>"",F33<>""),(F33-E33)*1440,""),"")
A34: =+A33+1 -> 31 | B34: =IFERROR(IF((INDEX(OB!$B:$B,MATCH('STARTUP LOSS'!$A:$A,OB!$A:$A,0)))=0,"",(INDEX(OB!$B:$B,MATCH('STARTUP LOSS'!$A:$A,OB!$A:$A,0)))),"") -> TACK FRONT & BACK AT INSEAM FOR LEG ZIPPER | C34: =IFERROR(IF((INDEX(OB!$G:$G,MATCH('STARTUP LOSS'!$A:$A,OB!$A:$A,0)))=0,"",(INDEX(OB!$G:$G,MATCH('STARTUP LOSS'!$A:$A,OB!$A:$A,0)))),"") -> SNLS | G34: =IFERROR(IF(AND(E34<>"",F34<>""),(F34-E34)*1440,""),"")
... A93: =+A92+1 -> 90 | B93: =IFERROR(IF((INDEX(OB!$B:$B,MATCH('STARTUP LOSS'!$A:$A,OB!$A:$A,0)))=0,"",(INDEX(OB!$B:$B,MATCH('STARTUP LOSS'!$A:$A,OB!$A:$A,0)))),"") | C93: =IFERROR(IF((INDEX(OB!$G:$G,MATCH('STARTUP LOSS'!$A:$A,OB!$A:$A,0)))=0,"",(INDEX(OB!$G:$G,MATCH('STARTUP LOSS'!$A:$A,OB!$A:$A,0)))),"") | G93: =IFERROR(IF(AND(E93<>"",F93<>""),(F93-E93)*1440,""),"")

Sheet SDR INSIGHT 1.0
A7: HIGHEST CAPACITY
A9: SL NO | B9: OPERATION | C9: CAPACITY | D9: OPERATOR | E9: OPERATOR ID
A10: 1 | B10: {=INDEX('STARTUP DRIVE REPORT'!$B$5:$B$94,MATCH('SDR INSIGHT 1.0'!C10,'STARTUP DRIVE REPORT'!$P$5:$P$16,0))} -> #NUM! | C10: {=LARGE('STARTUP DRIVE REPORT'!$P$5:$P$16,1)} -> #NUM! | D10: {=INDEX('STARTUP DRIVE REPORT'!$C$5:$C$94,MATCH('SDR INSIGHT 1.0'!C10,'STARTUP DRIVE REPORT'!$P$5:$P$16,0))} -> #NUM! | E10: {=INDEX('STARTUP DRIVE REPORT'!$D$5:$D$94,MATCH('SDR INSIGHT 1.0'!C10,'STARTUP DRIVE REPORT'!$P$5:$P$16,0))} -> #NUM!
A11: 2 | B11: {=INDEX('STARTUP DRIVE REPORT'!$B$5:$B$94,MATCH('SDR INSIGHT 1.0'!C11,'STARTUP DRIVE REPORT'!$P$5:$P$16,0))} -> #NUM! | C11: {=LARGE('STARTUP DRIVE REPORT'!$P$5:$P$16,2)} -> #NUM! | D11: {=INDEX('STARTUP DRIVE REPORT'!$C$5:$C$94,MATCH('SDR INSIGHT 1.0'!C11,'STARTUP DRIVE REPORT'!$P$5:$P$16,0))} -> #NUM! | E11: {=INDEX('STARTUP DRIVE REPORT'!$D$5:$D$94,MATCH('SDR INSIGHT 1.0'!C11,'STARTUP DRIVE REPORT'!$P$5:$P$16,0))} -> #NUM!
A12: 3 | B12: {=INDEX('STARTUP DRIVE REPORT'!$B$5:$B$94,MATCH('SDR INSIGHT 1.0'!C12,'STARTUP DRIVE REPORT'!$P$5:$P$16,0))} -> #NUM! | C12: {=LARGE('STARTUP DRIVE REPORT'!$P$5:$P$16,3)} -> #NUM! | D12: {=INDEX('STARTUP DRIVE REPORT'!$C$5:$C$94,MATCH('SDR INSIGHT 1.0'!C12,'STARTUP DRIVE REPORT'!$P$5:$P$16,0))} -> #NUM! | E12: {=INDEX('STARTUP DRIVE REPORT'!$D$5:$D$94,MATCH('SDR INSIGHT 1.0'!C12,'STARTUP DRIVE REPORT'!$P$5:$P$16,0))} -> #NUM!
A13: 4 | B13: {=INDEX('STARTUP DRIVE REPORT'!$B$5:$B$94,MATCH('SDR INSIGHT 1.0'!C13,'STARTUP DRIVE REPORT'!$P$5:$P$16,0))} -> #NUM! | C13: {=LARGE('STARTUP DRIVE REPORT'!$P$5:$P$16,4)} -> #NUM! | D13: {=INDEX('STARTUP DRIVE REPORT'!$C$5:$C$94,MATCH('SDR INSIGHT 1.0'!C13,'STARTUP DRIVE REPORT'!$P$5:$P$16,0))} -> #NUM! | E13: {=INDEX('STARTUP DRIVE REPORT'!$D$5:$D$94,MATCH('SDR INSIGHT 1.0'!C13,'STARTUP DRIVE REPORT'!$P$5:$P$16,0))} -> #NUM!
A14: 5 | B14: {=INDEX('STARTUP DRIVE REPORT'!$B$5:$B$94,MATCH('SDR INSIGHT 1.0'!C14,'STARTUP DRIVE REPORT'!$P$5:$P$16,0))} -> #NUM! | C14: {=LARGE('STARTUP DRIVE REPORT'!$P$5:$P$16,5)} -> #NUM! | D14: {=INDEX('STARTUP DRIVE REPORT'!$C$5:$C$94,MATCH('SDR INSIGHT 1.0'!C14,'STARTUP DRIVE REPORT'!$P$5:$P$16,0))} -> #NUM! | E14: {=INDEX('STARTUP DRIVE REPORT'!$D$5:$D$94,MATCH('SDR INSIGHT 1.0'!C14,'STARTUP DRIVE REPORT'!$P$5:$P$16,0))} -> #NUM!
A24: LOWEST CAPACITY
A26: SL NO | B26: OPERATION | C26: CAPACITY | D26: OPERATOR | E26: OPERATOR ID
A27: 1 | B27: {=INDEX('STARTUP DRIVE REPORT'!$B$5:$B$94,MATCH('SDR INSIGHT 1.0'!C27,'STARTUP DRIVE REPORT'!$P$5:$P$16,0))} -> #NUM! | C27: {=SMALL('STARTUP DRIVE REPORT'!$P$5:$P$16,1)} -> #NUM! | D27: {=INDEX('STARTUP DRIVE REPORT'!$C$5:$C$94,MATCH('SDR INSIGHT 1.0'!C27,'STARTUP DRIVE REPORT'!$P$5:$P$16,0))} -> #NUM! | E27: {=INDEX('STARTUP DRIVE REPORT'!$D$5:$D$94,MATCH('SDR INSIGHT 1.0'!C27,'STARTUP DRIVE REPORT'!$P$5:$P$16,0))} -> #NUM!
A28: 2 | B28: {=INDEX('STARTUP DRIVE REPORT'!$B$5:$B$94,MATCH('SDR INSIGHT 1.0'!C28,'STARTUP DRIVE REPORT'!$P$5:$P$16,0))} -> #NUM! | C28: {=SMALL('STARTUP DRIVE REPORT'!$P$5:$P$16,2)} -> #NUM! | D28: {=INDEX('STARTUP DRIVE REPORT'!$C$5:$C$94,MATCH('SDR INSIGHT 1.0'!C28,'STARTUP DRIVE REPORT'!$P$5:$P$16,0))} -> #NUM! | E28: {=INDEX('STARTUP DRIVE REPORT'!$D$5:$D$94,MATCH('SDR INSIGHT 1.0'!C28,'STARTUP DRIVE REPORT'!$P$5:$P$16,0))} -> #NUM!
A29: 3 | B29: {=INDEX('STARTUP DRIVE REPORT'!$B$5:$B$94,MATCH('SDR INSIGHT 1.0'!C29,'STARTUP DRIVE REPORT'!$P$5:$P$16,0))} -> #NUM! | C29: {=SMALL('STARTUP DRIVE REPORT'!$P$5:$P$16,3)} -> #NUM! | D29: {=INDEX('STARTUP DRIVE REPORT'!$C$5:$C$94,MATCH('SDR INSIGHT 1.0'!C29,'STARTUP DRIVE REPORT'!$P$5:$P$16,0))} -> #NUM! | E29: {=INDEX('STARTUP DRIVE REPORT'!$D$5:$D$94,MATCH('SDR INSIGHT 1.0'!C29,'STARTUP DRIVE REPORT'!$P$5:$P$16,0))} -> #NUM!
A30: 4 | B30: {=INDEX('STARTUP DRIVE REPORT'!$B$5:$B$94,MATCH('SDR INSIGHT 1.0'!C30,'STARTUP DRIVE REPORT'!$P$5:$P$16,0))} -> #NUM! | C30: {=SMALL('STARTUP DRIVE REPORT'!$P$5:$P$16,4)} -> #NUM! | D30: {=INDEX('STARTUP DRIVE REPORT'!$C$5:$C$94,MATCH('SDR INSIGHT 1.0'!C30,'STARTUP DRIVE REPORT'!$P$5:$P$16,0))} -> #NUM! | E30: {=INDEX('STARTUP DRIVE REPORT'!$D$5:$D$94,MATCH('SDR INSIGHT 1.0'!C30,'STARTUP DRIVE REPORT'!$P$5:$P$16,0))} -> #NUM!
A31: 5 | B31: {=INDEX('STARTUP DRIVE REPORT'!$B$5:$B$94,MATCH('SDR INSIGHT 1.0'!C31,'STARTUP DRIVE REPORT'!$P$5:$P$16,0))} -> #NUM! | C31: {=SMALL('STARTUP DRIVE REPORT'!$P$5:$P$16,5)} -> #NUM! | D31: {=INDEX('STARTUP DRIVE REPORT'!$C$5:$C$94,MATCH('SDR INSIGHT 1.0'!C31,'STARTUP DRIVE REPORT'!$P$5:$P$16,0))} -> #NUM! | E31: {=INDEX('STARTUP DRIVE REPORT'!$D$5:$D$94,MATCH('SDR INSIGHT 1.0'!C31,'STARTUP DRIVE REPORT'!$P$5:$P$16,0))} -> #NUM!

Sheet SDR INSIGHT 2.0
B1: MACHINE VERIFICATION | G1: PROCESS EXPERIENCE | L1: QUALITY DEFECTS
A3: Sl No | B3: Operation | C3: Operator Name | D3: Operator Id | F3: Sl No | G3: Operation | H3: Operator Name | I3: Operator Id | K3: Sl No | L3: Operation | M3: Operator Name | N3: Operator Id
A4: 1 | B4: {=IFERROR(INDEX('STARTUP DRIVE REPORT'!B5,MATCH("NO",'STARTUP DRIVE REPORT'!S5,0)),"")} | C4: {=IFERROR(INDEX('STARTUP DRIVE REPORT'!C5,MATCH(B4,'STARTUP DRIVE REPORT'!B5,0)),"")} | D4: {=IFERROR(INDEX('STARTUP DRIVE REPORT'!D5,MATCH(B4,'STARTUP DRIVE REPORT'!B5,0)),"")} | F4: 1 | G4: =IFERROR(INDEX('STARTUP DRIVE REPORT'!B5,MATCH("NO",'STARTUP DRIVE REPORT'!T5,0)),"") | H4: {=IFERROR(INDEX('STARTUP DRIVE REPORT'!C5,MATCH(G4,'STARTUP DRIVE REPORT'!B5,0)),"")} | I4: {=IFERROR(INDEX('STARTUP DRIVE REPORT'!D5,MATCH(G4,'STARTUP DRIVE REPORT'!B5,0)),"")} | K4: 1 | L4: =IF('STARTUP DRIVE REPORT'!AJ5>=1,'STARTUP DRIVE REPORT'!B5,"") | M4: {=IFERROR(INDEX('STARTUP DRIVE REPORT'!C5,MATCH(L4,'STARTUP DRIVE REPORT'!B5,0)),"")} | N4: {=IFERROR(INDEX('STARTUP DRIVE REPORT'!D5,MATCH(L4,'STARTUP DRIVE REPORT'!B5,0)),"")}
A5: =+A4+1 -> 2 | B5: {=IFERROR(INDEX('STARTUP DRIVE REPORT'!B6,MATCH("NO",'STARTUP DRIVE REPORT'!S6,0)),"")} | C5: {=IFERROR(INDEX('STARTUP DRIVE REPORT'!C6,MATCH(B5,'STARTUP DRIVE REPORT'!B6,0)),"")} | D5: {=IFERROR(INDEX('STARTUP DRIVE REPORT'!D6,MATCH(B5,'STARTUP DRIVE REPORT'!B6,0)),"")} | F5: =+F4+1 -> 2 | G5: {=IFERROR(INDEX('STARTUP DRIVE REPORT'!B6,MATCH("NO",'STARTUP DRIVE REPORT'!T6,0)),"")} | H5: {=IFERROR(INDEX('STARTUP DRIVE REPORT'!C6,MATCH(G5,'STARTUP DRIVE REPORT'!B6,0)),"")} | I5: {=IFERROR(INDEX('STARTUP DRIVE REPORT'!D6,MATCH(G5,'STARTUP DRIVE REPORT'!B6,0)),"")} | K5: =+K4+1 -> 2 | L5: =IF('STARTUP DRIVE REPORT'!AJ6>=1,'STARTUP DRIVE REPORT'!B6,"") | M5: {=IFERROR(INDEX('STARTUP DRIVE REPORT'!C6,MATCH(L5,'STARTUP DRIVE REPORT'!B6,0)),"")} | N5: {=IFERROR(INDEX('STARTUP DRIVE REPORT'!D6,MATCH(L5,'STARTUP DRIVE REPORT'!B6,0)),"")}
A6: =+A5+1 -> 3 | B6: {=IFERROR(INDEX('STARTUP DRIVE REPORT'!B7,MATCH("NO",'STARTUP DRIVE REPORT'!S7,0)),"")} | C6: {=IFERROR(INDEX('STARTUP DRIVE REPORT'!C7,MATCH(B6,'STARTUP DRIVE REPORT'!B7,0)),"")} | D6: {=IFERROR(INDEX('STARTUP DRIVE REPORT'!D7,MATCH(B6,'STARTUP DRIVE REPORT'!B7,0)),"")} | F6: =+F5+1 -> 3 | G6: {=IFERROR(INDEX('STARTUP DRIVE REPORT'!B7,MATCH("NO",'STARTUP DRIVE REPORT'!T7,0)),"")} | H6: {=IFERROR(INDEX('STARTUP DRIVE REPORT'!C7,MATCH(G6,'STARTUP DRIVE REPORT'!B7,0)),"")} | I6: {=IFERROR(INDEX('STARTUP DRIVE REPORT'!D7,MATCH(G6,'STARTUP DRIVE REPORT'!B7,0)),"")} | K6: =+K5+1 -> 3 | L6: =IF('STARTUP DRIVE REPORT'!AJ7>=1,'STARTUP DRIVE REPORT'!B7,"") | M6: {=IFERROR(INDEX('STARTUP DRIVE REPORT'!C7,MATCH(L6,'STARTUP DRIVE REPORT'!B7,0)),"")} | N6: {=IFERROR(INDEX('STARTUP DRIVE REPORT'!D7,MATCH(L6,'STARTUP DRIVE REPORT'!B7,0)),"")}
A7: =+A6+1 -> 4 | B7: {=IFERROR(INDEX('STARTUP DRIVE REPORT'!B8,MATCH("NO",'STARTUP DRIVE REPORT'!S8,0)),"")} | C7: {=IFERROR(INDEX('STARTUP DRIVE REPORT'!C8,MATCH(B7,'STARTUP DRIVE REPORT'!B8,0)),"")} | D7: {=IFERROR(INDEX('STARTUP DRIVE REPORT'!D8,MATCH(B7,'STARTUP DRIVE REPORT'!B8,0)),"")} | F7: =+F6+1 -> 4 | G7: {=IFERROR(INDEX('STARTUP DRIVE REPORT'!B8,MATCH("NO",'STARTUP DRIVE REPORT'!T8,0)),"")} | H7: {=IFERROR(INDEX('STARTUP DRIVE REPORT'!C8,MATCH(G7,'STARTUP DRIVE REPORT'!B8,0)),"")} | I7: {=IFERROR(INDEX('STARTUP DRIVE REPORT'!D8,MATCH(G7,'STARTUP DRIVE REPORT'!B8,0)),"")} | K7: =+K6+1 -> 4 | L7: =IF('STARTUP DRIVE REPORT'!AJ8>=1,'STARTUP DRIVE REPORT'!B8,"") | M7: {=IFERROR(INDEX('STARTUP DRIVE REPORT'!C8,MATCH(L7,'STARTUP DRIVE REPORT'!B8,0)),"")} | N7: {=IFERROR(INDEX('STARTUP DRIVE REPORT'!D8,MATCH(L7,'STARTUP DRIVE REPORT'!B8,0)),"")}
A8: =+A7+1 -> 5 | B8: {=IFERROR(INDEX('STARTUP DRIVE REPORT'!B9,MATCH("NO",'STARTUP DRIVE REPORT'!S9,0)),"")} | C8: {=IFERROR(INDEX('STARTUP DRIVE REPORT'!C9,MATCH(B8,'STARTUP DRIVE REPORT'!B9,0)),"")} | D8: {=IFERROR(INDEX('STARTUP DRIVE REPORT'!D9,MATCH(B8,'STARTUP DRIVE REPORT'!B9,0)),"")} | F8: =+F7+1 -> 5 | G8: {=IFERROR(INDEX('STARTUP DRIVE REPORT'!B9,MATCH("NO",'STARTUP DRIVE REPORT'!T9,0)),"")} | H8: {=IFERROR(INDEX('STARTUP DRIVE REPORT'!C9,MATCH(G8,'STARTUP DRIVE REPORT'!B9,0)),"")} | I8: {=IFERROR(INDEX('STARTUP DRIVE REPORT'!D9,MATCH(G8,'STARTUP DRIVE REPORT'!B9,0)),"")} | K8: =+K7+1 -> 5 | L8: =IF('STARTUP DRIVE REPORT'!AJ9>=1,'STARTUP DRIVE REPORT'!B9,"") | M8: {=IFERROR(INDEX('STARTUP DRIVE REPORT'!C9,MATCH(L8,'STARTUP DRIVE REPORT'!B9,0)),"")} | N8: {=IFERROR(INDEX('STARTUP DRIVE REPORT'!D9,MATCH(L8,'STARTUP DRIVE REPORT'!B9,0)),"")}
A9: =+A8+1 -> 6 | B9: {=IFERROR(INDEX('STARTUP DRIVE REPORT'!B10,MATCH("NO",'STARTUP DRIVE REPORT'!S10,0)),"")} | C9: {=IFERROR(INDEX('STARTUP DRIVE REPORT'!C10,MATCH(B9,'STARTUP DRIVE REPORT'!B10,0)),"")} -> 0 | D9: {=IFERROR(INDEX('STARTUP DRIVE REPORT'!D10,MATCH(B9,'STARTUP DRIVE REPORT'!B10,0)),"")} -> 0 | F9: =+F8+1 -> 6 | G9: {=IFERROR(INDEX('STARTUP DRIVE REPORT'!B10,MATCH("NO",'STARTUP DRIVE REPORT'!T10,0)),"")} | H9: {=IFERROR(INDEX('STARTUP DRIVE REPORT'!C10,MATCH(G9,'STARTUP DRIVE REPORT'!B10,0)),"")} -> 0 | I9: {=IFERROR(INDEX('STARTUP DRIVE REPORT'!D10,MATCH(G9,'STARTUP DRIVE REPORT'!B10,0)),"")} -> 0 | K9: =+K8+1 -> 6 | L9: =IF('STARTUP DRIVE REPORT'!AJ10>=1,'STARTUP DRIVE REPORT'!B10,"") | M9: {=IFERROR(INDEX('STARTUP DRIVE REPORT'!C10,MATCH(L9,'STARTUP DRIVE REPORT'!B10,0)),"")} -> 0 | N9: {=IFERROR(INDEX('STARTUP DRIVE REPORT'!D10,MATCH(L9,'STARTUP DRIVE REPORT'!B10,0)),"")} -> 0
A10: =+A9+1 -> 7 | B10: {=IFERROR(INDEX('STARTUP DRIVE REPORT'!B11,MATCH("NO",'STARTUP DRIVE REPORT'!S11,0)),"")} | C10: {=IFERROR(INDEX('STARTUP DRIVE REPORT'!C11,MATCH(B10,'STARTUP DRIVE REPORT'!B11,0)),"")} -> 0 | D10: {=IFERROR(INDEX('STARTUP DRIVE REPORT'!D11,MATCH(B10,'STARTUP DRIVE REPORT'!B11,0)),"")} -> 0 | F10: =+F9+1 -> 7 | G10: {=IFERROR(INDEX('STARTUP DRIVE REPORT'!B11,MATCH("NO",'STARTUP DRIVE REPORT'!T11,0)),"")} | H10: {=IFERROR(INDEX('STARTUP DRIVE REPORT'!C11,MATCH(G10,'STARTUP DRIVE REPORT'!B11,0)),"")} -> 0 | I10: {=IFERROR(INDEX('STARTUP DRIVE REPORT'!D11,MATCH(G10,'STARTUP DRIVE REPORT'!B11,0)),"")} -> 0 | K10: =+K9+1 -> 7 | L10: =IF('STARTUP DRIVE REPORT'!AJ11>=1,'STARTUP DRIVE REPORT'!B11,"") | M10: {=IFERROR(INDEX('STARTUP DRIVE REPORT'!C11,MATCH(L10,'STARTUP DRIVE REPORT'!B11,0)),"")} -> 0 | N10: {=IFERROR(INDEX('STARTUP DRIVE REPORT'!D11,MATCH(L10,'STARTUP DRIVE REPORT'!B11,0)),"")} -> 0
A11: =+A10+1 -> 8 | B11: {=IFERROR(INDEX('STARTUP DRIVE REPORT'!B12,MATCH("NO",'STARTUP DRIVE REPORT'!S12,0)),"")} | C11: {=IFERROR(INDEX('STARTUP DRIVE REPORT'!C12,MATCH(B11,'STARTUP DRIVE REPORT'!B12,0)),"")} -> 0 | D11: {=IFERROR(INDEX('STARTUP DRIVE REPORT'!D12,MATCH(B11,'STARTUP DRIVE REPORT'!B12,0)),"")} -> 0 | F11: =+F10+1 -> 8 | G11: {=IFERROR(INDEX('STARTUP DRIVE REPORT'!B12,MATCH("NO",'STARTUP DRIVE REPORT'!T12,0)),"")} | H11: {=IFERROR(INDEX('STARTUP DRIVE REPORT'!C12,MATCH(G11,'STARTUP DRIVE REPORT'!B12,0)),"")} -> 0 | I11: {=IFERROR(INDEX('STARTUP DRIVE REPORT'!D12,MATCH(G11,'STARTUP DRIVE REPORT'!B12,0)),"")} -> 0 | K11: =+K10+1 -> 8 | L11: =IF('STARTUP DRIVE REPORT'!AJ12>=1,'STARTUP DRIVE REPORT'!B12,"") | M11: {=IFERROR(INDEX('STARTUP DRIVE REPORT'!C12,MATCH(L11,'STARTUP DRIVE REPORT'!B12,0)),"")} -> 0 | N11: {=IFERROR(INDEX('STARTUP DRIVE REPORT'!D12,MATCH(L11,'STARTUP DRIVE REPORT'!B12,0)),"")} -> 0
A12: =+A11+1 -> 9 | B12: {=IFERROR(INDEX('STARTUP DRIVE REPORT'!B13,MATCH("NO",'STARTUP DRIVE REPORT'!S13,0)),"")} | C12: {=IFERROR(INDEX('STARTUP DRIVE REPORT'!C13,MATCH(B12,'STARTUP DRIVE REPORT'!B13,0)),"")} -> 0 | D12: {=IFERROR(INDEX('STARTUP DRIVE REPORT'!D13,MATCH(B12,'STARTUP DRIVE REPORT'!B13,0)),"")} -> 0 | F12: =+F11+1 -> 9 | G12: {=IFERROR(INDEX('STARTUP DRIVE REPORT'!B13,MATCH("NO",'STARTUP DRIVE REPORT'!T13,0)),"")} | H12: {=IFERROR(INDEX('STARTUP DRIVE REPORT'!C13,MATCH(G12,'STARTUP DRIVE REPORT'!B13,0)),"")} -> 0 | I12: {=IFERROR(INDEX('STARTUP DRIVE REPORT'!D13,MATCH(G12,'STARTUP DRIVE REPORT'!B13,0)),"")} -> 0 | K12: =+K11+1 -> 9 | L12: =IF('STARTUP DRIVE REPORT'!AJ13>=1,'STARTUP DRIVE REPORT'!B13,"") | M12: {=IFERROR(INDEX('STARTUP DRIVE REPORT'!C13,MATCH(L12,'STARTUP DRIVE REPORT'!B13,0)),"")} -> 0 | N12: {=IFERROR(INDEX('STARTUP DRIVE REPORT'!D13,MATCH(L12,'STARTUP DRIVE REPORT'!B13,0)),"")} -> 0
A13: =+A12+1 -> 10 | B13: {=IFERROR(INDEX('STARTUP DRIVE REPORT'!B14,MATCH("NO",'STARTUP DRIVE REPORT'!S14,0)),"")} | C13: {=IFERROR(INDEX('STARTUP DRIVE REPORT'!C14,MATCH(B13,'STARTUP DRIVE REPORT'!B14,0)),"")} -> 0 | D13: {=IFERROR(INDEX('STARTUP DRIVE REPORT'!D14,MATCH(B13,'STARTUP DRIVE REPORT'!B14,0)),"")} -> 0 | F13: =+F12+1 -> 10 | G13: {=IFERROR(INDEX('STARTUP DRIVE REPORT'!B14,MATCH("NO",'STARTUP DRIVE REPORT'!T14,0)),"")} | H13: {=IFERROR(INDEX('STARTUP DRIVE REPORT'!C14,MATCH(G13,'STARTUP DRIVE REPORT'!B14,0)),"")} -> 0 | I13: {=IFERROR(INDEX('STARTUP DRIVE REPORT'!D14,MATCH(G13,'STARTUP DRIVE REPORT'!B14,0)),"")} -> 0 | K13: =+K12+1 -> 10 | L13: =IF('STARTUP DRIVE REPORT'!AJ14>=1,'STARTUP DRIVE REPORT'!B14,"") | M13: {=IFERROR(INDEX('STARTUP DRIVE REPORT'!C14,MATCH(L13,'STARTUP DRIVE REPORT'!B14,0)),"")} -> 0 | N13: {=IFERROR(INDEX('STARTUP DRIVE REPORT'!D14,MATCH(L13,'STARTUP DRIVE REPORT'!B14,0)),"")} -> 0
A14: =+A13+1 -> 11 | B14: {=IFERROR(INDEX('STARTUP DRIVE REPORT'!B15,MATCH("NO",'STARTUP DRIVE REPORT'!S15,0)),"")} | C14: {=IFERROR(INDEX('STARTUP DRIVE REPORT'!C15,MATCH(B14,'STARTUP DRIVE REPORT'!B15,0)),"")} -> 0 | D14: {=IFERROR(INDEX('STARTUP DRIVE REPORT'!D15,MATCH(B14,'STARTUP DRIVE REPORT'!B15,0)),"")} -> 0 | F14: =+F13+1 -> 11 | G14: {=IFERROR(INDEX('STARTUP DRIVE REPORT'!B15,MATCH("NO",'STARTUP DRIVE REPORT'!T15,0)),"")} | H14: {=IFERROR(INDEX('STARTUP DRIVE REPORT'!C15,MATCH(G14,'STARTUP DRIVE REPORT'!B15,0)),"")} -> 0 | I14: {=IFERROR(INDEX('STARTUP DRIVE REPORT'!D15,MATCH(G14,'STARTUP DRIVE REPORT'!B15,0)),"")} -> 0 | K14: =+K13+1 -> 11 | L14: =IF('STARTUP DRIVE REPORT'!AJ15>=1,'STARTUP DRIVE REPORT'!B15,"") | M14: {=IFERROR(INDEX('STARTUP DRIVE REPORT'!C15,MATCH(L14,'STARTUP DRIVE REPORT'!B15,0)),"")} -> 0 | N14: {=IFERROR(INDEX('STARTUP DRIVE REPORT'!D15,MATCH(L14,'STARTUP DRIVE REPORT'!B15,0)),"")} -> 0
A15: =+A14+1 -> 12 | B15: {=IFERROR(INDEX('STARTUP DRIVE REPORT'!B16,MATCH("NO",'STARTUP DRIVE REPORT'!S16,0)),"")} | C15: {=IFERROR(INDEX('STARTUP DRIVE REPORT'!C16,MATCH(B15,'STARTUP DRIVE REPORT'!B16,0)),"")} -> 0 | D15: {=IFERROR(INDEX('STARTUP DRIVE REPORT'!D16,MATCH(B15,'STARTUP DRIVE REPORT'!B16,0)),"")} -> 0 | F15: =+F14+1 -> 12 | G15: {=IFERROR(INDEX('STARTUP DRIVE REPORT'!B16,MATCH("NO",'STARTUP DRIVE REPORT'!T16,0)),"")} | H15: {=IFERROR(INDEX('STARTUP DRIVE REPORT'!C16,MATCH(G15,'STARTUP DRIVE REPORT'!B16,0)),"")} -> 0 | I15: {=IFERROR(INDEX('STARTUP DRIVE REPORT'!D16,MATCH(G15,'STARTUP DRIVE REPORT'!B16,0)),"")} -> 0 | K15: =+K14+1 -> 12 | L15: =IF('STARTUP DRIVE REPORT'!AJ16>=1,'STARTUP DRIVE REPORT'!B16,"") | M15: {=IFERROR(INDEX('STARTUP DRIVE REPORT'!C16,MATCH(L15,'STARTUP DRIVE REPORT'!B16,0)),"")} -> 0 | N15: {=IFERROR(INDEX('STARTUP DRIVE REPORT'!D16,MATCH(L15,'STARTUP DRIVE REPORT'!B16,0)),"")} -> 0
A16: =+A15+1 -> 13 | B16: {=IFERROR(INDEX('STARTUP DRIVE REPORT'!B17,MATCH("NO",'STARTUP DRIVE REPORT'!S17,0)),"")} | C16: {=IFERROR(INDEX('STARTUP DRIVE REPORT'!C17,MATCH(B16,'STARTUP DRIVE REPORT'!B17,0)),"")} | D16: {=IFERROR(INDEX('STARTUP DRIVE REPORT'!D17,MATCH(B16,'STARTUP DRIVE REPORT'!B17,0)),"")} | F16: =+F15+1 -> 13 | G16: {=IFERROR(INDEX('STARTUP DRIVE REPORT'!B17,MATCH("NO",'STARTUP DRIVE REPORT'!T17,0)),"")} | H16: {=IFERROR(INDEX('STARTUP DRIVE REPORT'!C17,MATCH(G16,'STARTUP DRIVE REPORT'!B17,0)),"")} | I16: {=IFERROR(INDEX('STARTUP DRIVE REPORT'!D17,MATCH(G16,'STARTUP DRIVE REPORT'!B17,0)),"")} | K16: =+K15+1 -> 13 | L16: =IF('STARTUP DRIVE REPORT'!AJ17>=1,'STARTUP DRIVE REPORT'!B17,"") | M16: {=IFERROR(INDEX('STARTUP DRIVE REPORT'!C17,MATCH(L16,'STARTUP DRIVE REPORT'!B17,0)),"")} | N16: {=IFERROR(INDEX('STARTUP DRIVE REPORT'!D17,MATCH(L16,'STARTUP DRIVE REPORT'!B17,0)),"")}
... A58: =+A57+1 -> 55 | B58: {=IFERROR(INDEX('STARTUP DRIVE REPORT'!B59,MATCH("NO",'STARTUP DRIVE REPORT'!S59,0)),"")} | C58: {=IFERROR(INDEX('STARTUP DRIVE REPORT'!C59,MATCH(B58,'STARTUP DRIVE REPORT'!B59,0)),"")} | D58: {=IFERROR(INDEX('STARTUP DRIVE REPORT'!D59,MATCH(B58,'STARTUP DRIVE REPORT'!B59,0)),"")} | F58: =+F57+1 -> 55 | G58: {=IFERROR(INDEX('STARTUP DRIVE REPORT'!B59,MATCH("NO",'STARTUP DRIVE REPORT'!T59,0)),"")} | H58: {=IFERROR(INDEX('STARTUP DRIVE REPORT'!C59,MATCH(G58,'STARTUP DRIVE REPORT'!B59,0)),"")} | I58: {=IFERROR(INDEX('STARTUP DRIVE REPORT'!D59,MATCH(G58,'STARTUP DRIVE REPORT'!B59,0)),"")} | K58: =+K57+1 -> 55 | L58: =IF('STARTUP DRIVE REPORT'!AJ59>=1,'STARTUP DRIVE REPORT'!B59,"") | M58: {=IFERROR(INDEX('STARTUP DRIVE REPORT'!C59,MATCH(L58,'STARTUP DRIVE REPORT'!B59,0)),"")} | N58: {=IFERROR(INDEX('STARTUP DRIVE REPORT'!D59,MATCH(L58,'STARTUP DRIVE REPORT'!B59,0)),"")}

Sheet LAYOUT
A1: MACHINE LAYOUT
B3: STYLE NO. | D3: =+OB!C2 -> S2554MESS651WV | H3: NO. OF WORKPLACES | I3: =+OB!J85 -> 65
B4: LINE | H4: TARGET/DAY | I4: =+OB!K3 -> 850
B5: INPUT DATE
A7: S.NO | B7: OPERATION | C7: Machine | D7: Workaids | E7: Workstation | G7: S.NO | H7: OPERATION | I7: Machine | J7: Workaids | K7: Workstation
D8: Folders / Attachment | J8: Folders / Attachment
A10: 46 | B10: =IFERROR(INDEX(OB!$B:$B,MATCH(LAYOUT!A10,OB!$A:$A,0)),"") -> VERTICAL TACK WB | C10: =IFERROR(INDEX(OB!$G:$G,MATCH(LAYOUT!A10,OB!$A:$A,0)),"") -> SNLS | D10: =IFERROR(INDEX(OB!$H:$H,MATCH(LAYOUT!A10,OB!$A:$A,0)),"") -> 0 | E10: =IFERROR(INDEX(OB!$J:$J,MATCH(LAYOUT!A10,OB!$A:$A,0)),"") -> 1 | G10: 45 | H10: =IFERROR(INDEX(OB!$B:$B,MATCH(LAYOUT!G10,OB!$A:$A,0)),"") -> ATTACH LABEL*2 | I10: =IFERROR(INDEX(OB!$G:$G,MATCH(LAYOUT!G10,OB!$A:$A,0)),"") -> SNLS | J10: =IFERROR(INDEX(OB!$H:$H,MATCH(LAYOUT!G10,OB!$A:$A,0)),"") -> 0 | K10: =IFERROR(INDEX(OB!$J:$J,MATCH(LAYOUT!G10,OB!$A:$A,0)),"") -> 1
A12: 47 | B12: =IFERROR(INDEX(OB!$B:$B,MATCH(LAYOUT!A12,OB!$A:$A,0)),"") -> CLOSE WAISTBAND | C12: =IFERROR(INDEX(OB!$G:$G,MATCH(LAYOUT!A12,OB!$A:$A,0)),"") -> KANSAI | D12: =IFERROR(INDEX(OB!$H:$H,MATCH(LAYOUT!A12,OB!$A:$A,0)),"") -> 0 | E12: =IFERROR(INDEX(OB!$J:$J,MATCH(LAYOUT!A12,OB!$A:$A,0)),"") -> 1 | G12: 44 | H12: =IFERROR(INDEX(OB!$B:$B,MATCH(LAYOUT!G12,OB!$A:$A,0)),"") -> ATTACH ELASTIC TO WB | I12: =IFERROR(INDEX(OB!$G:$G,MATCH(LAYOUT!G12,OB!$A:$A,0)),"") -> FL3T-CB | J12: =IFERROR(INDEX(OB!$H:$H,MATCH(LAYOUT!G12,OB!$A:$A,0)),"") -> 0 | K12: =IFERROR(INDEX(OB!$J:$J,MATCH(LAYOUT!G12,OB!$A:$A,0)),"") -> 1
A14: 48 | B14: =IFERROR(INDEX(OB!$B:$B,MATCH(LAYOUT!A14,OB!$A:$A,0)),"") -> REMOVE VERTICAL TACK | C14: =IFERROR(INDEX(OB!$G:$G,MATCH(LAYOUT!A14,OB!$A:$A,0)),"") -> TABLE | D14: =IFERROR(INDEX(OB!$H:$H,MATCH(LAYOUT!A14,OB!$A:$A,0)),"") -> 0 | E14: =IFERROR(INDEX(OB!$J:$J,MATCH(LAYOUT!A14,OB!$A:$A,0)),"") -> 1 | G14: 43 | H14: =IFERROR(INDEX(OB!$B:$B,MATCH(LAYOUT!G14,OB!$A:$A,0)),"") -> MAKE ELASTIC READY | I14: =IFERROR(INDEX(OB!$G:$G,MATCH(LAYOUT!G14,OB!$A:$A,0)),"") -> PREP | J14: =IFERROR(INDEX(OB!$H:$H,MATCH(LAYOUT!G14,OB!$A:$A,0)),"") -> 0 | K14: =IFERROR(INDEX(OB!$J:$J,MATCH(LAYOUT!G14,OB!$A:$A,0)),"") -> 1
A16: 49 | B16: =IFERROR(INDEX(OB!$B:$B,MATCH(LAYOUT!A16,OB!$A:$A,0)),"") -> CREASE BOTTOM FOR HEM | C16: =IFERROR(INDEX(OB!$G:$G,MATCH(LAYOUT!A16,OB!$A:$A,0)),"") -> IRON TABLE | D16: =IFERROR(INDEX(OB!$H:$H,MATCH(LAYOUT!A16,OB!$A:$A,0)),"") -> 0 | E16: =IFERROR(INDEX(OB!$J:$J,MATCH(LAYOUT!A16,OB!$A:$A,0)),"") -> 1 | G16: 42 | H16: =IFERROR(INDEX(OB!$B:$B,MATCH(LAYOUT!G16,OB!$A:$A,0)),"") -> ATTACH WB TO BODY | I16: =IFERROR(INDEX(OB!$G:$G,MATCH(LAYOUT!G16,OB!$A:$A,0)),"") -> OL4T | J16: =IFERROR(INDEX(OB!$H:$H,MATCH(LAYOUT!G16,OB!$A:$A,0)),"") -> 0 | K16: =IFERROR(INDEX(OB!$J:$J,MATCH(LAYOUT!G16,OB!$A:$A,0)),"") -> 1
A18: 50 | B18: =IFERROR(INDEX(OB!$B:$B,MATCH(LAYOUT!A18,OB!$A:$A,0)),"") -> FOLD & TACK BOTTOM WITH ZIPPER FOR HEM | C18: =IFERROR(INDEX(OB!$G:$G,MATCH(LAYOUT!A18,OB!$A:$A,0)),"") -> SNLS | D18: =IFERROR(INDEX(OB!$H:$H,MATCH(LAYOUT!A18,OB!$A:$A,0)),"") -> 0 | E18: =IFERROR(INDEX(OB!$J:$J,MATCH(LAYOUT!A18,OB!$A:$A,0)),"") -> 1 | G18: 41 | H18: =IFERROR(INDEX(OB!$B:$B,MATCH(LAYOUT!G18,OB!$A:$A,0)),"") -> TOP STITCH BUTTON HOLE SIDE | I18: =IFERROR(INDEX(OB!$G:$G,MATCH(LAYOUT!G18,OB!$A:$A,0)),"") -> SNLS | J18: =IFERROR(INDEX(OB!$H:$H,MATCH(LAYOUT!G18,OB!$A:$A,0)),"") -> 0 | K18: =IFERROR(INDEX(OB!$J:$J,MATCH(LAYOUT!G18,OB!$A:$A,0)),"") -> 2
A20: 51 | B20: =IFERROR(INDEX(OB!$B:$B,MATCH(LAYOUT!A20,OB!$A:$A,0)),"") -> BOTTOM HEM | C20: =IFERROR(INDEX(OB!$G:$G,MATCH(LAYOUT!A20,OB!$A:$A,0)),"") -> SNLS | D20: =IFERROR(INDEX(OB!$H:$H,MATCH(LAYOUT!A20,OB!$A:$A,0)),"") -> 0 | E20: =IFERROR(INDEX(OB!$J:$J,MATCH(LAYOUT!A20,OB!$A:$A,0)),"") -> 1 | G20: 40 | H20: =IFERROR(INDEX(OB!$B:$B,MATCH(LAYOUT!G20,OB!$A:$A,0)),"") -> CREASE WB JOININGS TO SPLIT | I20: =IFERROR(INDEX(OB!$G:$G,MATCH(LAYOUT!G20,OB!$A:$A,0)),"") -> IRON TABLE | J20: =IFERROR(INDEX(OB!$H:$H,MATCH(LAYOUT!G20,OB!$A:$A,0)),"") -> 0 | K20: =IFERROR(INDEX(OB!$J:$J,MATCH(LAYOUT!G20,OB!$A:$A,0)),"") -> 1
A22: 52 | B22: =IFERROR(INDEX(OB!$B:$B,MATCH(LAYOUT!A22,OB!$A:$A,0)),"") -> BARTACK FRONT WB*4 | C22: =IFERROR(INDEX(OB!$G:$G,MATCH(LAYOUT!A22,OB!$A:$A,0)),"") -> BRTK | D22: =IFERROR(INDEX(OB!$H:$H,MATCH(LAYOUT!A22,OB!$A:$A,0)),"") -> 0 | E22: =IFERROR(INDEX(OB!$J:$J,MATCH(LAYOUT!A22,OB!$A:$A,0)),"") -> 1 | G22: 39 | H22: =IFERROR(INDEX(OB!$B:$B,MATCH(LAYOUT!G22,OB!$A:$A,0)),"") -> MARK & TACK WB FOR BUTTON HOLE | I22: =IFERROR(INDEX(OB!$G:$G,MATCH(LAYOUT!G22,OB!$A:$A,0)),"") -> SNLS | J22: =IFERROR(INDEX(OB!$H:$H,MATCH(LAYOUT!G22,OB!$A:$A,0)),"") -> 0 | K22: =IFERROR(INDEX(OB!$J:$J,MATCH(LAYOUT!G22,OB!$A:$A,0)),"") -> 2
A24: 53 | B24: =IFERROR(INDEX(OB!$B:$B,MATCH(LAYOUT!A24,OB!$A:$A,0)),"") -> INSERT DRAWCORD | C24: =IFERROR(INDEX(OB!$G:$G,MATCH(LAYOUT!A24,OB!$A:$A,0)),"") -> TABLE | D24: =IFERROR(INDEX(OB!$H:$H,MATCH(LAYOUT!A24,OB!$A:$A,0)),"") -> 0 | E24: =IFERROR(INDEX(OB!$J:$J,MATCH(LAYOUT!A24,OB!$A:$A,0)),"") -> 1 | G24: 38 | H24: =IFERROR(INDEX(OB!$B:$B,MATCH(LAYOUT!G24,OB!$A:$A,0)),"") -> MARK FOR HIGH LOW | I24: =IFERROR(INDEX(OB!$G:$G,MATCH(LAYOUT!G24,OB!$A:$A,0)),"") -> TABLE | J24: =IFERROR(INDEX(OB!$H:$H,MATCH(LAYOUT!G24,OB!$A:$A,0)),"") -> 0 | K24: =IFERROR(INDEX(OB!$J:$J,MATCH(LAYOUT!G24,OB!$A:$A,0)),"") -> 1
A26: 54 | B26: =IFERROR(INDEX(OB!$B:$B,MATCH(LAYOUT!A26,OB!$A:$A,0)),"") -> BARTACK WB*4, CROTCH*1 & ZIPPER*2 | C26: =IFERROR(INDEX(OB!$G:$G,MATCH(LAYOUT!A26,OB!$A:$A,0)),"") -> BRTK | D26: =IFERROR(INDEX(OB!$H:$H,MATCH(LAYOUT!A26,OB!$A:$A,0)),"") -> 0 | E26: =IFERROR(INDEX(OB!$J:$J,MATCH(LAYOUT!A26,OB!$A:$A,0)),"") -> 1 | G26: 37 | H26: =IFERROR(INDEX(OB!$B:$B,MATCH(LAYOUT!G26,OB!$A:$A,0)),"") -> CREASE SIDE SEAM | I26: =IFERROR(INDEX(OB!$G:$G,MATCH(LAYOUT!G26,OB!$A:$A,0)),"") -> IRON TABLE | J26: =IFERROR(INDEX(OB!$H:$H,MATCH(LAYOUT!G26,OB!$A:$A,0)),"") -> 0 | K26: =IFERROR(INDEX(OB!$J:$J,MATCH(LAYOUT!G26,OB!$A:$A,0)),"") -> 1
A28: 55 | B28: =IFERROR(INDEX(OB!$B:$B,MATCH(LAYOUT!A28,OB!$A:$A,0)),"") -> TRIM AND INLINE CHECK | C28: =IFERROR(INDEX(OB!$G:$G,MATCH(LAYOUT!A28,OB!$A:$A,0)),"") -> TABLE | D28: =IFERROR(INDEX(OB!$H:$H,MATCH(LAYOUT!A28,OB!$A:$A,0)),"") -> 0 | E28: =IFERROR(INDEX(OB!$J:$J,MATCH(LAYOUT!A28,OB!$A:$A,0)),"") -> 1 | G28: 36 | H28: =IFERROR(INDEX(OB!$B:$B,MATCH(LAYOUT!G28,OB!$A:$A,0)),"") -> SIDE SEAM | I28: =IFERROR(INDEX(OB!$G:$G,MATCH(LAYOUT!G28,OB!$A:$A,0)),"") -> OL4T | J28: =IFERROR(INDEX(OB!$H:$H,MATCH(LAYOUT!G28,OB!$A:$A,0)),"") -> 0 | K28: =IFERROR(INDEX(OB!$J:$J,MATCH(LAYOUT!G28,OB!$A:$A,0)),"") -> 2
A30: 56 | B30: =IFERROR(INDEX(OB!$B:$B,MATCH(LAYOUT!A30,OB!$A:$A,0)),"") -> BUFFER | C30: =IFERROR(INDEX(OB!$G:$G,MATCH(LAYOUT!A30,OB!$A:$A,0)),"") -> 0 | D30: =IFERROR(INDEX(OB!$H:$H,MATCH(LAYOUT!A30,OB!$A:$A,0)),"") -> 0 | E30: =IFERROR(INDEX(OB!$J:$J,MATCH(LAYOUT!A30,OB!$A:$A,0)),"") -> 12 | G30: 35 | H30: =IFERROR(INDEX(OB!$B:$B,MATCH(LAYOUT!G30,OB!$A:$A,0)),"") -> TACK FOR SIDE SEAM | I30: =IFERROR(INDEX(OB!$G:$G,MATCH(LAYOUT!G30,OB!$A:$A,0)),"") -> SNLS | J30: =IFERROR(INDEX(OB!$H:$H,MATCH(LAYOUT!G30,OB!$A:$A,0)),"") -> 0 | K30: =IFERROR(INDEX(OB!$J:$J,MATCH(LAYOUT!G30,OB!$A:$A,0)),"") -> 2
